Workbook

Sheet PRICING PLANTILLA
C1: Herramienta Pricing | P1: Código: | Q1: FO - FI - 03
P2: Versión: | Q2: 1
P3: Fecha de emisión: | Q3: 44171
B5: *Todos los meses cambiar el # de personas actuales - Ojo! | E5: Comisión Venta | F5: =I5*C17 -> 107310 | G5: Jugar con Gross Margin | H5: PV COP | I5: =+((C12+C8+C10)/(1-F6-'Parámetros'!L8*C18))+'Parámetros'!L9*C18 -> 1073100
E6: Gross Margin | F6: 0.5 | H6: PV USD | I6: =I5/'Parámetros'!L3 -> 302.28169
B7: Resumen | E7: Imp. Renta | F7: =(I5-F5-C12)*'Parámetros'!L6 -> 0 | H7: Horas | I7: 180
B8: Costo Equipo | C8: =G20 -> 0 | E8: ICA | F8: =I5*'Parámetros'!L5 -> 7404.39 | H8: USD/Horas | I8: =I6/I7 -> 1.6793427
B9: Costo + Gasto Fijo | C9: =C11+C12+C10 -> 536550 | E9: NET Margin | F9: =(I5-C13-F8-F5-C18*'Parámetros'!L8*I5)/I5 -> 0.3931
B10: Computador Herramientas Trabajo | C10: =6000000/30*F20*1.095 -> 536550
B11: - ROP Gasto | C11: =H20*AVERAGE('Parámetros'!G5:G6)*IF(C19=1,15%,1) -> 0
B12: - ROP Costo Fijo | C12: =H20*AVERAGE('Parámetros'!H5:H6)*IF(C19=1,15%,1) -> 0 | E12: Comisión Venta | F12: =I12*C17 -> 60077.259 | G12: Jugar con Net Margin | H12: PV COP | I12: =+(C13/(1-C17-F13-'Parámetros'!L5-'Parámetros'!L8*C18))+('Parámetros'!L9*C18) -> 600772.59
B13: T. C + G Equipo | C13: =C8+C9 -> 536550 | E13: NET Margin | F13: 0 | H13: PV USD | I13: =I12/'Parámetros'!L3 -> 169.23172
E14: Imp. Renta | F14: =(I12-F13-C12)*'Parámetros'!L6 -> 0 | H14: Horas | I14: 180
B15: Comisión Bruta | C15: 0.1 | E15: ICA | F15: =I12*'Parámetros'!L5 -> 4145.3309 | H15: USD/Horas | I15: =I13/I14 -> 0.9401762
B16: ¿Tipo de contrato vendedor? | C16: Prestación de Servicios
B17: Comisión Total | C17: =IF('PRICING PLANTILLA'!C16="Nómina",C15*1.38522,C15) -> 0.1
B18: ¿Pago con TC? | C18: 0 | F18: Proyectado
B19: ¿Staff Augmentation? | C19: 0
F20: =SUM(F22:F34) -> 2.45 | G20: =SUM(G22:G34) -> 0 | H20: =SUM(H22:H34) -> 0
B21: Equipo | C21: Salario Base | D21: Tipo Contrato | E21: Costo Total | F21: Dedicación | G21: Costo Final | H21: % Tiempo Equipo | I21: % Costo Equipo | J21: PV (USD)
B22: Software Developer Junior Nivel 1 | C22: =iferror(VLOOKUP(B22,'Parámetros'!A$1:B120,2, FALSE),"") | D22: Nómina | E22: =+iferror(IF(D22="Nómina",C22*1.38352,C22),"") -> 0 | F22: 1 | G22: =E22*F22 -> 0 | H22: =G22/(AVERAGE('Parámetros'!$F$5:$F$6)+$G$20) -> 0 | I22: =G22/$G$20 -> #DIV/0! | J22: =$I$13*I22 -> #DIV/0!
B23: Project Analyst Junior | C23: =iferror(VLOOKUP(B23,'Parámetros'!A$1:B121,2, FALSE),"") | D23: Nómina | E23: =+iferror(IF(D23="Nómina",C23*1.38352,C23),"") -> 0 | F23: 0.25 | G23: =E23*F23 -> 0 | H23: =G23/(AVERAGE('Parámetros'!$F$5:$F$6)+$G$20) -> 0 | I23: =G23/$G$20 -> #DIV/0! | J23: =$I$13*I23 -> #DIV/0!
B24: Diseñador Junior | C24: =iferror(VLOOKUP(B24,'Parámetros'!A$1:B122,2, FALSE),"") | D24: Nómina | E24: =+iferror(IF(D24="Nómina",C24*1.38352,C24),"") -> 0 | F24: 0.2 | G24: =E24*F24 -> 0 | H24: =G24/(AVERAGE('Parámetros'!$F$5:$F$6)+$G$20) -> 0 | I24: =G24/$G$20 -> #DIV/0! | J24: =$I$13*I24 -> #DIV/0!
C25: =iferror(VLOOKUP(B25,'Parámetros'!A$1:B123,2, FALSE),"") | D25: Nómina | E25: =+iferror(IF(D25="Nómina",C25*1.38352,C25),"") -> 0 | F25: 1 | G25: =E25*F25 -> 0 | H25: =G25/(AVERAGE('Parámetros'!$F$5:$F$6)+$G$20) -> 0 | I25: =G25/$G$20 -> #DIV/0! | J25: =$I$13*I25 -> #DIV/0!
C26: =iferror(VLOOKUP(B26,'Parámetros'!A$1:B124,2, FALSE),"") | E26: =+iferror(IF(D26="Nómina",C26*1.38352,C26),"") | G26: =E26*F26 -> 0 | H26: =G26/AVERAGE('Parámetros'!$F$5:$F$6) -> 0 | I26: =G26/$G$20 -> #DIV/0! | J26: =$I$13*I26 -> #DIV/0!
C27: =iferror(VLOOKUP(B27,'Parámetros'!A$1:B126,2, FALSE),"") | E27: =+iferror(IF(D27="Nómina",C27*1.38352,C27),"") | G27: =E27*F27 -> 0 | I27: =G27/$G$20 -> #DIV/0! | J27: =$I$13*I27 -> #DIV/0!
C28: =iferror(VLOOKUP(B28,'Parámetros'!A$1:B126,2, FALSE),"") | E28: =+iferror(IF(D28="Nómina",C28*1.38352,C28),"") | G28: =E28*F28 -> 0 | I28: =G28/$G$20 -> #DIV/0! | J28: =$I$13*I28 -> #DIV/0!
C29: =iferror(VLOOKUP(B29,'Parámetros'!A$1:B126,2, FALSE),"") | D29: Nómina | E29: =+iferror(IF(D29="Nómina",C29*1.38352,C29),"") -> 0 | G29: =E29*F29 -> 0 | I29: =G29/$G$20 -> #DIV/0! | J29: =$I$13*I29 -> #DIV/0!
C30: =iferror(VLOOKUP(B30,'Parámetros'!A$1:B126,2, FALSE),"") | E30: =+iferror(IF(D30="Nómina",C30*1.38352,C30),"") | G30: =E30*F30 -> 0 | I30: =G30/$G$20 -> #DIV/0! | J30: =$I$13*I30 -> #DIV/0!
C31: =iferror(VLOOKUP(B31,'Parámetros'!A$1:B126,2, FALSE),"") | E31: =+iferror(IF(D31="Nómina",C31*1.38352,C31),"") | G31: =E31*F31 -> 0 | I31: =G31/$G$20 -> #DIV/0! | J31: =$I$13*I31 -> #DIV/0!
C32: =iferror(VLOOKUP(B32,'Parámetros'!A$1:B126,2, FALSE),"") | E32: =+iferror(IF(D32="Nómina",C32*1.38352,C32),"") | G32: =E32*F32 -> 0 | I32: =G32/$G$20 -> #DIV/0! | J32: =$I$13*I32 -> #DIV/0!
C33: =iferror(VLOOKUP(B33,'Parámetros'!A$1:B126,2, FALSE),"") | E33: =+iferror(IF(D33="Nómina",C33*1.38352,C33),"") | G33: =E33*F33 -> 0 | I33: =G33/$G$20 -> #DIV/0! | J33: =$I$13*I33 -> #DIV/0!
C34: =iferror(VLOOKUP(B34,'Parámetros'!A$1:B126,2, FALSE),"") | D34: Nómina | E34: =+iferror(IF(D34="Nómina",C34*1.38352,C34),"") -> 0 | G34: =E34*F34 -> 0 | I34: =G34/$G$20 -> #DIV/0! | J34: =$I$13*I34 -> #DIV/0!
B36: COP | K36: USD
B37: Pricing | C37: Gross Margin | K37: Pricing | L37: Gross Margin
B39: Perfil | C39: Dedicación | D39: Capacidad Horas | E39: Precio COP | F39: Precio x Hora | K39: Perfil | L39: Dedicación | M39: Capacidad Horas | N39: Precio USD | O39: Precio x Hora
B40: =B22 -> Software Developer Junior Nivel 1 | C40: =F22 -> 1 | D40: =C40*180 -> 180 | E40: =IF(C$37="Gross Margin",I22*$I$5,IF(C$37="Net Margin",I22*$I$12,"Error")) -> #DIV/0! | F40: =iferror(E40/D40,0) -> 0 | K40: =B40 -> Software Developer Junior Nivel 1 | L40: =C40 -> 1 | M40: =D40 -> 180 | N40: =E40/'Parámetros'!$L$3 -> #DIV/0! | O40: =iferror(N40/M40,0) -> 0
B41: =B23 -> Project Analyst Junior | C41: =F23 -> 0.25 | D41: =C41*180 -> 45 | E41: =IF(C$37="Gross Margin",I23*$I$5,IF(C$37="Net Margin",I23*$I$12,"Error")) -> #DIV/0! | F41: =iferror(E41/D41,0) -> 0 | K41: =B41 -> Project Analyst Junior | L41: =C41 -> 0.25 | M41: =D41 -> 45 | N41: =E41/'Parámetros'!$L$3 -> #DIV/0! | O41: =iferror(N41/M41,0) -> 0
B42: =B24 -> Diseñador Junior | C42: =F24 -> 0.2 | D42: =C42*180 -> 36 | E42: =IF(C$37="Gross Margin",I24*$I$5,IF(C$37="Net Margin",I24*$I$12,"Error")) -> #DIV/0! | F42: =iferror(E42/D42,0) -> 0 | K42: =B42 -> Diseñador Junior | L42: =C42 -> 0.2 | M42: =D42 -> 36 | N42: =E42/'Parámetros'!$L$3 -> #DIV/0! | O42: =iferror(N42/M42,0) -> 0
B43: =B25 | C43: =F25 -> 1 | D43: =C43*180 -> 180 | E43: =IF(C$37="Gross Margin",I25*$I$5,IF(C$37="Net Margin",I25*$I$12,"Error")) -> #DIV/0! | F43: =iferror(E43/D43,0) -> 0 | K43: =B43 | L43: =C43 -> 1 | M43: =D43 -> 180 | N43: =E43/'Parámetros'!$L$3 -> #DIV/0! | O43: =iferror(N43/M43,0) -> 0
B44: =B26 | C44: =F26 | D44: =C44*180 -> 0 | E44: =IF(C$37="Gross Margin",I26*$I$5,IF(C$37="Net Margin",I26*$I$12,"Error")) -> #DIV/0! | F44: =iferror(E44/D44,0) -> 0 | K44: =B44 | L44: =C44 | M44: =D44 -> 0 | N44: =E44/'Parámetros'!$L$3 -> #DIV/0! | O44: =iferror(N44/M44,0) -> 0
B45: =B27 | C45: =F27 | D45: =C45*180 -> 0 | E45: =IF(C$37="Gross Margin",I27*$I$5,IF(C$37="Net Margin",I27*$I$12,"Error")) -> #DIV/0! | F45: =iferror(E45/D45,0) -> 0 | K45: =B45 | L45: =C45 | M45: =D45 -> 0 | N45: =E45/'Parámetros'!$L$3 -> #DIV/0! | O45: =iferror(N45/M45,0) -> 0
B46: =B28 | C46: =F28 | D46: =C46*180 -> 0 | E46: =IF(C$37="Gross Margin",I28*$I$5,IF(C$37="Net Margin",I28*$I$12,"Error")) -> #DIV/0! | F46: =iferror(E46/D46,0) -> 0 | K46: =B46 | L46: =C46 | M46: =D46 -> 0 | N46: =E46/'Parámetros'!$L$3 -> #DIV/0! | O46: =iferror(N46/M46,0) -> 0
B47: =B29 | C47: =F29 | D47: =C47*180 -> 0 | E47: =IF(C$37="Gross Margin",I29*$I$5,IF(C$37="Net Margin",I29*$I$12,"Error")) -> #DIV/0! | F47: =iferror(E47/D47,0) -> 0 | K47: =B47 | L47: =C47 | M47: =D47 -> 0 | N47: =E47/'Parámetros'!$L$3 -> #DIV/0! | O47: =iferror(N47/M47,0) -> 0
B48: =B30 | C48: =F30 | D48: =C48*180 -> 0 | E48: =IF(C$37="Gross Margin",I30*$I$5,IF(C$37="Net Margin",I30*$I$12,"Error")) -> #DIV/0! | F48: =iferror(E48/D48,0) -> 0 | K48: =B48 | L48: =C48 | M48: =D48 -> 0 | N48: =E48/'Parámetros'!$L$3 -> #DIV/0! | O48: =iferror(N48/M48,0) -> 0
C49: Total | D49: =SUM(D40:D45) -> 441 | E49: =SUM(E40:E48) -> #DIV/0! | F49: =E49/D49 -> #DIV/0! | L49: Total | M49: =SUM(M40:M45) -> 441 | N49: =SUM(N40:N45) -> #DIV/0! | O49: =N49/M49 -> #DIV/0!

Sheet Parámetros
A1: Perfil | B1: Salario | C1: Costo Empresa
A2: Forward Deployed Product manager | B2: 5000000 | C2: =B2*1.38 -> 6900000 | K2: Parámetros
A3: DevOps Engineer Senior | B3: 8000000 | C3: =B3*1.38 -> 11040000 | K3: TRM | L3: 3550 | O3: =IFERROR(__xludf.DUMMYFUNCTION("GOOGLEFINANCE(""currency:USDCOP"",""price"",(TODAY()-20)-20,60)"),"Date") -> Date | P3: =IFERROR(__xludf.DUMMYFUNCTION("""COMPUTED_VALUE"""),"Close") -> Close
A4: Forward Deployed Enginnier | B4: 7000000 | C4: =B4*1.38 -> 9660000 | F4: Bolsa | G4: Gastos Fijos | H4: Costos | K4: # Proyectos x Pod | L4: 1 | O4: =IFERROR(__xludf.DUMMYFUNCTION("""COMPUTED_VALUE"""),46061.99861111111) -> 46061.999 | P4: =IFERROR(__xludf.DUMMYFUNCTION("""COMPUTED_VALUE"""),3657.237) -> 3657.237
A5: Forward Deployed Pruduct experience | B5: 5000000 | C5: =B5*1.38 -> 6900000 | E5: Diciembre | F5: 322239393 | G5: 219207359 | H5: =21584031+12296884 -> 33880915 | K5: ICA | L5: =6.9/1000 -> 0.0069 | O5: =IFERROR(__xludf.DUMMYFUNCTION("""COMPUTED_VALUE"""),46062.99861111111) -> 46062.999 | P5: =IFERROR(__xludf.DUMMYFUNCTION("""COMPUTED_VALUE"""),3668.26) -> 3668.26
A6: Tech Leald Orchestaror | B6: 10000000 | C6: =B6*1.38 -> 13800000 | E6: Enero | F6: 345674120 | G6: =153922294-23803671 -> 130118623 | H6: =18000124+17676944 -> 35677068 | K6: Renta | L6: 0 | O6: =IFERROR(__xludf.DUMMYFUNCTION("""COMPUTED_VALUE"""),46063.99861111111) -> 46063.999 | P6: =IFERROR(__xludf.DUMMYFUNCTION("""COMPUTED_VALUE"""),3663.72) -> 3663.72 | V6: 2022-Apr | W6: 4055.2343
A7: QA Engineer Semi Senior | B7: 3000000 | C7: =B7*1.38 -> 4140000 | E7: Febrero | F7: 339294343 | G7: =163844091-30578849 -> 133265242 | H7: =17853308+7452783 -> 25306091 | K7: Face Value Comisión | L7: 0.1 | O7: =IFERROR(__xludf.DUMMYFUNCTION("""COMPUTED_VALUE"""),46064.99861111111) -> 46064.999 | P7: =IFERROR(__xludf.DUMMYFUNCTION("""COMPUTED_VALUE"""),3669.53) -> 3669.53 | V7: 2022-May | W7: 4377.3221
A8: Software Developer Semi Senior Nivel 1 | B8: 5000000 | C8: =B8*1.38 -> 6900000 | E8: Marzo | F8: 333648543 | G8: =154935476-9678137 -> 145257339 | H8: =7027325+20727068 -> 27754393 | K8: Comisión TC | L8: 0.029 | O8: =IFERROR(__xludf.DUMMYFUNCTION("""COMPUTED_VALUE"""),46065.99861111111) -> 46065.999 | P8: =IFERROR(__xludf.DUMMYFUNCTION("""COMPUTED_VALUE"""),3668.0) -> 3668 | W8: #DIV/0!
A9: Software Developer Semi Senior Nivel 2 | B9: 7000000 | C9: =B9*1.38 -> 9660000 | E9: Abril | F9: 324919373 | G9: =179893216-43368730 -> 136524486 | H9: =16643013-1443598+7452783 -> 22652198 | K9: Comisión 2 | L9: 0.3 | O9: =IFERROR(__xludf.DUMMYFUNCTION("""COMPUTED_VALUE"""),46066.99861111111) -> 46066.999 | P9: =IFERROR(__xludf.DUMMYFUNCTION("""COMPUTED_VALUE"""),3664.65) -> 3664.65 | V9: Grand Total | W9: 4242.253
A10: Software Developer Senior Nivel 1 | B10: 9000000 | C10: =B10*1.38 -> 12420000 | E10: Mayo | F10: 354200345 | G10: =175297648-34194521 -> 141103127 | H10: =23598164-1138139+7452783 -> 29912808 | O10: =IFERROR(__xludf.DUMMYFUNCTION("""COMPUTED_VALUE"""),46067.99861111111) -> 46067.999 | P10: =IFERROR(__xludf.DUMMYFUNCTION("""COMPUTED_VALUE"""),3618.33) -> 3618.33
A11: Software Developer Senior Nivel 2 | B11: 12000000 | C11: =B11*1.38 -> 16560000 | O11: =IFERROR(__xludf.DUMMYFUNCTION("""COMPUTED_VALUE"""),46069.99861111111) -> 46069.999 | P11: =IFERROR(__xludf.DUMMYFUNCTION("""COMPUTED_VALUE"""),3656.07) -> 3656.07
A12: Forward Deployed Enginnier - On Site | B12: 9000000 | C12: =B12*1.38 -> 12420000 | O12: =IFERROR(__xludf.DUMMYFUNCTION("""COMPUTED_VALUE"""),46070.99861111111) -> 46070.999 | P12: =IFERROR(__xludf.DUMMYFUNCTION("""COMPUTED_VALUE"""),3663.75) -> 3663.75
O13: =IFERROR(__xludf.DUMMYFUNCTION("""COMPUTED_VALUE"""),46071.99861111111) -> 46071.999 | P13: =IFERROR(__xludf.DUMMYFUNCTION("""COMPUTED_VALUE"""),3678.28) -> 3678.28
O14: =IFERROR(__xludf.DUMMYFUNCTION("""COMPUTED_VALUE"""),46072.99861111111) -> 46072.999 | P14: =IFERROR(__xludf.DUMMYFUNCTION("""COMPUTED_VALUE"""),3698.79) -> 3698.79
O15: =IFERROR(__xludf.DUMMYFUNCTION("""COMPUTED_VALUE"""),46073.99861111111) -> 46073.999 | P15: =IFERROR(__xludf.DUMMYFUNCTION("""COMPUTED_VALUE"""),3706.17) -> 3706.17
O16: =IFERROR(__xludf.DUMMYFUNCTION("""COMPUTED_VALUE"""),46074.99861111111) -> 46074.999 | P16: =IFERROR(__xludf.DUMMYFUNCTION("""COMPUTED_VALUE"""),3647.348) -> 3647.348
O17: =IFERROR(__xludf.DUMMYFUNCTION("""COMPUTED_VALUE"""),46075.99861111111) -> 46075.999 | P17: =IFERROR(__xludf.DUMMYFUNCTION("""COMPUTED_VALUE"""),3647.348) -> 3647.348
O18: =IFERROR(__xludf.DUMMYFUNCTION("""COMPUTED_VALUE"""),46076.99861111111) -> 46076.999 | P18: =IFERROR(__xludf.DUMMYFUNCTION("""COMPUTED_VALUE"""),3691.94) -> 3691.94
O19: =IFERROR(__xludf.DUMMYFUNCTION("""COMPUTED_VALUE"""),46077.99861111111) -> 46077.999 | P19: =IFERROR(__xludf.DUMMYFUNCTION("""COMPUTED_VALUE"""),3710.11) -> 3710.11
O20: =IFERROR(__xludf.DUMMYFUNCTION("""COMPUTED_VALUE"""),46078.99861111111) -> 46078.999 | P20: =IFERROR(__xludf.DUMMYFUNCTION("""COMPUTED_VALUE"""),3697.69) -> 3697.69
O21: =IFERROR(__xludf.DUMMYFUNCTION("""COMPUTED_VALUE"""),46079.99861111111) -> 46079.999 | P21: =IFERROR(__xludf.DUMMYFUNCTION("""COMPUTED_VALUE"""),3764.29) -> 3764.29
O22: =IFERROR(__xludf.DUMMYFUNCTION("""COMPUTED_VALUE"""),46080.99861111111) -> 46080.999 | P22: =IFERROR(__xludf.DUMMYFUNCTION("""COMPUTED_VALUE"""),3759.93) -> 3759.93
O23: =IFERROR(__xludf.DUMMYFUNCTION("""COMPUTED_VALUE"""),46081.99861111111) -> 46081.999 | P23: =IFERROR(__xludf.DUMMYFUNCTION("""COMPUTED_VALUE"""),3716.57) -> 3716.57
O24: =IFERROR(__xludf.DUMMYFUNCTION("""COMPUTED_VALUE"""),46082.99861111111) -> 46082.999 | P24: =IFERROR(__xludf.DUMMYFUNCTION("""COMPUTED_VALUE"""),3716.57) -> 3716.57
O25: =IFERROR(__xludf.DUMMYFUNCTION("""COMPUTED_VALUE"""),46083.99861111111) -> 46083.999 | P25: =IFERROR(__xludf.DUMMYFUNCTION("""COMPUTED_VALUE"""),3770.8) -> 3770.8
O26: =IFERROR(__xludf.DUMMYFUNCTION("""COMPUTED_VALUE"""),46084.99861111111) -> 46084.999 | P26: =IFERROR(__xludf.DUMMYFUNCTION("""COMPUTED_VALUE"""),3801.26) -> 3801.26
O27: =IFERROR(__xludf.DUMMYFUNCTION("""COMPUTED_VALUE"""),46085.99861111111) -> 46085.999 | P27: =IFERROR(__xludf.DUMMYFUNCTION("""COMPUTED_VALUE"""),3759.11) -> 3759.11
O28: =IFERROR(__xludf.DUMMYFUNCTION("""COMPUTED_VALUE"""),46086.99861111111) -> 46086.999 | P28: =IFERROR(__xludf.DUMMYFUNCTION("""COMPUTED_VALUE"""),3788.48) -> 3788.48
O29: =IFERROR(__xludf.DUMMYFUNCTION("""COMPUTED_VALUE"""),46087.99861111111) -> 46087.999 | P29: =IFERROR(__xludf.DUMMYFUNCTION("""COMPUTED_VALUE"""),3782.66) -> 3782.66
O30: =IFERROR(__xludf.DUMMYFUNCTION("""COMPUTED_VALUE"""),46088.99861111111) -> 46088.999 | P30: =IFERROR(__xludf.DUMMYFUNCTION("""COMPUTED_VALUE"""),3711.902) -> 3711.902
O31: =IFERROR(__xludf.DUMMYFUNCTION("""COMPUTED_VALUE"""),46090.99861111111) -> 46090.999 | P31: =IFERROR(__xludf.DUMMYFUNCTION("""COMPUTED_VALUE"""),3761.83) -> 3761.83
O32: =IFERROR(__xludf.DUMMYFUNCTION("""COMPUTED_VALUE"""),46091.99861111111) -> 46091.999 | P32: =IFERROR(__xludf.DUMMYFUNCTION("""COMPUTED_VALUE"""),3709.07) -> 3709.07
O33: =IFERROR(__xludf.DUMMYFUNCTION("""COMPUTED_VALUE"""),46092.99861111111) -> 46092.999 | P33: =IFERROR(__xludf.DUMMYFUNCTION("""COMPUTED_VALUE"""),3703.43) -> 3703.43
O34: =IFERROR(__xludf.DUMMYFUNCTION("""COMPUTED_VALUE"""),46093.99861111111) -> 46093.999 | P34: =IFERROR(__xludf.DUMMYFUNCTION("""COMPUTED_VALUE"""),3692.56) -> 3692.56
O35: =IFERROR(__xludf.DUMMYFUNCTION("""COMPUTED_VALUE"""),46094.99861111111) -> 46094.999 | P35: =IFERROR(__xludf.DUMMYFUNCTION("""COMPUTED_VALUE"""),3704.68) -> 3704.68
O36: =IFERROR(__xludf.DUMMYFUNCTION("""COMPUTED_VALUE"""),46095.99861111111) -> 46095.999 | P36: =IFERROR(__xludf.DUMMYFUNCTION("""COMPUTED_VALUE"""),3638.607) -> 3638.607
O37: =IFERROR(__xludf.DUMMYFUNCTION("""COMPUTED_VALUE"""),46097.99861111111) -> 46097.999 | P37: =IFERROR(__xludf.DUMMYFUNCTION("""COMPUTED_VALUE"""),3702.24) -> 3702.24
O38: =IFERROR(__xludf.DUMMYFUNCTION("""COMPUTED_VALUE"""),46098.99861111111) -> 46098.999 | P38: =IFERROR(__xludf.DUMMYFUNCTION("""COMPUTED_VALUE"""),3689.13572) -> 3689.1357
O39: =IFERROR(__xludf.DUMMYFUNCTION("""COMPUTED_VALUE"""),46099.99861111111) -> 46099.999 | P39: =IFERROR(__xludf.DUMMYFUNCTION("""COMPUTED_VALUE"""),3706.06) -> 3706.06
O40: =IFERROR(__xludf.DUMMYFUNCTION("""COMPUTED_VALUE"""),46100.99861111111) -> 46100.999 | P40: =IFERROR(__xludf.DUMMYFUNCTION("""COMPUTED_VALUE"""),3704.24) -> 3704.24
A117: Linea de Negocio | B117: TC. Real | C117: Margen Bruto
A118: Network | B118: 0.085 | C118: 0.3
A119: Equipo Dedicado | B119: 0.1 | C119: 0.4
A120: Descubrimiento | B120: 0.1 | C120: 0.5
A121: Proyecto | B121: 0.1 | C121: 0.5
A122: Servidores | C122: 0.6
A123: Enterprise | B123: 0.1 | C123: 0.45
C128: Renting
A129: Tecnologias | C129: 1 | D129: 3 | E129: 6 | F129: 12
A130: Angular | B130: 2599000 | C130: 354750 | D130: 354750 | E130: 354750 | F130: 354750
A131: Vue | B131: 2599000 | C131: 354750 | D131: 354750 | E131: 354750 | F131: 354750
A132: Flutter | B132: 5431900 | C132: 683700 | D132: 632100 | E132: 580500 | F132: 516000
A133: Node Js | B133: 2599000 | C133: 354750 | D133: 354750 | E133: 354750 | F133: 354750
A134: Fullstack | B134: 2599000 | C134: 354750 | D134: 354750 | E134: 354750 | F134: 354750
A135: Fullstack Spring- Java | B135: 2599000 | C135: 354750 | D135: 354750 | E135: 354750 | F135: 354750
A136: Net Core | B136: 2599000 | C136: 354750 | D136: 354750 | E136: 354750 | F136: 354750
A137: Angular js | B137: 2599000 | C137: 354750 | D137: 354750 | E137: 354750 | F137: 354750
A138: Sql Server | B138: 2599000 | C138: 354750 | D138: 354750 | E138: 354750 | F138: 354750
A139: PHP | B139: 2599000 | C139: 354750 | D139: 354750 | E139: 354750 | F139: 354750
A140: Fullstack Python | B140: 2599000 | C140: 354750 | D140: 354750 | E140: 354750 | F140: 354750
A141: QA (Iphone) | B141: 2419000 | C141: 210000 | D141: 180000 | E141: 150000
A142: QA (Android) | B142: 349900
A144: COmputador y celular (1, 0 o 2)
A146: Restricciones compra de computadores
B147: Mensual | C147: Valor Contrato
A148: Primera condicion | B148: 25000000 | C148: 150000000
A149: Segunda restriccion | B149: Considerar como mínimo por cada Dev: PM:33%, QA:20%, Diseño:10%

Sheet Política de Servidores
B4: - Si el despliegue es en servidor Imagine: Despliegue sin costo pero mensualidad entre 25 - 50 usd* x plataforma (App o Web)-
B5: *Precio promedio, sujeto al consumo real, en caso de tener un consumo mayor se realizará el cobro real, adicional al servicio de administración que corresponde al 25% del consumo.
B6: Precio por instancia, ej: si tienen instancia de pruebas es $25 + producción $25. Y la de pruebas no la debemos cobrar si están pagando equipo dedicado
B7: - Si se despliega en un servidor del cliente: En el pricing debe contemplarse un 12.5% de devops.
B8: - Si inicialmente se despliega en un servidor de Imagine y se migra al del cliente: requerimos 3 días hábiles y tendrá un costo aproximado de 1.500 USD (se confirma con cotización específica del despliegue)
B9: - Sujeto a configuraciones y parámetros a configurar en el servidor externo
B10: - Si migra de un servidor externo a Imagine, el tiempo será de 3 días hábiles y tendrá un costo aproximado de 1.500 USD (se confirma con cotización específica del despliegue)
B11: - Sujeto a configuraciones y parámetros a configurar en el servidor externo

Sheet Política Comisiones
B2: Esquema de comisiones:
B4: Comisiones | D4: Referido | E4: KAM | F4: Comisiones
B5: Fuente lead | C5: Mercadeo | D5: 0.02 | E5: 0.1 | F5: =D5+E5 -> 0.12
C6: Directo | D6: 0 | E6: 0.1 | F6: =D6+E6 -> 0.1
C7: Referido Imagine | D7: 0.05 | E7: 0.05 | F7: =D7+E7 -> 0.1
C8: Network- Cold Calling | D8: 0.02 | E8: 0.065 | F8: =D8+E8 -> 0.085
C9: Cold Calling / Mailing | D9: 0.02 | E9: 0.065 | F9: =D9+E9 -> 0.085
B11: Definiciones
B12: Mercadeo | C12: Lisseth Carhuapoma
B13: Directo | C13: Venta directa del comercial
B14: Referido Imagine | C14: Personal de Imagine que ayuda a la obtención de una venta.
B15: Network - Cold Calling | C15: Personal comercial que ayuda a la obtención de una venta.
B16: Cold Calling / Mailing | C16: Personal comercial que ayuda a la obtención de una venta.
B19: Esquema de bonos de reclutamiento:
B21: Seniority | C21: Bono
B22: Perfil Semi Sr. | C22: 350000
B23: Perfil Sr. | C23: 600000
B24: Perdil Junior | C24: 200000

Sheet Foward Deployed Enginnier
B2: Línea de Negocio | C2: Equipo Dedicado
B3: ¿Tipo de contrato vendedor? | C3: Deel/Ontop
B4: Comisión vendedor | C4: 0.05
B5: ¿Cuál es la fuente de tu lead? | C5: Directo
B6: Perfil Network | C6: Perfil Sr.
B7: ¿Pago con TC? | C7: 0 | F7: Gross Margin Meta | G7: =VLOOKUP($C$2,'Parámetros'!$A$118:$D$124,3,0) -> 0.4
B8: Factoring | C8: 0 | F8: =IF(D13>=G7,"Dentro del margen","¡Por debajo del margen!") -> ¡Por debajo del margen!
B9: Tecnologia
B10: Tiempo Duración: Mes | C10: 4
F11: COP | G11: USD
B12: Jugar con Gross Margin | C12: Comisión Venta | D12: =F12*C4+IFS(C5="Cold Calling",2%*138.3522%,C5="Mercadeo",2%*101%,C5="Network - Cold Calling",2%*138.3522%,C5="Referido Imagine",5%*138.3522%,C5="Directo",0)*F12+ifs(AND(C6="Perfil Jr.",C2="Network"),200000,AND(C6="Perfil Sr.",C2="Network"),350000,AND(C2="Network",C6="Perfil Semi Senior"), 600000,C2="Proyecto",1,C2="Equipo dedicado",1,C2="Servidores",1,C2="Enterprise",1,C2="Descubrimiento",1) -> 2903226.8 | E12: Precio Total | F12: =((C61+C57+C59)/((1-D13-'Parámetros'!L8*C7)))*IF(C8=1,102.4%,1) -> 58064516 | G12: =F12/'Parámetros'!$L$3 -> 16356.202 | I12: 160 | J12: 1
C13: Gross Margin | D13: 0.38 | E13: Precio mensual | F13: =F12/C10 -> 14516129 | G13: =F13/'Parámetros'!$L$3 -> 4089.0504 | I13: 12 | J13: =I13*J12/I12 -> 0.075
C14: ICA | D14: =F12*'Parámetros'!L5 -> 400645.16 | E14: Precio/Horas | F14: =F12/SUM(D43:D52)/C10 -> 80645.161 | G14: =G12/SUM(D43:D52)/C10 -> 22.716947
C15: NET Margin | D15: =(F12-C62-D14-D12-C7*'Parámetros'!L8*F12-IF(C8=1,2.4%,0)*F12)/F12 -> 0.25942405 | I15: 12 horas | J15: 3127889.9
I16: 20 horas | J16: 5044796.6
B18: Jugar con Net Margin | C18: Comisión Venta | D18: =F18*C4+IFS(C5="Cold Calling",2%*138.3522%,C5="Mercadeo",2%*101%,C5="Network - Cold Calling",2%*138.3522%,C5="Referido Imagine",5%*138.3522%,C5="Directo",0)*F18 -> 2671061.2 | E18: Precio Total | F18: =+C62/((1-IFS(C5="Cold Calling",2%*138.3522%,C5="Mercadeo",2%*101%,C5="Network - Cold Calling",2%*138.3522%,C5="Referido Imagine",5%*138.3522%,C5="Directo",0)-C4-D19-'Parámetros'!L5-C7*'Parámetros'!L8))*IF(C8=1,102.4%,1) -> 53421225 | G18: =F18/'Parámetros'!L3 -> 15048.232
C19: NET Margin | D19: 0.2 | E19: Precio mensual | F19: =F18/C10 -> 13355306 | G19: =G18/C10 -> 3762.0581
C20: ICA | D20: =F18*'Parámetros'!L5 -> 368606.45 | E20: Precio/Horas | F20: =F18/SUM(D43:D52)/C10 -> 74196.146 | G20: =G18/SUM(D43:D52)/C10 -> 20.900323
C21: Gross Margin | D21: =(((F18-C57-C59-C61-C7*'Parámetros'!L8*F18)-IF(C8=1,2.4%,0)*F18)/F18) -> 0.32611055
B23: ='Parámetros'!B149 -> Considerar como mínimo por cada Dev: PM:33%, QA:20%, Diseño:10%
E25: =SUM(E27:E34) -> 1
B26: Equipo | C26: Salario Base | D26: Tipo Contrato | E26: Dedicación | F26: Costo mensual | G26: Costo total | H26: % Tiempo Equipo
A27: =IFERROR(__xludf.DUMMYFUNCTION("COUNTIF(SPLIT(B27,"" ""),""Developer"")"),0.0) -> 0 | B27: Forward Deployed Enginnier - On Site | C27: =IFERROR(VLOOKUP(B27,'Parámetros'!A$1:B113,2, FALSE),"") -> 9000000 | D27: P. Servicios | E27: 1 | F27: =+IFERROR(IF(D27="Nómina",C27*1.38352,C27),"")*E27 -> 9000000 | G27: =F27*C$10 -> 36000000 | H27: =F27/(AVERAGE('Parámetros'!$F$5:$F$6)+$F$37) -> 0.026242376
A28: =IFERROR(__xludf.DUMMYFUNCTION("COUNTIF(SPLIT(B28,"" ""),""Developer"")"),0.0) -> 0
A29: =IFERROR(__xludf.DUMMYFUNCTION("COUNTIF(SPLIT(B29,"" ""),""Developer"")"),0.0) -> 0
A30: =IFERROR(__xludf.DUMMYFUNCTION("COUNTIF(SPLIT(B30,"" ""),""Developer"")"),0.0) -> 0 | C30: =IFERROR(VLOOKUP(B30,'Parámetros'!A$1:B116,2, FALSE),"") | F30: =+IFERROR(IF(D30="Nómina",C30*1.38352,C30),"")*E30*105% -> 0 | G30: =F30*C$10 -> 0 | H30: =G30/(AVERAGE('Parámetros'!$F$5:$F$6)+$F$37) -> 0
A31: =IFERROR(__xludf.DUMMYFUNCTION("COUNTIF(SPLIT(B31,"" ""),""Developer"")"),0.0) -> 0
A32: =IFERROR(__xludf.DUMMYFUNCTION("COUNTIF(SPLIT(B32,"" ""),""Developer"")"),0.0) -> 0 | F32: =+IFERROR(IF(D32="Nómina",C32*1.38352,C32),"")*E32*105% -> 0 | G32: =F32*C$10 -> 0 | H32: =G32/(AVERAGE('Parámetros'!$F$5:$F$6)+$F$37) -> 0
A33: =IFERROR(__xludf.DUMMYFUNCTION("COUNTIF(SPLIT(B33,"" ""),""Developer"")"),0.0) -> 0 | F33: =+IFERROR(IF(D33="Nómina",C33*1.38352,C33),"")*E33*105% -> 0 | G33: =F33*C$10 -> 0 | H33: =G33/(AVERAGE('Parámetros'!$F$5:$F$6)+$F$37) -> 0
A34: =IFERROR(__xludf.DUMMYFUNCTION("COUNTIF(SPLIT(B34,"" ""),""Developer"")"),0.0) -> 0 | C34: =IFERROR(VLOOKUP(B34,'Parámetros'!A$1:B120,2, FALSE),"") | F34: =+IFERROR(IF(D34="Nómina",C34*1.38352,C34),"")*E34*105% -> 0 | G34: =F34*C$10 -> 0 | H34: =G34/(AVERAGE('Parámetros'!$F$5:$F$6)+$F$37) -> 0
C35: =IFERROR(VLOOKUP(B35,'Parámetros'!A$1:B121,2, FALSE),"") | F35: =+IFERROR(IF(D35="Nómina",C35*1.38352,C35),"")*E35*105% -> 0 | G35: =F35*C$10 -> 0 | H35: =G35/(AVERAGE('Parámetros'!$F$5:$F$6)+$F$37) -> 0
C36: =IFERROR(VLOOKUP(B36,'Parámetros'!A$1:B122,2, FALSE),"") | F36: =+IFERROR(IF(D36="Nómina",C36*1.38352,C36),"")*E36*105% -> 0 | G36: =F36*C$10 -> 0 | H36: =G36/(AVERAGE('Parámetros'!$F$5:$F$6)+$F$37) -> 0
F37: =SUM(F27:F36) -> 9000000 | G37: =SUM(G27:G36) -> 36000000 | H37: =SUM(H27:H36) -> 0.026242376
C40: Gross Margin | D40: USD
B42: Equipo | C42: Dedicación | D42: Capacidad Horas | E42: Precio x Hora | F42: Precio Total
B43: =B27 -> Forward Deployed Enginnier - On Site | C43: =E27 -> 1 | D43: =C43*180 -> 180 | E43: =IFERROR((IF($C$40="Gross Margin",F27/$F$37*$F$12,IF($C$40="Net Margin",F27/$F$37*$F$18,"Error")))/D43,"")/IF($D$40="USD",'Parámetros'!$L$3,1)/$C$10 -> 22.716947 | F43: =E43*D43 -> 4089.0504
B44: =B28 | C44: =E28 | D44: =C44*180 -> 0 | E44: =IFERROR((IF($C$40="Gross Margin",F28/$F$37*$F$12,IF($C$40="Net Margin",F28/$F$37*$F$18,"Error")))/D44,"")/IF($D$40="USD",'Parámetros'!$L$3,1)/$C$10 -> 0 | F44: =E44*D44 -> 0
B45: =B29 | C45: =E29 | D45: =C45*180 -> 0 | E45: =IFERROR((IF($C$40="Gross Margin",F29/$F$37*$F$12,IF($C$40="Net Margin",F29/$F$37*$F$18,"Error")))/D45,"")/IF($D$40="USD",'Parámetros'!$L$3,1)/$C$10 -> 0 | F45: =E45*D45 -> 0
B46: =B30 | C46: =E30 | D46: =C46*180 -> 0 | E46: =IFERROR((IF($C$40="Gross Margin",F30/$F$37*$F$12,IF($C$40="Net Margin",F30/$F$37*$F$18,"Error")))/D46,"")/IF($D$40="USD",'Parámetros'!$L$3,1)/$C$10 -> 0 | F46: =E46*D46 -> 0
B47: =B31 | C47: =E31 | D47: =C47*180 -> 0 | E47: =IFERROR((IF($C$40="Gross Margin",F31/$F$37*$F$12,IF($C$40="Net Margin",F31/$F$37*$F$18,"Error")))/D47,"")/IF($D$40="USD",'Parámetros'!$L$3,1)/$C$10 -> 0 | F47: =E47*D47 -> 0
B48: =B32 | C48: =E32 | D48: =C48*180 -> 0 | E48: =IFERROR((IF($C$40="Gross Margin",F32/$F$37*$F$12,IF($C$40="Net Margin",F32/$F$37*$F$18,"Error")))/D48,"")/IF($D$40="USD",'Parámetros'!$L$3,1) -> 0 | F48: =E48*D48 -> 0
B49: =B33 | C49: =E33 | D49: =C49*180 -> 0 | E49: =IFERROR((IF($C$40="Gross Margin",F33/$F$37*$F$12,IF($C$40="Net Margin",F33/$F$37*$F$18,"Error")))/D49,"")/IF($D$40="USD",'Parámetros'!$L$3,1) -> 0 | F49: =E49*D49 -> 0
B50: =B34 | C50: =E34 | D50: =C50*180 -> 0 | E50: =IFERROR((IF($C$40="Gross Margin",F34/$F$37*$F$12,IF($C$40="Net Margin",F34/$F$37*$F$18,"Error")))/D50,"")/IF($D$40="USD",'Parámetros'!$L$3,1) -> 0 | F50: =E50*D50 -> 0
B51: =B35 | C51: =E35 | D51: =C51*180 -> 0 | E51: =IFERROR((IF($C$40="Gross Margin",F35/$F$37*$F$12,IF($C$40="Net Margin",F35/$F$37*$F$18,"Error")))/D51,"")/IF($D$40="USD",'Parámetros'!$L$3,1) -> 0 | F51: =E51*D51 -> 0
B52: =B36 | C52: =E36 | D52: =C52*180 -> 0 | E52: =IFERROR((IF($C$40="Gross Margin",F36/$F$37*$F$12,IF($C$40="Net Margin",F36/$F$37*$F$18,"Error")))/D52,"")/IF($D$40="USD",'Parámetros'!$L$3,1) -> 0 | F52: =E52*D52 -> 0
E53: Total | F53: =SUM(F43:F52) -> 4089.0504
E54: Validación | F54: =F53-G13 -> 0
B56: Resumen | C56: Total | D56: Mensual
B57: Costo Equipo | C57: =G37 -> 36000000 | D57: =C57/C$10 -> 9000000
B58: Costo + Gasto Fijo | C58: =C60+C61+C59 -> 3697312.2 | D58: =C58/C$10 -> 924328.06
B59: Computador Herramientas Trabajo | D59: =C59/C$10 -> 0
B60: - ROP Gasto | C60: =H37*AVERAGE('Parámetros'!G8:G9)*IF(C2="Network",15%,100%)*IF(C2="Enterprise",40%,100%) -> 3697312.2 | D60: =C60/C$10 -> 924328.06
B61: - ROP Costo Fijo | D61: =C61/C$10 -> 0
B62: T. C + G Equipo | C62: =C57+C58 -> 39697312 | D62: =C62/C$10 -> 9924328.1
B63: Costo Total Interno Compañía | C63: =C57+C59+C61 -> 36000000 | D63: =D57+D59+D61 -> 9000000

Sheet Equipo Base
B2: Línea de Negocio | C2: Equipo Dedicado
B3: ¿Tipo de contrato vendedor? | C3: Deel/Ontop
B4: Comisión vendedor | C4: 0.08
B5: ¿Cuál es la fuente de tu lead? | C5: Directo
B6: Perfil Network | C6: Perfil Sr.
B7: ¿Pago con TC? | C7: 0 | F7: Gross Margin Meta | G7: =VLOOKUP($C$2,'Parámetros'!$A$118:$D$124,3,0) -> 0.4
B8: Factoring | C8: 0 | F8: =IF(D13>=G7,"Dentro del margen","¡Por debajo del margen!") -> Dentro del margen
B9: Tecnologia
B10: Tiempo Duración: Mes | C10: 0.25
F11: COP | G11: USD
B12: Jugar con Gross Margin | C12: Comisión Venta | D12: =F12*C4+IFS(C5="Cold Calling",2%*138.3522%,C5="Mercadeo",2%*101%,C5="Network - Cold Calling",2%*138.3522%,C5="Referido Imagine",5%*138.3522%,C5="Directo",0)*F12+ifs(AND(C6="Perfil Jr.",C2="Network"),200000,AND(C6="Perfil Sr.",C2="Network"),350000,AND(C2="Network",C6="Perfil Semi Senior"), 600000,C2="Proyecto",1,C2="Equipo dedicado",1,C2="Servidores",1,C2="Enterprise",1,C2="Descubrimiento",1) -> 460001 | E12: Precio Total | F12: =((C61+C57+C59)/((1-D13-'Parámetros'!L8*C7)))*IF(C8=1,102.4%,1) -> 5750000 | G12: =F12/'Parámetros'!$L$3 -> 1619.7183 | I12: 160 | J12: 1
C13: Gross Margin | D13: 0.75 | E13: Precio mensual | F13: =F12/C10 -> 23000000 | G13: =F13/'Parámetros'!$L$3 -> 6478.8732 | I13: 12 | J13: =I13*J12/I12 -> 0.075
C14: ICA | D14: =F12*'Parámetros'!L5 -> 39675 | E14: Precio/Horas | F14: =F12/SUM(D43:D52)/C10 -> 111111.11 | G14: =G12/SUM(D43:D52)/C10 -> 31.298905
C15: NET Margin | D15: =(F12-C62-D14-D12-C7*'Parámetros'!L8*F12-IF(C8=1,2.4%,0)*F12)/F12 -> 0.28892974 | I15: 12 horas | J15: 3127889.9
I16: 20 horas | J16: 5044796.6
B18: Jugar con Net Margin | C18: Comisión Venta | D18: =F18*C4+IFS(C5="Cold Calling",2%*138.3522%,C5="Mercadeo",2%*101%,C5="Network - Cold Calling",2%*138.3522%,C5="Referido Imagine",5%*138.3522%,C5="Directo",0)*F18 -> 402633.91 | E18: Precio Total | F18: =+C62/((1-IFS(C5="Cold Calling",2%*138.3522%,C5="Mercadeo",2%*101%,C5="Network - Cold Calling",2%*138.3522%,C5="Referido Imagine",5%*138.3522%,C5="Directo",0)-C4-D19-'Parámetros'!L5-C7*'Parámetros'!L8))*IF(C8=1,102.4%,1) -> 5032923.8 | G18: =F18/'Parámetros'!L3 -> 1417.725
C19: NET Margin | D19: 0.2 | E19: Precio mensual | F19: =F18/C10 -> 20131695 | G19: =G18/C10 -> 5670.9001
C20: ICA | D20: =F18*'Parámetros'!L5 -> 34727.174 | E20: Precio/Horas | F20: =F18/SUM(D43:D52)/C10 -> 97254.567 | G20: =G18/SUM(D43:D52)/C10 -> 27.395653
C21: Gross Margin | D21: =(((F18-C57-C59-C61-C7*'Parámetros'!L8*F18)-IF(C8=1,2.4%,0)*F18)/F18) -> 0.71438074
B23: ='Parámetros'!B149 -> Considerar como mínimo por cada Dev: PM:33%, QA:20%, Diseño:10%
E25: =SUM(E27:E34) -> 1.15
B26: Equipo | C26: Salario Base | D26: Tipo Contrato | E26: Dedicación | F26: Costo mensual | G26: Costo total | H26: % Tiempo Equipo
A27: =IFERROR(__xludf.DUMMYFUNCTION("COUNTIF(SPLIT(B27,"" ""),""Developer"")"),0.0) -> 0 | B27: Forward Deployed Product manager | C27: =IFERROR(VLOOKUP(B27,'Parámetros'!A$1:B113,2, FALSE),"") -> 5000000 | D27: P. Servicios | E27: 1 | F27: =+IFERROR(IF(D27="Nómina",C27*1.38352,C27),"")*E27 -> 5000000 | G27: =F27*C$10 -> 1250000 | H27: =F27/(AVERAGE('Parámetros'!$F$5:$F$6)+$F$37) -> 0.014718577
A28: =IFERROR(__xludf.DUMMYFUNCTION("COUNTIF(SPLIT(B28,"" ""),""Developer"")"),0.0) -> 0 | B28: Forward Deployed Enginnier | C28: 9000000 | D28: P. Servicios | F28: =+IFERROR(IF(D28="Nómina",C28*1.38352,C28),"")*E28 -> 0 | G28: =F28*C$10 -> 0 | H28: =G28/(AVERAGE('Parámetros'!$F$5:$F$6)+$F$37) -> 0
A29: =IFERROR(__xludf.DUMMYFUNCTION("COUNTIF(SPLIT(B29,"" ""),""Developer"")"),0.0) -> 0 | B29: Forward Deployed Pruduct experience | C29: =IFERROR(VLOOKUP(B29,'Parámetros'!A$1:B115,2, FALSE),"") -> 5000000 | D29: P. Servicios | E29: 0.15 | F29: =+IFERROR(IF(D29="Nómina",C29*1.38352,C29),"")*E29 -> 750000 | G29: =F29*C$10 -> 187500 | H29: =G29/(AVERAGE('Parámetros'!$F$5:$F$6)+$F$37) -> 0.00055194663
A30: =IFERROR(__xludf.DUMMYFUNCTION("COUNTIF(SPLIT(B30,"" ""),""Developer"")"),0.0) -> 0 | B30: Forward Deployed Enginnier | C30: 9000000 | D30: P. Servicios | F30: =+IFERROR(IF(D30="Nómina",C30*1.38352,C30),"")*E30 -> 0 | G30: =F30*C$10 -> 0 | H30: =G30/(AVERAGE('Parámetros'!$F$5:$F$6)+$F$37) -> 0
A31: =IFERROR(__xludf.DUMMYFUNCTION("COUNTIF(SPLIT(B31,"" ""),""Developer"")"),0.0) -> 0
A32: =IFERROR(__xludf.DUMMYFUNCTION("COUNTIF(SPLIT(B32,"" ""),""Developer"")"),0.0) -> 0 | F32: =+IFERROR(IF(D32="Nómina",C32*1.38352,C32),"")*E32*105% -> 0 | G32: =F32*C$10 -> 0 | H32: =G32/(AVERAGE('Parámetros'!$F$5:$F$6)+$F$37) -> 0
A33: =IFERROR(__xludf.DUMMYFUNCTION("COUNTIF(SPLIT(B33,"" ""),""Developer"")"),0.0) -> 0 | F33: =+IFERROR(IF(D33="Nómina",C33*1.38352,C33),"")*E33*105% -> 0 | G33: =F33*C$10 -> 0 | H33: =G33/(AVERAGE('Parámetros'!$F$5:$F$6)+$F$37) -> 0
A34: =IFERROR(__xludf.DUMMYFUNCTION("COUNTIF(SPLIT(B34,"" ""),""Developer"")"),0.0) -> 0 | C34: =IFERROR(VLOOKUP(B34,'Parámetros'!A$1:B120,2, FALSE),"") | F34: =+IFERROR(IF(D34="Nómina",C34*1.38352,C34),"")*E34*105% -> 0 | G34: =F34*C$10 -> 0 | H34: =G34/(AVERAGE('Parámetros'!$F$5:$F$6)+$F$37) -> 0
C35: =IFERROR(VLOOKUP(B35,'Parámetros'!A$1:B121,2, FALSE),"") | F35: =+IFERROR(IF(D35="Nómina",C35*1.38352,C35),"")*E35*105% -> 0 | G35: =F35*C$10 -> 0 | H35: =G35/(AVERAGE('Parámetros'!$F$5:$F$6)+$F$37) -> 0
C36: =IFERROR(VLOOKUP(B36,'Parámetros'!A$1:B122,2, FALSE),"") | F36: =+IFERROR(IF(D36="Nómina",C36*1.38352,C36),"")*E36*105% -> 0 | G36: =F36*C$10 -> 0 | H36: =G36/(AVERAGE('Parámetros'!$F$5:$F$6)+$F$37) -> 0
F37: =SUM(F27:F36) -> 5750000 | G37: =SUM(G27:G36) -> 1437500 | H37: =SUM(H27:H36) -> 0.015270523
C40: Gross Margin | D40: USD
B42: Equipo | C42: Dedicación | D42: Capacidad Horas | E42: Precio x Hora | F42: Precio Total
B43: =B27 -> Forward Deployed Product manager | C43: =E27 -> 1 | D43: =C43*180 -> 180 | E43: =IFERROR((IF($C$40="Gross Margin",F27/$F$37*$F$12,IF($C$40="Net Margin",F27/$F$37*$F$18,"Error")))/D43,"")/IF($D$40="USD",'Parámetros'!$L$3,1)/$C$10 -> 31.298905 | F43: =E43*D43 -> 5633.8028
B44: =B28 -> Forward Deployed Enginnier | C44: =E28 | D44: =C44*180 -> 0 | E44: =IFERROR((IF($C$40="Gross Margin",F28/$F$37*$F$12,IF($C$40="Net Margin",F28/$F$37*$F$18,"Error")))/D44,"")/IF($D$40="USD",'Parámetros'!$L$3,1)/$C$10 -> 0 | F44: =E44*D44 -> 0
B45: =B29 -> Forward Deployed Pruduct experience | C45: =E29 -> 0.15 | D45: =C45*180 -> 27 | E45: =IFERROR((IF($C$40="Gross Margin",F29/$F$37*$F$12,IF($C$40="Net Margin",F29/$F$37*$F$18,"Error")))/D45,"")/IF($D$40="USD",'Parámetros'!$L$3,1)/$C$10 -> 31.298905 | F45: =E45*D45 -> 845.07042
B46: =B30 -> Forward Deployed Enginnier | C46: =E30 | D46: =C46*180 -> 0 | E46: =IFERROR((IF($C$40="Gross Margin",F30/$F$37*$F$12,IF($C$40="Net Margin",F30/$F$37*$F$18,"Error")))/D46,"")/IF($D$40="USD",'Parámetros'!$L$3,1)/$C$10 -> 0 | F46: =E46*D46 -> 0
B47: =B31 | C47: =E31 | D47: =C47*180 -> 0 | E47: =IFERROR((IF($C$40="Gross Margin",F31/$F$37*$F$12,IF($C$40="Net Margin",F31/$F$37*$F$18,"Error")))/D47,"")/IF($D$40="USD",'Parámetros'!$L$3,1)/$C$10 -> 0 | F47: =E47*D47 -> 0
B48: =B32 | C48: =E32 | D48: =C48*180 -> 0 | E48: =IFERROR((IF($C$40="Gross Margin",F32/$F$37*$F$12,IF($C$40="Net Margin",F32/$F$37*$F$18,"Error")))/D48,"")/IF($D$40="USD",'Parámetros'!$L$3,1) -> 0 | F48: =E48*D48 -> 0
B49: =B33 | C49: =E33 | D49: =C49*180 -> 0 | E49: =IFERROR((IF($C$40="Gross Margin",F33/$F$37*$F$12,IF($C$40="Net Margin",F33/$F$37*$F$18,"Error")))/D49,"")/IF($D$40="USD",'Parámetros'!$L$3,1) -> 0 | F49: =E49*D49 -> 0
B50: =B34 | C50: =E34 | D50: =C50*180 -> 0 | E50: =IFERROR((IF($C$40="Gross Margin",F34/$F$37*$F$12,IF($C$40="Net Margin",F34/$F$37*$F$18,"Error")))/D50,"")/IF($D$40="USD",'Parámetros'!$L$3,1) -> 0 | F50: =E50*D50 -> 0
B51: =B35 | C51: =E35 | D51: =C51*180 -> 0 | E51: =IFERROR((IF($C$40="Gross Margin",F35/$F$37*$F$12,IF($C$40="Net Margin",F35/$F$37*$F$18,"Error")))/D51,"")/IF($D$40="USD",'Parámetros'!$L$3,1) -> 0 | F51: =E51*D51 -> 0
B52: =B36 | C52: =E36 | D52: =C52*180 -> 0 | E52: =IFERROR((IF($C$40="Gross Margin",F36/$F$37*$F$12,IF($C$40="Net Margin",F36/$F$37*$F$18,"Error")))/D52,"")/IF($D$40="USD",'Parámetros'!$L$3,1) -> 0 | F52: =E52*D52 -> 0
E53: Total | F53: =SUM(F43:F52) -> 6478.8732
E54: Validación | F54: =F53-G13 -> 0
B56: Resumen | C56: Total | D56: Mensual
B57: Costo Equipo | C57: =G37 -> 1437500 | D57: =C57/C$10 -> 5750000
B58: Costo + Gasto Fijo | C58: =C60+C61+C59 -> 2151478 | D58: =C58/C$10 -> 8605911.9
B59: Computador Herramientas Trabajo | D59: =C59/C$10 -> 0
B60: - ROP Gasto | C60: =H37*AVERAGE('Parámetros'!G8:G9)*IF(C2="Network",15%,100%)*IF(C2="Enterprise",40%,100%) -> 2151478 | D60: =C60/C$10 -> 8605911.9
B61: - ROP Costo Fijo | D61: =C61/C$10 -> 0
B62: T. C + G Equipo | C62: =C57+C58 -> 3588978 | D62: =C62/C$10 -> 14355912
B63: Costo Total Interno Compañía | C63: =C57+C59+C61 -> 1437500 | D63: =D57+D59+D61 -> 5750000

Sheet Equipo con UX
B2: Línea de Negocio | C2: Equipo Dedicado
B3: ¿Tipo de contrato vendedor? | C3: Deel/Ontop
B4: Comisión vendedor | C4: 0.05
B5: ¿Cuál es la fuente de tu lead? | C5: Directo
B6: Perfil Network | C6: Perfil Sr.
B7: ¿Pago con TC? | C7: 0 | F7: Gross Margin Meta | G7: =VLOOKUP($C$2,'Parámetros'!$A$118:$D$124,3,0) -> 0.4
B8: Factoring | C8: 0 | F8: =IF(D13>=G7,"Dentro del margen","¡Por debajo del margen!") -> ¡Por debajo del margen!
B9: Tecnologia
B10: Tiempo Duración: Mes | C10: 4
F11: COP | G11: USD
B12: Jugar con Gross Margin | C12: Comisión Venta | D12: =F12*C4+IFS(C5="Cold Calling",2%*138.3522%,C5="Mercadeo",2%*101%,C5="Network - Cold Calling",2%*138.3522%,C5="Referido Imagine",5%*138.3522%,C5="Directo",0)*F12+ifs(AND(C6="Perfil Jr.",C2="Network"),200000,AND(C6="Perfil Sr.",C2="Network"),350000,AND(C2="Network",C6="Perfil Semi Senior"), 600000,C2="Proyecto",1,C2="Equipo dedicado",1,C2="Servidores",1,C2="Enterprise",1,C2="Descubrimiento",1) -> 4032259.1 | E12: Precio Total | F12: =((C61+C57+C59)/((1-D13-'Parámetros'!L8*C7)))*IF(C8=1,102.4%,1) -> 80645161 | G12: =F12/'Parámetros'!$L$3 -> 22716.947 | I12: 160 | J12: 1
C13: Gross Margin | D13: 0.38 | E13: Precio mensual | F13: =F12/C10 -> 20161290 | G13: =F13/'Parámetros'!$L$3 -> 5679.2367 | I13: 12 | J13: =I13*J12/I12 -> 0.075
C14: ICA | D14: =F12*'Parámetros'!L5 -> 556451.61 | E14: Precio/Horas | F14: =F12/SUM(D43:D52)/C10 -> 62226.205 | G14: =G12/SUM(D43:D52)/C10 -> 17.528508
C15: NET Margin | D15: =(F12-C62-D14-D12-C7*'Parámetros'!L8*F12-IF(C8=1,2.4%,0)*F12)/F12 -> 0.10878894 | I15: 12 horas | J15: 3127889.9
I16: 20 horas | J16: 5044796.6
B18: Jugar con Net Margin | C18: Comisión Venta | D18: =F18*C4+IFS(C5="Cold Calling",2%*138.3522%,C5="Mercadeo",2%*101%,C5="Network - Cold Calling",2%*138.3522%,C5="Referido Imagine",5%*138.3522%,C5="Directo",0)*F18 -> 4527193.5 | E18: Precio Total | F18: =+C62/((1-IFS(C5="Cold Calling",2%*138.3522%,C5="Mercadeo",2%*101%,C5="Network - Cold Calling",2%*138.3522%,C5="Referido Imagine",5%*138.3522%,C5="Directo",0)-C4-D19-'Parámetros'!L5-C7*'Parámetros'!L8))*IF(C8=1,102.4%,1) -> 90543869 | G18: =F18/'Parámetros'!L3 -> 25505.315
C19: NET Margin | D19: 0.2 | E19: Precio mensual | F19: =F18/C10 -> 22635967 | G19: =G18/C10 -> 6376.3288
C20: ICA | D20: =F18*'Parámetros'!L5 -> 624752.7 | E20: Precio/Horas | F20: =F18/SUM(D43:D52)/C10 -> 69864.096 | G20: =G18/SUM(D43:D52)/C10 -> 19.680027
C21: Gross Margin | D21: =(((F18-C57-C59-C61-C7*'Parámetros'!L8*F18)-IF(C8=1,2.4%,0)*F18)/F18) -> 0.4477815
B23: ='Parámetros'!B149 -> Considerar como mínimo por cada Dev: PM:33%, QA:20%, Diseño:10%
E25: =SUM(E27:E34) -> 1.8
B26: Equipo | C26: Salario Base | D26: Tipo Contrato | E26: Dedicación | F26: Costo mensual | G26: Costo total | H26: % Tiempo Equipo
A27: =IFERROR(__xludf.DUMMYFUNCTION("COUNTIF(SPLIT(B27,"" ""),""Developer"")"),0.0) -> 0 | B27: Forward Deployed Pruduct experience | C27: =IFERROR(VLOOKUP(B27,'Parámetros'!A$1:B113,2, FALSE),"") -> 5000000 | D27: P. Servicios | E27: 0.5 | F27: =+IFERROR(IF(D27="Nómina",C27*1.38352,C27),"")*E27 -> 2500000 | G27: =F27*C$10 -> 10000000 | H27: =F27/(AVERAGE('Parámetros'!$F$5:$F$6)+$F$37) -> 0.0072159078
A28: =IFERROR(__xludf.DUMMYFUNCTION("COUNTIF(SPLIT(B28,"" ""),""Developer"")"),0.0) -> 0 | B28: Forward Deployed Enginnier | C28: =IFERROR(VLOOKUP(B28,'Parámetros'!A$1:B114,2, FALSE),"") -> 7000000 | D28: P. Servicios | E28: 1 | F28: =+IFERROR(IF(D28="Nómina",C28*1.38352,C28),"")*E28 -> 7000000 | G28: =F28*C$10 -> 28000000 | H28: =G28/(AVERAGE('Parámetros'!$F$5:$F$6)+$F$37) -> 0.080818167
A29: =IFERROR(__xludf.DUMMYFUNCTION("COUNTIF(SPLIT(B29,"" ""),""Developer"")"),0.0) -> 0 | B29: Tech Leald Orchestaror | C29: =IFERROR(VLOOKUP(B29,'Parámetros'!A$1:B115,2, FALSE),"") -> 10000000 | D29: P. Servicios | E29: 0.3 | F29: =+IFERROR(IF(D29="Nómina",C29*1.38352,C29),"")*E29 -> 3000000 | G29: =F29*C$10 -> 12000000 | H29: =G29/(AVERAGE('Parámetros'!$F$5:$F$6)+$F$37) -> 0.034636357
A30: =IFERROR(__xludf.DUMMYFUNCTION("COUNTIF(SPLIT(B30,"" ""),""Developer"")"),0.0) -> 0 | C30: =IFERROR(VLOOKUP(B30,'Parámetros'!A$1:B116,2, FALSE),"") | F30: =+IFERROR(IF(D30="Nómina",C30*1.38352,C30),"")*E30*105% -> 0 | G30: =F30*C$10 -> 0 | H30: =G30/(AVERAGE('Parámetros'!$F$5:$F$6)+$F$37) -> 0
A31: =IFERROR(__xludf.DUMMYFUNCTION("COUNTIF(SPLIT(B31,"" ""),""Developer"")"),0.0) -> 0
A32: =IFERROR(__xludf.DUMMYFUNCTION("COUNTIF(SPLIT(B32,"" ""),""Developer"")"),0.0) -> 0 | F32: =+IFERROR(IF(D32="Nómina",C32*1.38352,C32),"")*E32*105% -> 0 | G32: =F32*C$10 -> 0 | H32: =G32/(AVERAGE('Parámetros'!$F$5:$F$6)+$F$37) -> 0
A33: =IFERROR(__xludf.DUMMYFUNCTION("COUNTIF(SPLIT(B33,"" ""),""Developer"")"),0.0) -> 0 | F33: =+IFERROR(IF(D33="Nómina",C33*1.38352,C33),"")*E33*105% -> 0 | G33: =F33*C$10 -> 0 | H33: =G33/(AVERAGE('Parámetros'!$F$5:$F$6)+$F$37) -> 0
A34: =IFERROR(__xludf.DUMMYFUNCTION("COUNTIF(SPLIT(B34,"" ""),""Developer"")"),0.0) -> 0 | C34: =IFERROR(VLOOKUP(B34,'Parámetros'!A$1:B120,2, FALSE),"") | F34: =+IFERROR(IF(D34="Nómina",C34*1.38352,C34),"")*E34*105% -> 0 | G34: =F34*C$10 -> 0 | H34: =G34/(AVERAGE('Parámetros'!$F$5:$F$6)+$F$37) -> 0
C35: =IFERROR(VLOOKUP(B35,'Parámetros'!A$1:B121,2, FALSE),"") | F35: =+IFERROR(IF(D35="Nómina",C35*1.38352,C35),"")*E35*105% -> 0 | G35: =F35*C$10 -> 0 | H35: =G35/(AVERAGE('Parámetros'!$F$5:$F$6)+$F$37) -> 0
C36: =IFERROR(VLOOKUP(B36,'Parámetros'!A$1:B122,2, FALSE),"") | F36: =+IFERROR(IF(D36="Nómina",C36*1.38352,C36),"")*E36*105% -> 0 | G36: =F36*C$10 -> 0 | H36: =G36/(AVERAGE('Parámetros'!$F$5:$F$6)+$F$37) -> 0
F37: =SUM(F27:F36) -> 12500000 | G37: =SUM(G27:G36) -> 50000000 | H37: =SUM(H27:H36) -> 0.12267043
C40: Gross Margin | D40: USD
B42: Equipo | C42: Dedicación | D42: Capacidad Horas | E42: Precio x Hora | F42: Precio Total
B43: =B27 -> Forward Deployed Pruduct experience | C43: =E27 -> 0.5 | D43: =C43*180 -> 90 | E43: =IFERROR((IF($C$40="Gross Margin",F27/$F$37*$F$12,IF($C$40="Net Margin",F27/$F$37*$F$18,"Error")))/D43,"")/IF($D$40="USD",'Parámetros'!$L$3,1)/$C$10 -> 12.620526 | F43: =E43*D43 -> 1135.8473
B44: =B28 -> Forward Deployed Enginnier | C44: =E28 -> 1 | D44: =C44*180 -> 180 | E44: =IFERROR((IF($C$40="Gross Margin",F28/$F$37*$F$12,IF($C$40="Net Margin",F28/$F$37*$F$18,"Error")))/D44,"")/IF($D$40="USD",'Parámetros'!$L$3,1)/$C$10 -> 17.668736 | F44: =E44*D44 -> 3180.3726
B45: =B29 -> Tech Leald Orchestaror | C45: =E29 -> 0.3 | D45: =C45*180 -> 54 | E45: =IFERROR((IF($C$40="Gross Margin",F29/$F$37*$F$12,IF($C$40="Net Margin",F29/$F$37*$F$18,"Error")))/D45,"")/IF($D$40="USD",'Parámetros'!$L$3,1)/$C$10 -> 25.241052 | F45: =E45*D45 -> 1363.0168
B46: =B30 | C46: =E30 | D46: =C46*180 -> 0 | E46: =IFERROR((IF($C$40="Gross Margin",F30/$F$37*$F$12,IF($C$40="Net Margin",F30/$F$37*$F$18,"Error")))/D46,"")/IF($D$40="USD",'Parámetros'!$L$3,1)/$C$10 -> 0 | F46: =E46*D46 -> 0
B47: =B31 | C47: =E31 | D47: =C47*180 -> 0 | E47: =IFERROR((IF($C$40="Gross Margin",F31/$F$37*$F$12,IF($C$40="Net Margin",F31/$F$37*$F$18,"Error")))/D47,"")/IF($D$40="USD",'Parámetros'!$L$3,1)/$C$10 -> 0 | F47: =E47*D47 -> 0
B48: =B32 | C48: =E32 | D48: =C48*180 -> 0 | E48: =IFERROR((IF($C$40="Gross Margin",F32/$F$37*$F$12,IF($C$40="Net Margin",F32/$F$37*$F$18,"Error")))/D48,"")/IF($D$40="USD",'Parámetros'!$L$3,1) -> 0 | F48: =E48*D48 -> 0
B49: =B33 | C49: =E33 | D49: =C49*180 -> 0 | E49: =IFERROR((IF($C$40="Gross Margin",F33/$F$37*$F$12,IF($C$40="Net Margin",F33/$F$37*$F$18,"Error")))/D49,"")/IF($D$40="USD",'Parámetros'!$L$3,1) -> 0 | F49: =E49*D49 -> 0
B50: =B34 | C50: =E34 | D50: =C50*180 -> 0 | E50: =IFERROR((IF($C$40="Gross Margin",F34/$F$37*$F$12,IF($C$40="Net Margin",F34/$F$37*$F$18,"Error")))/D50,"")/IF($D$40="USD",'Parámetros'!$L$3,1) -> 0 | F50: =E50*D50 -> 0
B51: =B35 | C51: =E35 | D51: =C51*180 -> 0 | E51: =IFERROR((IF($C$40="Gross Margin",F35/$F$37*$F$12,IF($C$40="Net Margin",F35/$F$37*$F$18,"Error")))/D51,"")/IF($D$40="USD",'Parámetros'!$L$3,1) -> 0 | F51: =E51*D51 -> 0
B52: =B36 | C52: =E36 | D52: =C52*180 -> 0 | E52: =IFERROR((IF($C$40="Gross Margin",F36/$F$37*$F$12,IF($C$40="Net Margin",F36/$F$37*$F$18,"Error")))/D52,"")/IF($D$40="USD",'Parámetros'!$L$3,1) -> 0 | F52: =E52*D52 -> 0
E53: Total | F53: =SUM(F43:F52) -> 5679.2367
E54: Validación | F54: =F53-G13 -> 0
B56: Resumen | C56: Total | D56: Mensual
B57: Costo Equipo | C57: =G37 -> 50000000 | D57: =C57/C$10 -> 12500000
B58: Costo + Gasto Fijo | C58: =C60+C61+C59 -> 17283149 | D58: =C58/C$10 -> 4320787.3
B59: Computador Herramientas Trabajo | D59: =C59/C$10 -> 0
B60: - ROP Gasto | C60: =H37*AVERAGE('Parámetros'!G8:G9)*IF(C2="Network",15%,100%)*IF(C2="Enterprise",40%,100%) -> 17283149 | D60: =C60/C$10 -> 4320787.3
B61: - ROP Costo Fijo | D61: =C61/C$10 -> 0
B62: T. C + G Equipo | C62: =C57+C58 -> 67283149 | D62: =C62/C$10 -> 16820787
B63: Costo Total Interno Compañía | C63: =C57+C59+C61 -> 50000000 | D63: =D57+D59+D61 -> 12500000

Sheet Equipo UX + Pm
B2: Línea de Negocio | C2: Equipo Dedicado
B3: ¿Tipo de contrato vendedor? | C3: Deel/Ontop
B4: Comisión vendedor | C4: 0.05
B5: ¿Cuál es la fuente de tu lead? | C5: Directo
B6: Perfil Network | C6: Perfil Sr.
B7: ¿Pago con TC? | C7: 0 | F7: Gross Margin Meta | G7: =VLOOKUP($C$2,'Parámetros'!$A$118:$D$124,3,0) -> 0.4
B8: Factoring | C8: 0 | F8: =IF(D13>=G7,"Dentro del margen","¡Por debajo del margen!") -> ¡Por debajo del margen!
B9: Tecnologia
B10: Tiempo Duración: Mes | C10: 4
F11: COP | G11: USD
B12: Jugar con Gross Margin | C12: Comisión Venta | D12: =F12*C4+IFS(C5="Cold Calling",2%*138.3522%,C5="Mercadeo",2%*101%,C5="Network - Cold Calling",2%*138.3522%,C5="Referido Imagine",5%*138.3522%,C5="Directo",0)*F12+ifs(AND(C6="Perfil Jr.",C2="Network"),200000,AND(C6="Perfil Sr.",C2="Network"),350000,AND(C2="Network",C6="Perfil Semi Senior"), 600000,C2="Proyecto",1,C2="Equipo dedicado",1,C2="Servidores",1,C2="Enterprise",1,C2="Descubrimiento",1) -> 4370968.7 | E12: Precio Total | F12: =((C61+C57+C59)/((1-D13-'Parámetros'!L8*C7)))*IF(C8=1,102.4%,1) -> 87419355 | G12: =F12/'Parámetros'!$L$3 -> 24625.17 | I12: 160 | J12: 1
C13: Gross Margin | D13: 0.38 | E13: Precio mensual | F13: =F12/C10 -> 21854839 | G13: =F13/'Parámetros'!$L$3 -> 6156.2926 | I13: 12 | J13: =I13*J12/I12 -> 0.075
C14: ICA | D14: =F12*'Parámetros'!L5 -> 603193.55 | E14: Precio/Horas | F14: =F12/SUM(D43:D52)/C10 -> 60707.885 | G14: =G12/SUM(D43:D52)/C10 -> 17.100813
C15: NET Margin | D15: =(F12-C62-D14-D12-C7*'Parámetros'!L8*F12-IF(C8=1,2.4%,0)*F12)/F12 -> 0.10651467 | I15: 12 horas | J15: 3127889.9
I16: 20 horas | J16: 5044796.6
B18: Jugar con Net Margin | C18: Comisión Venta | D18: =F18*C4+IFS(C5="Cold Calling",2%*138.3522%,C5="Mercadeo",2%*101%,C5="Network - Cold Calling",2%*138.3522%,C5="Referido Imagine",5%*138.3522%,C5="Directo",0)*F18 -> 4920855.1 | E18: Precio Total | F18: =+C62/((1-IFS(C5="Cold Calling",2%*138.3522%,C5="Mercadeo",2%*101%,C5="Network - Cold Calling",2%*138.3522%,C5="Referido Imagine",5%*138.3522%,C5="Directo",0)-C4-D19-'Parámetros'!L5-C7*'Parámetros'!L8))*IF(C8=1,102.4%,1) -> 98417102 | G18: =F18/'Parámetros'!L3 -> 27723.127
C19: NET Margin | D19: 0.2 | E19: Precio mensual | F19: =F18/C10 -> 24604276 | G19: =G18/C10 -> 6930.7819
C20: ICA | D20: =F18*'Parámetros'!L5 -> 679078.01 | E20: Precio/Horas | F20: =F18/SUM(D43:D52)/C10 -> 68345.21 | G20: =G18/SUM(D43:D52)/C10 -> 19.252172
C21: Gross Margin | D21: =(((F18-C57-C59-C61-C7*'Parámetros'!L8*F18)-IF(C8=1,2.4%,0)*F18)/F18) -> 0.44928271
B23: ='Parámetros'!B149 -> Considerar como mínimo por cada Dev: PM:33%, QA:20%, Diseño:10%
E25: =SUM(E27:E34) -> 2
B26: Equipo | C26: Salario Base | D26: Tipo Contrato | E26: Dedicación | F26: Costo mensual | G26: Costo total | H26: % Tiempo Equipo
A27: =IFERROR(__xludf.DUMMYFUNCTION("COUNTIF(SPLIT(B27,"" ""),""Developer"")"),0.0) -> 0 | B27: Forward Deployed Pruduct experience | C27: =IFERROR(VLOOKUP(B27,'Parámetros'!A$1:B113,2, FALSE),"") -> 5000000 | D27: P. Servicios | E27: 0.5 | F27: =+IFERROR(IF(D27="Nómina",C27*1.38352,C27),"")*E27 -> 2500000 | G27: =F27*C$10 -> 10000000 | H27: =F27/(AVERAGE('Parámetros'!$F$5:$F$6)+$F$37) -> 0.0071941047
A28: =IFERROR(__xludf.DUMMYFUNCTION("COUNTIF(SPLIT(B28,"" ""),""Developer"")"),0.0) -> 0 | B28: Forward Deployed Enginnier | C28: =IFERROR(VLOOKUP(B28,'Parámetros'!A$1:B114,2, FALSE),"") -> 7000000 | D28: P. Servicios | E28: 1 | F28: =+IFERROR(IF(D28="Nómina",C28*1.38352,C28),"")*E28 -> 7000000 | G28: =F28*C$10 -> 28000000 | H28: =G28/(AVERAGE('Parámetros'!$F$5:$F$6)+$F$37) -> 0.080573973
A29: =IFERROR(__xludf.DUMMYFUNCTION("COUNTIF(SPLIT(B29,"" ""),""Developer"")"),0.0) -> 0 | B29: Tech Leald Orchestaror | C29: =IFERROR(VLOOKUP(B29,'Parámetros'!A$1:B115,2, FALSE),"") -> 10000000 | D29: P. Servicios | E29: 0.3 | F29: =+IFERROR(IF(D29="Nómina",C29*1.38352,C29),"")*E29 -> 3000000 | G29: =F29*C$10 -> 12000000 | H29: =G29/(AVERAGE('Parámetros'!$F$5:$F$6)+$F$37) -> 0.034531703
A30: =IFERROR(__xludf.DUMMYFUNCTION("COUNTIF(SPLIT(B30,"" ""),""Developer"")"),0.0) -> 0 | B30: Forward Deployed Product manager | C30: =IFERROR(VLOOKUP(B30,'Parámetros'!A$1:B116,2, FALSE),"") -> 5000000 | D30: P. Servicios | E30: 0.2 | F30: =+IFERROR(IF(D30="Nómina",C30*1.38352,C30),"")*E30*105% -> 1050000 | G30: =F30*C$10 -> 4200000 | H30: =G30/(AVERAGE('Parámetros'!$F$5:$F$6)+$F$37) -> 0.012086096
A31: =IFERROR(__xludf.DUMMYFUNCTION("COUNTIF(SPLIT(B31,"" ""),""Developer"")"),0.0) -> 0
A32: =IFERROR(__xludf.DUMMYFUNCTION("COUNTIF(SPLIT(B32,"" ""),""Developer"")"),0.0) -> 0 | F32: =+IFERROR(IF(D32="Nómina",C32*1.38352,C32),"")*E32*105% -> 0 | G32: =F32*C$10 -> 0 | H32: =G32/(AVERAGE('Parámetros'!$F$5:$F$6)+$F$37) -> 0
A33: =IFERROR(__xludf.DUMMYFUNCTION("COUNTIF(SPLIT(B33,"" ""),""Developer"")"),0.0) -> 0 | F33: =+IFERROR(IF(D33="Nómina",C33*1.38352,C33),"")*E33*105% -> 0 | G33: =F33*C$10 -> 0 | H33: =G33/(AVERAGE('Parámetros'!$F$5:$F$6)+$F$37) -> 0
A34: =IFERROR(__xludf.DUMMYFUNCTION("COUNTIF(SPLIT(B34,"" ""),""Developer"")"),0.0) -> 0 | C34: =IFERROR(VLOOKUP(B34,'Parámetros'!A$1:B120,2, FALSE),"") | F34: =+IFERROR(IF(D34="Nómina",C34*1.38352,C34),"")*E34*105% -> 0 | G34: =F34*C$10 -> 0 | H34: =G34/(AVERAGE('Parámetros'!$F$5:$F$6)+$F$37) -> 0
C35: =IFERROR(VLOOKUP(B35,'Parámetros'!A$1:B121,2, FALSE),"") | F35: =+IFERROR(IF(D35="Nómina",C35*1.38352,C35),"")*E35*105% -> 0 | G35: =F35*C$10 -> 0 | H35: =G35/(AVERAGE('Parámetros'!$F$5:$F$6)+$F$37) -> 0
C36: =IFERROR(VLOOKUP(B36,'Parámetros'!A$1:B122,2, FALSE),"") | F36: =+IFERROR(IF(D36="Nómina",C36*1.38352,C36),"")*E36*105% -> 0 | G36: =F36*C$10 -> 0 | H36: =G36/(AVERAGE('Parámetros'!$F$5:$F$6)+$F$37) -> 0
F37: =SUM(F27:F36) -> 13550000 | G37: =SUM(G27:G36) -> 54200000 | H37: =SUM(H27:H36) -> 0.13438588
C40: Gross Margin | D40: USD
B42: Equipo | C42: Dedicación | D42: Capacidad Horas | E42: Precio x Hora | F42: Precio Total
B43: =B27 -> Forward Deployed Pruduct experience | C43: =E27 -> 0.5 | D43: =C43*180 -> 90 | E43: =IFERROR((IF($C$40="Gross Margin",F27/$F$37*$F$12,IF($C$40="Net Margin",F27/$F$37*$F$18,"Error")))/D43,"")/IF($D$40="USD",'Parámetros'!$L$3,1)/$C$10 -> 12.620526 | F43: =E43*D43 -> 1135.8473
B44: =B28 -> Forward Deployed Enginnier | C44: =E28 -> 1 | D44: =C44*180 -> 180 | E44: =IFERROR((IF($C$40="Gross Margin",F28/$F$37*$F$12,IF($C$40="Net Margin",F28/$F$37*$F$18,"Error")))/D44,"")/IF($D$40="USD",'Parámetros'!$L$3,1)/$C$10 -> 17.668736 | F44: =E44*D44 -> 3180.3726
B45: =B29 -> Tech Leald Orchestaror | C45: =E29 -> 0.3 | D45: =C45*180 -> 54 | E45: =IFERROR((IF($C$40="Gross Margin",F29/$F$37*$F$12,IF($C$40="Net Margin",F29/$F$37*$F$18,"Error")))/D45,"")/IF($D$40="USD",'Parámetros'!$L$3,1)/$C$10 -> 25.241052 | F45: =E45*D45 -> 1363.0168
B46: =B30 -> Forward Deployed Product manager | C46: =E30 -> 0.2 | D46: =C46*180 -> 36 | E46: =IFERROR((IF($C$40="Gross Margin",F30/$F$37*$F$12,IF($C$40="Net Margin",F30/$F$37*$F$18,"Error")))/D46,"")/IF($D$40="USD",'Parámetros'!$L$3,1)/$C$10 -> 13.251552 | F46: =E46*D46 -> 477.05588
B47: =B31 | C47: =E31 | D47: =C47*180 -> 0 | E47: =IFERROR((IF($C$40="Gross Margin",F31/$F$37*$F$12,IF($C$40="Net Margin",F31/$F$37*$F$18,"Error")))/D47,"")/IF($D$40="USD",'Parámetros'!$L$3,1)/$C$10 -> 0 | F47: =E47*D47 -> 0
B48: =B32 | C48: =E32 | D48: =C48*180 -> 0 | E48: =IFERROR((IF($C$40="Gross Margin",F32/$F$37*$F$12,IF($C$40="Net Margin",F32/$F$37*$F$18,"Error")))/D48,"")/IF($D$40="USD",'Parámetros'!$L$3,1) -> 0 | F48: =E48*D48 -> 0
B49: =B33 | C49: =E33 | D49: =C49*180 -> 0 | E49: =IFERROR((IF($C$40="Gross Margin",F33/$F$37*$F$12,IF($C$40="Net Margin",F33/$F$37*$F$18,"Error")))/D49,"")/IF($D$40="USD",'Parámetros'!$L$3,1) -> 0 | F49: =E49*D49 -> 0
B50: =B34 | C50: =E34 | D50: =C50*180 -> 0 | E50: =IFERROR((IF($C$40="Gross Margin",F34/$F$37*$F$12,IF($C$40="Net Margin",F34/$F$37*$F$18,"Error")))/D50,"")/IF($D$40="USD",'Parámetros'!$L$3,1) -> 0 | F50: =E50*D50 -> 0
B51: =B35 | C51: =E35 | D51: =C51*180 -> 0 | E51: =IFERROR((IF($C$40="Gross Margin",F35/$F$37*$F$12,IF($C$40="Net Margin",F35/$F$37*$F$18,"Error")))/D51,"")/IF($D$40="USD",'Parámetros'!$L$3,1) -> 0 | F51: =E51*D51 -> 0
B52: =B36 | C52: =E36 | D52: =C52*180 -> 0 | E52: =IFERROR((IF($C$40="Gross Margin",F36/$F$37*$F$12,IF($C$40="Net Margin",F36/$F$37*$F$18,"Error")))/D52,"")/IF($D$40="USD",'Parámetros'!$L$3,1) -> 0 | F52: =E52*D52 -> 0
E53: Total | F53: =SUM(F43:F52) -> 6156.2926
E54: Validación | F54: =F53-G13 -> 0
B56: Resumen | C56: Total | D56: Mensual
B57: Costo Equipo | C57: =G37 -> 54200000 | D57: =C57/C$10 -> 13550000
B58: Costo + Gasto Fijo | C58: =C60+C61+C59 -> 18933749 | D58: =C58/C$10 -> 4733437.2
B59: Computador Herramientas Trabajo | D59: =C59/C$10 -> 0
B60: - ROP Gasto | C60: =H37*AVERAGE('Parámetros'!G8:G9)*IF(C2="Network",15%,100%)*IF(C2="Enterprise",40%,100%) -> 18933749 | D60: =C60/C$10 -> 4733437.2
B61: - ROP Costo Fijo | D61: =C61/C$10 -> 0
B62: T. C + G Equipo | C62: =C57+C58 -> 73133749 | D62: =C62/C$10 -> 18283437
B63: Costo Total Interno Compañía | C63: =C57+C59+C61 -> 54200000 | D63: =D57+D59+D61 -> 13550000

Sheet Equipo dos FDE
B2: Línea de Negocio | C2: Equipo Dedicado
B3: ¿Tipo de contrato vendedor? | C3: Deel/Ontop
B4: Comisión vendedor | C4: 0.05
B5: ¿Cuál es la fuente de tu lead? | C5: Directo
B6: Perfil Network | C6: Perfil Sr.
B7: ¿Pago con TC? | C7: 0 | F7: Gross Margin Meta | G7: =VLOOKUP($C$2,'Parámetros'!$A$118:$D$124,3,0) -> 0.4
B8: Factoring | C8: 0 | F8: =IF(D13>=G7,"Dentro del margen","¡Por debajo del margen!") -> ¡Por debajo del margen!
B9: Tecnologia
B10: Tiempo Duración: Mes | C10: 4
F11: COP | G11: USD
B12: Jugar con Gross Margin | C12: Comisión Venta | D12: =F12*C4+IFS(C5="Cold Calling",2%*138.3522%,C5="Mercadeo",2%*101%,C5="Network - Cold Calling",2%*138.3522%,C5="Referido Imagine",5%*138.3522%,C5="Directo",0)*F12+ifs(AND(C6="Perfil Jr.",C2="Network"),200000,AND(C6="Perfil Sr.",C2="Network"),350000,AND(C2="Network",C6="Perfil Semi Senior"), 600000,C2="Proyecto",1,C2="Equipo dedicado",1,C2="Servidores",1,C2="Enterprise",1,C2="Descubrimiento",1) -> 6629033.3 | E12: Precio Total | F12: =((C61+C57+C59)/((1-D13-'Parámetros'!L8*C7)))*IF(C8=1,102.4%,1) -> 1.3258065e+08 | G12: =F12/'Parámetros'!$L$3 -> 37346.661 | I12: 160 | J12: 1
C13: Gross Margin | D13: 0.38 | E13: Precio mensual | F13: =F12/C10 -> 33145161 | G13: =F13/'Parámetros'!$L$3 -> 9336.6652 | I13: 12 | J13: =I13*J12/I12 -> 0.075
C14: ICA | D14: =F12*'Parámetros'!L5 -> 914806.45 | E14: Precio/Horas | F14: =F12/SUM(D43:D52)/C10 -> 61379.928 | G14: =G12/SUM(D43:D52)/C10 -> 17.290121
C15: NET Margin | D15: =(F12-C62-D14-D12-C7*'Parámetros'!L8*F12-IF(C8=1,2.4%,0)*F12)/F12 -> 0.099176871 | I15: 12 horas | J15: 3127889.9
I16: 20 horas | J16: 5044796.6
B18: Jugar con Net Margin | C18: Comisión Venta | D18: =F18*C4+IFS(C5="Cold Calling",2%*138.3522%,C5="Mercadeo",2%*101%,C5="Network - Cold Calling",2%*138.3522%,C5="Referido Imagine",5%*138.3522%,C5="Directo",0)*F18 -> 7528453.2 | E18: Precio Total | F18: =+C62/((1-IFS(C5="Cold Calling",2%*138.3522%,C5="Mercadeo",2%*101%,C5="Network - Cold Calling",2%*138.3522%,C5="Referido Imagine",5%*138.3522%,C5="Directo",0)-C4-D19-'Parámetros'!L5-C7*'Parámetros'!L8))*IF(C8=1,102.4%,1) -> 1.5056906e+08 | G18: =F18/'Parámetros'!L3 -> 42413.821
C19: NET Margin | D19: 0.2 | E19: Precio mensual | F19: =F18/C10 -> 37642266 | G19: =G18/C10 -> 10603.455
C20: ICA | D20: =F18*'Parámetros'!L5 -> 1038926.5 | E20: Precio/Horas | F20: =F18/SUM(D43:D52)/C10 -> 69707.9 | G20: =G18/SUM(D43:D52)/C10 -> 19.636028
C21: Gross Margin | D21: =(((F18-C57-C59-C61-C7*'Parámetros'!L8*F18)-IF(C8=1,2.4%,0)*F18)/F18) -> 0.45407113
B23: ='Parámetros'!B149 -> Considerar como mínimo por cada Dev: PM:33%, QA:20%, Diseño:10%
E25: =SUM(E27:E34) -> 3
B26: Equipo | C26: Salario Base | D26: Tipo Contrato | E26: Dedicación | F26: Costo mensual | G26: Costo total | H26: % Tiempo Equipo
A27: =IFERROR(__xludf.DUMMYFUNCTION("COUNTIF(SPLIT(B27,"" ""),""Developer"")"),0.0) -> 0 | B27: Forward Deployed Pruduct experience | C27: =IFERROR(VLOOKUP(B27,'Parámetros'!A$1:B113,2, FALSE),"") -> 5000000 | D27: P. Servicios | E27: 0.5 | F27: =+IFERROR(IF(D27="Nómina",C27*1.38352,C27),"")*E27 -> 2500000 | G27: =F27*C$10 -> 10000000 | H27: =F27/(AVERAGE('Parámetros'!$F$5:$F$6)+$F$37) -> 0.0070520518
A28: =IFERROR(__xludf.DUMMYFUNCTION("COUNTIF(SPLIT(B28,"" ""),""Developer"")"),0.0) -> 0 | B28: Forward Deployed Enginnier | C28: =IFERROR(VLOOKUP(B28,'Parámetros'!A$1:B114,2, FALSE),"") -> 7000000 | D28: P. Servicios | E28: 1 | F28: =+IFERROR(IF(D28="Nómina",C28*1.38352,C28),"")*E28 -> 7000000 | G28: =F28*C$10 -> 28000000 | H28: =G28/(AVERAGE('Parámetros'!$F$5:$F$6)+$F$37) -> 0.07898298
A29: =IFERROR(__xludf.DUMMYFUNCTION("COUNTIF(SPLIT(B29,"" ""),""Developer"")"),0.0) -> 0 | B29: Tech Leald Orchestaror | C29: =IFERROR(VLOOKUP(B29,'Parámetros'!A$1:B115,2, FALSE),"") -> 10000000 | D29: P. Servicios | E29: 0.3 | F29: =+IFERROR(IF(D29="Nómina",C29*1.38352,C29),"")*E29 -> 3000000 | G29: =F29*C$10 -> 12000000 | H29: =G29/(AVERAGE('Parámetros'!$F$5:$F$6)+$F$37) -> 0.033849849
A30: =IFERROR(__xludf.DUMMYFUNCTION("COUNTIF(SPLIT(B30,"" ""),""Developer"")"),0.0) -> 0 | B30: Forward Deployed Product manager | C30: =IFERROR(VLOOKUP(B30,'Parámetros'!A$1:B116,2, FALSE),"") -> 5000000 | D30: P. Servicios | E30: 0.2 | F30: =+IFERROR(IF(D30="Nómina",C30*1.38352,C30),"")*E30*105% -> 1050000 | G30: =F30*C$10 -> 4200000 | H30: =G30/(AVERAGE('Parámetros'!$F$5:$F$6)+$F$37) -> 0.011847447
A31: =IFERROR(__xludf.DUMMYFUNCTION("COUNTIF(SPLIT(B31,"" ""),""Developer"")"),0.0) -> 0 | B31: Forward Deployed Enginnier | C31: =IFERROR(VLOOKUP(B31,'Parámetros'!A$1:B117,2, FALSE),"") -> 7000000 | D31: P. Servicios | E31: 1 | F31: =+IFERROR(IF(D31="Nómina",C31*1.38352,C31),"")*E31 -> 7000000 | G31: =F31*C$10 -> 28000000 | H31: =G31/(AVERAGE('Parámetros'!$F$5:$F$6)+$F$37) -> 0.07898298
A32: =IFERROR(__xludf.DUMMYFUNCTION("COUNTIF(SPLIT(B32,"" ""),""Developer"")"),0.0) -> 0 | F32: =+IFERROR(IF(D32="Nómina",C32*1.38352,C32),"")*E32*105% -> 0 | G32: =F32*C$10 -> 0 | H32: =G32/(AVERAGE('Parámetros'!$F$5:$F$6)+$F$37) -> 0
A33: =IFERROR(__xludf.DUMMYFUNCTION("COUNTIF(SPLIT(B33,"" ""),""Developer"")"),0.0) -> 0 | F33: =+IFERROR(IF(D33="Nómina",C33*1.38352,C33),"")*E33*105% -> 0 | G33: =F33*C$10 -> 0 | H33: =G33/(AVERAGE('Parámetros'!$F$5:$F$6)+$F$37) -> 0
A34: =IFERROR(__xludf.DUMMYFUNCTION("COUNTIF(SPLIT(B34,"" ""),""Developer"")"),0.0) -> 0 | C34: =IFERROR(VLOOKUP(B34,'Parámetros'!A$1:B120,2, FALSE),"") | F34: =+IFERROR(IF(D34="Nómina",C34*1.38352,C34),"")*E34*105% -> 0 | G34: =F34*C$10 -> 0 | H34: =G34/(AVERAGE('Parámetros'!$F$5:$F$6)+$F$37) -> 0
C35: =IFERROR(VLOOKUP(B35,'Parámetros'!A$1:B121,2, FALSE),"") | F35: =+IFERROR(IF(D35="Nómina",C35*1.38352,C35),"")*E35*105% -> 0 | G35: =F35*C$10 -> 0 | H35: =G35/(AVERAGE('Parámetros'!$F$5:$F$6)+$F$37) -> 0
C36: =IFERROR(VLOOKUP(B36,'Parámetros'!A$1:B122,2, FALSE),"") | F36: =+IFERROR(IF(D36="Nómina",C36*1.38352,C36),"")*E36*105% -> 0 | G36: =F36*C$10 -> 0 | H36: =G36/(AVERAGE('Parámetros'!$F$5:$F$6)+$F$37) -> 0
F37: =SUM(F27:F36) -> 20550000 | G37: =SUM(G27:G36) -> 82200000 | H37: =SUM(H27:H36) -> 0.21071531
C40: Gross Margin | D40: USD
B42: Equipo | C42: Dedicación | D42: Capacidad Horas | E42: Precio x Hora | F42: Precio Total
B43: =B27 -> Forward Deployed Pruduct experience | C43: =E27 -> 0.5 | D43: =C43*180 -> 90 | E43: =IFERROR((IF($C$40="Gross Margin",F27/$F$37*$F$12,IF($C$40="Net Margin",F27/$F$37*$F$18,"Error")))/D43,"")/IF($D$40="USD",'Parámetros'!$L$3,1)/$C$10 -> 12.620526 | F43: =E43*D43 -> 1135.8473
B44: =B28 -> Forward Deployed Enginnier | C44: =E28 -> 1 | D44: =C44*180 -> 180 | E44: =IFERROR((IF($C$40="Gross Margin",F28/$F$37*$F$12,IF($C$40="Net Margin",F28/$F$37*$F$18,"Error")))/D44,"")/IF($D$40="USD",'Parámetros'!$L$3,1)/$C$10 -> 17.668736 | F44: =E44*D44 -> 3180.3726
B45: =B29 -> Tech Leald Orchestaror | C45: =E29 -> 0.3 | D45: =C45*180 -> 54 | E45: =IFERROR((IF($C$40="Gross Margin",F29/$F$37*$F$12,IF($C$40="Net Margin",F29/$F$37*$F$18,"Error")))/D45,"")/IF($D$40="USD",'Parámetros'!$L$3,1)/$C$10 -> 25.241052 | F45: =E45*D45 -> 1363.0168
B46: =B30 -> Forward Deployed Product manager | C46: =E30 -> 0.2 | D46: =C46*180 -> 36 | E46: =IFERROR((IF($C$40="Gross Margin",F30/$F$37*$F$12,IF($C$40="Net Margin",F30/$F$37*$F$18,"Error")))/D46,"")/IF($D$40="USD",'Parámetros'!$L$3,1)/$C$10 -> 13.251552 | F46: =E46*D46 -> 477.05588
B47: =B31 -> Forward Deployed Enginnier | C47: =E31 -> 1 | D47: =C47*180 -> 180 | E47: =IFERROR((IF($C$40="Gross Margin",F31/$F$37*$F$12,IF($C$40="Net Margin",F31/$F$37*$F$18,"Error")))/D47,"")/IF($D$40="USD",'Parámetros'!$L$3,1)/$C$10 -> 17.668736 | F47: =E47*D47 -> 3180.3726
B48: =B32 | C48: =E32 | D48: =C48*180 -> 0 | E48: =IFERROR((IF($C$40="Gross Margin",F32/$F$37*$F$12,IF($C$40="Net Margin",F32/$F$37*$F$18,"Error")))/D48,"")/IF($D$40="USD",'Parámetros'!$L$3,1) -> 0 | F48: =E48*D48 -> 0
B49: =B33 | C49: =E33 | D49: =C49*180 -> 0 | E49: =IFERROR((IF($C$40="Gross Margin",F33/$F$37*$F$12,IF($C$40="Net Margin",F33/$F$37*$F$18,"Error")))/D49,"")/IF($D$40="USD",'Parámetros'!$L$3,1) -> 0 | F49: =E49*D49 -> 0
B50: =B34 | C50: =E34 | D50: =C50*180 -> 0 | E50: =IFERROR((IF($C$40="Gross Margin",F34/$F$37*$F$12,IF($C$40="Net Margin",F34/$F$37*$F$18,"Error")))/D50,"")/IF($D$40="USD",'Parámetros'!$L$3,1) -> 0 | F50: =E50*D50 -> 0
B51: =B35 | C51: =E35 | D51: =C51*180 -> 0 | E51: =IFERROR((IF($C$40="Gross Margin",F35/$F$37*$F$12,IF($C$40="Net Margin",F35/$F$37*$F$18,"Error")))/D51,"")/IF($D$40="USD",'Parámetros'!$L$3,1) -> 0 | F51: =E51*D51 -> 0
B52: =B36 | C52: =E36 | D52: =C52*180 -> 0 | E52: =IFERROR((IF($C$40="Gross Margin",F36/$F$37*$F$12,IF($C$40="Net Margin",F36/$F$37*$F$18,"Error")))/D52,"")/IF($D$40="USD",'Parámetros'!$L$3,1) -> 0 | F52: =E52*D52 -> 0
E53: Total | F53: =SUM(F43:F52) -> 9336.6652
E54: Validación | F54: =F53-G13 -> 0
B56: Resumen | C56: Total | D56: Mensual
B57: Costo Equipo | C57: =G37 -> 82200000 | D57: =C57/C$10 -> 20550000
B58: Costo + Gasto Fijo | C58: =C60+C61+C59 -> 29687872 | D58: =C58/C$10 -> 7421968
B59: Computador Herramientas Trabajo | D59: =C59/C$10 -> 0
B60: - ROP Gasto | C60: =H37*AVERAGE('Parámetros'!G8:G9)*IF(C2="Network",15%,100%)*IF(C2="Enterprise",40%,100%) -> 29687872 | D60: =C60/C$10 -> 7421968
B61: - ROP Costo Fijo | D61: =C61/C$10 -> 0
B62: T. C + G Equipo | C62: =C57+C58 -> 1.1188787e+08 | D62: =C62/C$10 -> 27971968
B63: Costo Total Interno Compañía | C63: =C57+C59+C61 -> 82200000 | D63: =D57+D59+D61 -> 20550000

Sheet Sprint MVP
B2: Línea de Negocio | C2: Descubrimiento
B3: ¿Tipo de contrato vendedor? | C3: Deel/Ontop
B4: Comisión vendedor | C4: 0.1
B5: ¿Cuál es la fuente de tu lead? | C5: Directo
B6: Perfil Network | C6: Perfil Sr.
B7: ¿Pago con TC? | C7: 0 | F7: Gross Margin Meta | G7: =VLOOKUP($C$2,'Parámetros'!$A$118:$D$124,3,0) -> 0.5
B8: Factoring | C8: 0 | F8: =IF(D13>=G7,"Dentro del margen","¡Por debajo del margen!") -> ¡Por debajo del margen!
B9: Tecnologia
B10: Tiempo Duración: Mes | C10: 1
F11: COP | G11: USD
B12: Jugar con Gross Margin | C12: Comisión Venta | D12: =F12*C4+IFS(C5="Cold Calling",2%*138.3522%,C5="Mercadeo",2%*101%,C5="Network - Cold Calling",2%*138.3522%,C5="Referido Imagine",5%*138.3522%,C5="Directo",0)*F12+ifs(AND(C6="Perfil Jr.",C2="Network"),200000,AND(C6="Perfil Sr.",C2="Network"),350000,AND(C2="Network",C6="Perfil Semi Senior"), 600000,C2="Proyecto",1,C2="Equipo dedicado",1,C2="Servidores",1,C2="Enterprise",1,C2="Descubrimiento",1) -> 2192983.5 | E12: Precio Total | F12: =((C61+C57+C59)/((1-D13-'Parámetros'!L8*C7)))*IF(C8=1,102.4%,1) -> 21929825 | G12: =F12/'Parámetros'!$L$3 -> 6177.4154 | I12: 160 | J12: 1
C13: Gross Margin | D13: 0.43 | E13: Precio mensual | F13: =F12/C10 -> 21929825 | G13: =F13/'Parámetros'!$L$3 -> 6177.4154 | I13: 12 | J13: =I13*J12/I12 -> 0.075
C14: ICA | D14: =F12*'Parámetros'!L5 -> 151315.79 | E14: Precio/Horas | F14: =F12/SUM(D43:D52)/C10 -> 81221.572 | G14: =G12/SUM(D43:D52)/C10 -> 22.879316
C15: NET Margin | D15: =(F12-C62-D14-D12-C7*'Parámetros'!L8*F12-IF(C8=1,2.4%,0)*F12)/F12 -> 0.091302425 | I15: 12 horas | J15: 3127889.9
I16: 20 horas | J16: 5044796.6
B18: Jugar con Net Margin | C18: Comisión Venta | D18: =F18*C4+IFS(C5="Cold Calling",2%*138.3522%,C5="Mercadeo",2%*101%,C5="Network - Cold Calling",2%*138.3522%,C5="Referido Imagine",5%*138.3522%,C5="Directo",0)*F18 -> 2536903.6 | E18: Precio Total | F18: =+C62/((1-IFS(C5="Cold Calling",2%*138.3522%,C5="Mercadeo",2%*101%,C5="Network - Cold Calling",2%*138.3522%,C5="Referido Imagine",5%*138.3522%,C5="Directo",0)-C4-D19-'Parámetros'!L5-C7*'Parámetros'!L8))*IF(C8=1,102.4%,1) -> 25369036 | G18: =F18/'Parámetros'!L3 -> 7146.2074
C19: NET Margin | D19: 0.2 | E19: Precio mensual | F19: =F18/C10 -> 25369036 | G19: =G18/C10 -> 7146.2074
C20: ICA | D20: =F18*'Parámetros'!L5 -> 175046.35 | E20: Precio/Horas | F20: =F18/SUM(D43:D52)/C10 -> 93959.394 | G20: =G18/SUM(D43:D52)/C10 -> 26.467435
C21: Gross Margin | D21: =(((F18-C57-C59-C61-C7*'Parámetros'!L8*F18)-IF(C8=1,2.4%,0)*F18)/F18) -> 0.50727336
B23: ='Parámetros'!B149 -> Considerar como mínimo por cada Dev: PM:33%, QA:20%, Diseño:10%
J24: dias | K24: 22 | L24: 100
E25: =SUM(E27:E34) -> 1.5 | J25: 5 | K25: =J25*L24/K24 -> 22.727273 | L25: 5729166.7
B26: Equipo | C26: Salario Base | D26: Tipo Contrato | E26: Dedicación | F26: Costo mensual | G26: Costo total | H26: % Tiempo Equipo | J26: 15 | K26: =J26*L24/K24 -> 68.181818 | L26: 14912281
A27: =IFERROR(__xludf.DUMMYFUNCTION("COUNTIF(SPLIT(B27,"" ""),""Developer"")"),0.0) -> 0 | B27: Forward Deployed Pruduct experience | C27: 5000000 | D27: P. Servicios | E27: 0.5 | F27: =+IFERROR(IF(D27="Nómina",C27*1.38352,C27),"")*E27 -> 2500000 | G27: =F27*C$10 -> 2500000 | H27: =F27/(AVERAGE('Parámetros'!$F$5:$F$6)+$F$37) -> 0.0072159078 | J27: 20 | K27: =J27*L24/K24 -> 90.909091 | L27: 21929825
A28: =IFERROR(__xludf.DUMMYFUNCTION("COUNTIF(SPLIT(B28,"" ""),""Developer"")"),0.0) -> 0 | B28: Forward Deployed Enginnier | C28: 10000000 | D28: P. Servicios | E28: 1 | F28: =+IFERROR(IF(D28="Nómina",C28*1.38352,C28),"")*E28 -> 10000000 | G28: =F28*C$10 -> 10000000 | H28: =G28/(AVERAGE('Parámetros'!$F$5:$F$6)+$F$37) -> 0.028863631
A29: =IFERROR(__xludf.DUMMYFUNCTION("COUNTIF(SPLIT(B29,"" ""),""Developer"")"),0.0) -> 0
A30: =IFERROR(__xludf.DUMMYFUNCTION("COUNTIF(SPLIT(B30,"" ""),""Developer"")"),0.0) -> 0
A31: =IFERROR(__xludf.DUMMYFUNCTION("COUNTIF(SPLIT(B31,"" ""),""Developer"")"),0.0) -> 0
A32: =IFERROR(__xludf.DUMMYFUNCTION("COUNTIF(SPLIT(B32,"" ""),""Developer"")"),0.0) -> 0 | F32: =+IFERROR(IF(D32="Nómina",C32*1.38352,C32),"")*E32*105% -> 0 | G32: =F32*C$10 -> 0 | H32: =G32/(AVERAGE('Parámetros'!$F$5:$F$6)+$F$37) -> 0
A33: =IFERROR(__xludf.DUMMYFUNCTION("COUNTIF(SPLIT(B33,"" ""),""Developer"")"),0.0) -> 0 | F33: =+IFERROR(IF(D33="Nómina",C33*1.38352,C33),"")*E33*105% -> 0 | G33: =F33*C$10 -> 0 | H33: =G33/(AVERAGE('Parámetros'!$F$5:$F$6)+$F$37) -> 0
A34: =IFERROR(__xludf.DUMMYFUNCTION("COUNTIF(SPLIT(B34,"" ""),""Developer"")"),0.0) -> 0 | C34: =IFERROR(VLOOKUP(B34,'Parámetros'!A$1:B120,2, FALSE),"") | F34: =+IFERROR(IF(D34="Nómina",C34*1.38352,C34),"")*E34*105% -> 0 | G34: =F34*C$10 -> 0 | H34: =G34/(AVERAGE('Parámetros'!$F$5:$F$6)+$F$37) -> 0
C35: =IFERROR(VLOOKUP(B35,'Parámetros'!A$1:B121,2, FALSE),"") | F35: =+IFERROR(IF(D35="Nómina",C35*1.38352,C35),"")*E35*105% -> 0 | G35: =F35*C$10 -> 0 | H35: =G35/(AVERAGE('Parámetros'!$F$5:$F$6)+$F$37) -> 0
C36: =IFERROR(VLOOKUP(B36,'Parámetros'!A$1:B122,2, FALSE),"") | F36: =+IFERROR(IF(D36="Nómina",C36*1.38352,C36),"")*E36*105% -> 0 | G36: =F36*C$10 -> 0 | H36: =G36/(AVERAGE('Parámetros'!$F$5:$F$6)+$F$37) -> 0
F37: =SUM(F27:F36) -> 12500000 | G37: =SUM(G27:G36) -> 12500000 | H37: =SUM(H27:H36) -> 0.036079539
C40: Gross Margin | D40: USD
B42: Equipo | C42: Dedicación | D42: Capacidad Horas | E42: Precio x Hora | F42: Precio Total
B43: =B27 -> Forward Deployed Pruduct experience | C43: =E27 -> 0.5 | D43: =C43*180 -> 90 | E43: =IFERROR((IF($C$40="Gross Margin",F27/$F$37*$F$12,IF($C$40="Net Margin",F27/$F$37*$F$18,"Error")))/D43,"")/IF($D$40="USD",'Parámetros'!$L$3,1)/$C$10 -> 13.72759 | F43: =E43*D43 -> 1235.4831
B44: =B28 -> Forward Deployed Enginnier | C44: =E28 -> 1 | D44: =C44*180 -> 180 | E44: =IFERROR((IF($C$40="Gross Margin",F28/$F$37*$F$12,IF($C$40="Net Margin",F28/$F$37*$F$18,"Error")))/D44,"")/IF($D$40="USD",'Parámetros'!$L$3,1)/$C$10 -> 27.455179 | F44: =E44*D44 -> 4941.9323
B45: =B29 | C45: =E29 | D45: =C45*180 -> 0 | E45: =IFERROR((IF($C$40="Gross Margin",F29/$F$37*$F$12,IF($C$40="Net Margin",F29/$F$37*$F$18,"Error")))/D45,"")/IF($D$40="USD",'Parámetros'!$L$3,1)/$C$10 -> 0 | F45: =E45*D45 -> 0
B46: =B30 | C46: =E30 | D46: =C46*180 -> 0 | E46: =IFERROR((IF($C$40="Gross Margin",F30/$F$37*$F$12,IF($C$40="Net Margin",F30/$F$37*$F$18,"Error")))/D46,"")/IF($D$40="USD",'Parámetros'!$L$3,1)/$C$10 -> 0 | F46: =E46*D46 -> 0
B47: =B31 | C47: =E31 | D47: =C47*180 -> 0 | E47: =IFERROR((IF($C$40="Gross Margin",F31/$F$37*$F$12,IF($C$40="Net Margin",F31/$F$37*$F$18,"Error")))/D47,"")/IF($D$40="USD",'Parámetros'!$L$3,1)/$C$10 -> 0 | F47: =E47*D47 -> 0
B48: =B32 | C48: =E32 | D48: =C48*180 -> 0 | E48: =IFERROR((IF($C$40="Gross Margin",F32/$F$37*$F$12,IF($C$40="Net Margin",F32/$F$37*$F$18,"Error")))/D48,"")/IF($D$40="USD",'Parámetros'!$L$3,1) -> 0 | F48: =E48*D48 -> 0
B49: =B33 | C49: =E33 | D49: =C49*180 -> 0 | E49: =IFERROR((IF($C$40="Gross Margin",F33/$F$37*$F$12,IF($C$40="Net Margin",F33/$F$37*$F$18,"Error")))/D49,"")/IF($D$40="USD",'Parámetros'!$L$3,1) -> 0 | F49: =E49*D49 -> 0
B50: =B34 | C50: =E34 | D50: =C50*180 -> 0 | E50: =IFERROR((IF($C$40="Gross Margin",F34/$F$37*$F$12,IF($C$40="Net Margin",F34/$F$37*$F$18,"Error")))/D50,"")/IF($D$40="USD",'Parámetros'!$L$3,1) -> 0 | F50: =E50*D50 -> 0
B51: =B35 | C51: =E35 | D51: =C51*180 -> 0 | E51: =IFERROR((IF($C$40="Gross Margin",F35/$F$37*$F$12,IF($C$40="Net Margin",F35/$F$37*$F$18,"Error")))/D51,"")/IF($D$40="USD",'Parámetros'!$L$3,1) -> 0 | F51: =E51*D51 -> 0
B52: =B36 | C52: =E36 | D52: =C52*180 -> 0 | E52: =IFERROR((IF($C$40="Gross Margin",F36/$F$37*$F$12,IF($C$40="Net Margin",F36/$F$37*$F$18,"Error")))/D52,"")/IF($D$40="USD",'Parámetros'!$L$3,1) -> 0 | F52: =E52*D52 -> 0
E53: Total | F53: =SUM(F43:F52) -> 6177.4154
E54: Validación | F54: =F53-G13 -> 0
B56: Resumen | C56: Total | D56: Mensual
B57: Costo Equipo | C57: =G37 -> 12500000 | D57: =C57/C$10 -> 12500000
B58: Costo + Gasto Fijo | C58: =C60+C61+C59 -> 5083279.1 | D58: =C58/C$10 -> 5083279.1
B59: Computador Herramientas Trabajo | D59: =C59/C$10 -> 0
B60: - ROP Gasto | C60: =H37*AVERAGE('Parámetros'!G8:G9)*IF(C2="Network",15%,100%)*IF(C2="Enterprise",40%,100%) -> 5083279.1 | D60: =C60/C$10 -> 5083279.1
B61: - ROP Costo Fijo | D61: =C61/C$10 -> 0
B62: T. C + G Equipo | C62: =C57+C58 -> 17583279 | D62: =C62/C$10 -> 17583279
B63: Costo Total Interno Compañía | C63: =C57+C59+C61 -> 12500000 | D63: =D57+D59+D61 -> 12500000

Sheet Copy of PRICING PLANTILLA  6
B2: Línea de Negocio | C2: Network
B3: ¿Tipo de contrato vendedor? | C3: Prestación de Servicios
B4: Comisión vendedor | C4: =Ifs(C5="Referido Imagine", VLOOKUP(C2,'Parámetros'!$A$118:$B$124,2,0)*IF(C3="Nómina",1.38522,IF(C3="Prestación de Servicios",1,102%))/2,C5="Network - Cold Calling",VLOOKUP(C2,'Parámetros'!$A$118:$B$124,2,0)*IF(C3="Nómina",1.38522,IF(C3="Prestación de Servicios",1,102%))-2%*138.352222%,C5="Mercadeo",VLOOKUP(C2,'Parámetros'!$A$118:$B$124,2,0)*IF(C3="Nómina",1.38522,IF(C3="Prestación de Servicios",1,102%)),C5="Cold Calling",VLOOKUP(C2,'Parámetros'!$A$118:$B$124,2,0)*IF(C3="Nómina",1.38522,IF(C3="Prestación de Servicios",1,102%)),C5="Directo",VLOOKUP(C2,'Parámetros'!$A$118:$B$124,2,0)*IF(C3="Nómina",1.38522,IF(C3="Prestación de Servicios",1,102%)))*IF(C2="Servidores ",0,1) -> 0.085
B5: ¿Cuál es la fuente de tu lead? | C5: Mercadeo
B6: Perfil Network | C6: Perfil Semi senior
B7: ¿Pago con TC? | C7: 0 | F7: Gross Margin Meta | G7: =VLOOKUP($C$2,'Parámetros'!$A$118:$D$124,3,0) -> 0.3
B8: Factoring | C8: 0 | F8: =IF(D13>=G7,"Dentro del margen","¡Por debajo del margen!") -> Dentro del margen
B9: Tecnologia | C9: Java SpringBoot
B10: Tiempo Duración: Mes | C10: 6
F11: COP | G11: USD
B12: Jugar con Gross Margin | C12: Comisión Venta | D12: =F12*C4+IFS(C5="Cold Calling",2%*138.3522%,C5="Mercadeo",2%*101%,C5="Network - Cold Calling",2%*138.3522%,C5="Referido Imagine",5%*138.3522%,C5="Directo",0)*F12+ifs(AND(C6="Perfil Jr.",C2="Network"),200000,AND(C6="Perfil Sr.",C2="Network"),350000,AND(C2="Network",C6="Perfil Semi Senior"), 600000,C2="Proyecto",1,C2="Equipo dedicado",1,C2="Servidores",1,C2="Enterprise",1,C2="Descubrimiento",1) -> 8459500.4 | E12: Precio Total | F12: =((C61+C57+C59)/((1-D13-'Parámetros'!L8*C7)))*IF(C8=1,102.4%,1) -> 74710080 | G12: =F12/'Parámetros'!$L$3 -> 21045.093
C13: Gross Margin | D13: 0.3 | E13: Precio mensual | F13: =F12/C10 -> 12451680 | G13: =F13/'Parámetros'!$L$3 -> 3507.5155
C14: ICA | D14: =F12*'Parámetros'!L5 -> 515499.55 | E14: Precio/Horas | F14: =F12/SUM(D43:D52)/C10 -> 69176 | G14: =G12/SUM(D43:D52)/C10 -> 19.486197
C15: NET Margin | D15: =(F12-C62-D14-D12-C7*'Parámetros'!L8*F12-IF(C8=1,2.4%,0)*F12)/F12 -> 0.13669792
B18: Jugar con Net Margin | C18: Comisión Venta | D18: =F18*C4+IFS(C5="Cold Calling",2%*138.3522%,C5="Mercadeo",2%*101%,C5="Network - Cold Calling",2%*138.3522%,C5="Referido Imagine",5%*138.3522%,C5="Directo",0)*F18 -> 8490991.5 | E18: Precio Total | F18: =+C62/((1-IFS(C5="Cold Calling",2%*138.3522%,C5="Mercadeo",2%*101%,C5="Network - Cold Calling",2%*138.3522%,C5="Referido Imagine",5%*138.3522%,C5="Directo",0)-C4-D19-'Parámetros'!L5-C7*'Parámetros'!L8))*IF(C8=1,102.4%,1) -> 80712847 | G18: =F18/'Parámetros'!L3 -> 22736.013
C19: NET Margin | D19: 0.2 | E19: Precio mensual | F19: =F18/C10 -> 13452141 | G19: =G18/C10 -> 3789.3356
C20: ICA | D20: =F18*'Parámetros'!L5 -> 556918.65 | E20: Precio/Horas | F20: =F18/SUM(D43:D52)/C10 -> 74734.118 | G20: =G18/SUM(D43:D52)/C10 -> 21.051864
C21: Gross Margin | D21: =(((F18-C57-C59-C61-C7*'Parámetros'!L8*F18)-IF(C8=1,2.4%,0)*F18)/F18) -> 0.35206033
B23: ='Parámetros'!B149 -> Considerar como mínimo por cada Dev: PM:33%, QA:20%, Diseño:10%
E25: =SUM(E27:E34) -> 1
B26: Equipo | C26: Salario Base | D26: Tipo Contrato | E26: Dedicación | F26: Costo mensual | G26: Costo total | H26: % Tiempo Equipo
A27: =IFERROR(__xludf.DUMMYFUNCTION("COUNTIF(SPLIT(B27,"" ""),""Developer"")"),0.0) -> 0 | B27: Project Analyst Senior | C27: =IFERROR(VLOOKUP(B27,'Parámetros'!A$1:B113,2, FALSE),"") | D27: Nómina | F27: =+IFERROR(IF(D27="Nómina",C27*1.38352,C27),"")*E27*105% -> 0 | G27: =F27*C$10 -> 0 | H27: =F27/(AVERAGE('Parámetros'!$F$5:$F$6)+$F$37) -> 0
A28: =IFERROR(__xludf.DUMMYFUNCTION("COUNTIF(SPLIT(B28,"" ""),""Developer"")"),1.0) -> 1 | B28: Software Developer Semi Senior Nivel 2 | C28: 6000000 | D28: Nómina | E28: 1 | F28: =+IFERROR(IF(D28="Nómina",C28*1.38352,C28),"")*E28*105% -> 8716176 | G28: =F28*C$10 -> 52297056 | H28: =G28/(AVERAGE('Parámetros'!$F$5:$F$6)+$F$37) -> 0.15261508
A29: =IFERROR(__xludf.DUMMYFUNCTION("COUNTIF(SPLIT(B29,"" ""),""Developer"")"),0.0) -> 0 | B29: QA Engineer Semi Senior | C29: =IFERROR(VLOOKUP(B29,'Parámetros'!A$1:B115,2, FALSE),"") -> 3000000 | D29: Nómina | F29: =+IFERROR(IF(D29="Nómina",C29*1.38352,C29),"")*E29*105% -> 0 | G29: =F29*C$10 -> 0 | H29: =G29/(AVERAGE('Parámetros'!$F$5:$F$6)+$F$37) -> 0
A30: =IFERROR(__xludf.DUMMYFUNCTION("COUNTIF(SPLIT(B30,"" ""),""Developer"")"),0.0) -> 0 | B30: Diseñador Semi Senior | C30: =IFERROR(VLOOKUP(B30,'Parámetros'!A$1:B116,2, FALSE),"") | D30: Nómina | F30: =+IFERROR(IF(D30="Nómina",C30*1.38352,C30),"")*E30*105% -> 0 | G30: =F30*C$10 -> 0 | H30: =G30/(AVERAGE('Parámetros'!$F$5:$F$6)+$F$37) -> 0
A31: =IFERROR(__xludf.DUMMYFUNCTION("COUNTIF(SPLIT(B31,"" ""),""Developer"")"),0.0) -> 0 | C31: =IFERROR(VLOOKUP(B31,'Parámetros'!A$1:B117,2, FALSE),"") | D31: Nómina | F31: =+IFERROR(IF(D31="Nómina",C31*1.38352,C31),"")*E31*105% -> 0 | G31: =F31*C$10 -> 0 | H31: =G31/(AVERAGE('Parámetros'!$F$5:$F$6)+$F$37) -> 0
A32: =IFERROR(__xludf.DUMMYFUNCTION("COUNTIF(SPLIT(B32,"" ""),""Developer"")"),0.0) -> 0 | C32: =IFERROR(VLOOKUP(B32,'Parámetros'!A$1:B118,2, FALSE),"") | D32: Nómina | F32: =+IFERROR(IF(D32="Nómina",C32*1.38352,C32),"")*E32*105% -> 0 | G32: =F32*C$10 -> 0 | H32: =G32/(AVERAGE('Parámetros'!$F$5:$F$6)+$F$37) -> 0
A33: =IFERROR(__xludf.DUMMYFUNCTION("COUNTIF(SPLIT(B33,"" ""),""Developer"")"),0.0) -> 0 | C33: =IFERROR(VLOOKUP(B33,'Parámetros'!A$1:B119,2, FALSE),"") | D33: Nómina | F33: =+IFERROR(IF(D33="Nómina",C33*1.38352,C33),"")*E33*105% -> 0 | G33: =F33*C$10 -> 0 | H33: =G33/(AVERAGE('Parámetros'!$F$5:$F$6)+$F$37) -> 0
A34: =IFERROR(__xludf.DUMMYFUNCTION("COUNTIF(SPLIT(B34,"" ""),""Developer"")"),0.0) -> 0 | C34: =IFERROR(VLOOKUP(B34,'Parámetros'!A$1:B120,2, FALSE),"") | D34: Nómina | F34: =+IFERROR(IF(D34="Nómina",C34*1.38352,C34),"")*E34*105% -> 0 | G34: =F34*C$10 -> 0 | H34: =G34/(AVERAGE('Parámetros'!$F$5:$F$6)+$F$37) -> 0
C35: =IFERROR(VLOOKUP(B35,'Parámetros'!A$1:B121,2, FALSE),"") | D35: Nómina | F35: =+IFERROR(IF(D35="Nómina",C35*1.38352,C35),"")*E35*105% -> 0 | G35: =F35*C$10 -> 0 | H35: =G35/(AVERAGE('Parámetros'!$F$5:$F$6)+$F$37) -> 0
C36: =IFERROR(VLOOKUP(B36,'Parámetros'!A$1:B122,2, FALSE),"") | D36: Nómina | F36: =+IFERROR(IF(D36="Nómina",C36*1.38352,C36),"")*E36*105% -> 0 | G36: =F36*C$10 -> 0 | H36: =G36/(AVERAGE('Parámetros'!$F$5:$F$6)+$F$37) -> 0
F37: =SUM(F27:F36) -> 8716176 | G37: =SUM(G27:G36) -> 52297056 | H37: =SUM(H27:H36) -> 0.15261508
C40: Gross Margin | D40: USD
B42: Equipo | C42: Dedicación | D42: Capacidad Horas | E42: Precio x Hora | F42: Precio Total
B43: =B27 -> Project Analyst Senior | C43: =E27 | D43: =C43*180 -> 0 | E43: =IFERROR((IF($C$40="Gross Margin",F27/$F$37*$F$12,IF($C$40="Net Margin",F27/$F$37*$F$18,"Error")))/D43,"")/IF($D$40="USD",'Parámetros'!$L$3,1) -> 0 | F43: =E43*D43 -> 0
B44: =B28 -> Software Developer Semi Senior Nivel 2 | C44: =E28 -> 1 | D44: =C44*180 -> 180 | E44: =IFERROR((IF($C$40="Gross Margin",F28/$F$37*$F$12,IF($C$40="Net Margin",F28/$F$37*$F$18,"Error")))/D44,"")/IF($D$40="USD",'Parámetros'!$L$3,1) -> 116.91718 | F44: =E44*D44 -> 21045.093
B45: =B29 -> QA Engineer Semi Senior | C45: =E29 | D45: =C45*180 -> 0 | E45: =IFERROR((IF($C$40="Gross Margin",F29/$F$37*$F$12,IF($C$40="Net Margin",F29/$F$37*$F$18,"Error")))/D45,"")/IF($D$40="USD",'Parámetros'!$L$3,1) -> 0 | F45: =E45*D45 -> 0
B46: =B30 -> Diseñador Semi Senior | C46: =E30 | D46: =C46*180 -> 0 | E46: =IFERROR((IF($C$40="Gross Margin",F30/$F$37*$F$12,IF($C$40="Net Margin",F30/$F$37*$F$18,"Error")))/D46,"")/IF($D$40="USD",'Parámetros'!$L$3,1) -> 0 | F46: =E46*D46 -> 0
B47: =B31 | C47: =E31 | D47: =C47*180 -> 0 | E47: =IFERROR((IF($C$40="Gross Margin",F31/$F$37*$F$12,IF($C$40="Net Margin",F31/$F$37*$F$18,"Error")))/D47,"")/IF($D$40="USD",'Parámetros'!$L$3,1) -> 0 | F47: =E47*D47 -> 0
B48: =B32 | C48: =E32 | D48: =C48*180 -> 0 | E48: =IFERROR((IF($C$40="Gross Margin",F32/$F$37*$F$12,IF($C$40="Net Margin",F32/$F$37*$F$18,"Error")))/D48,"")/IF($D$40="USD",'Parámetros'!$L$3,1) -> 0 | F48: =E48*D48 -> 0
B49: =B33 | C49: =E33 | D49: =C49*180 -> 0 | E49: =IFERROR((IF($C$40="Gross Margin",F33/$F$37*$F$12,IF($C$40="Net Margin",F33/$F$37*$F$18,"Error")))/D49,"")/IF($D$40="USD",'Parámetros'!$L$3,1) -> 0 | F49: =E49*D49 -> 0
B50: =B34 | C50: =E34 | D50: =C50*180 -> 0 | E50: =IFERROR((IF($C$40="Gross Margin",F34/$F$37*$F$12,IF($C$40="Net Margin",F34/$F$37*$F$18,"Error")))/D50,"")/IF($D$40="USD",'Parámetros'!$L$3,1) -> 0 | F50: =E50*D50 -> 0
B51: =B35 | C51: =E35 | D51: =C51*180 -> 0 | E51: =IFERROR((IF($C$40="Gross Margin",F35/$F$37*$F$12,IF($C$40="Net Margin",F35/$F$37*$F$18,"Error")))/D51,"")/IF($D$40="USD",'Parámetros'!$L$3,1) -> 0 | F51: =E51*D51 -> 0
B52: =B36 | C52: =E36 | D52: =C52*180 -> 0 | E52: =IFERROR((IF($C$40="Gross Margin",F36/$F$37*$F$12,IF($C$40="Net Margin",F36/$F$37*$F$18,"Error")))/D52,"")/IF($D$40="USD",'Parámetros'!$L$3,1) -> 0 | F52: =E52*D52 -> 0
E53: Total | F53: =SUM(F43:F52) -> 21045.093
E54: Validación | F54: =F53-G12 -> 0
B56: Resumen | C56: Total | D56: Mensual
B57: Costo Equipo | C57: =G37 -> 52297056 | D57: =C57/C$10 -> 8716176
B58: Costo + Gasto Fijo | C58: =C60+C61+C59 -> 3225311.6 | D58: =C58/C$10 -> 537551.94
B59: Computador Herramientas Trabajo | D59: =C59/C$10 -> 0
B60: - ROP Gasto | C60: =H37*AVERAGE('Parámetros'!G8:G9)*IF(C2="Network",15%,100%)*IF(C2="Enterprise",40%,100%) -> 3225311.6 | D60: =C60/C$10 -> 537551.94
B61: - ROP Costo Fijo | D61: =C61/C$10 -> 0
B62: T. C + G Equipo | C62: =C57+C58 -> 55522368 | D62: =C62/C$10 -> 9253727.9
B63: Costo Total Interno Compañía | C63: =C57+C59+C61 -> 52297056 | D63: =D57+D59+D61 -> 8716176
B67: Precio por mes COP 51´600.000, total inversión 6 meses COP 309´600.000
A68: Q | B68: Equipo | C68: Dedicación | D68: Capacidad Horas
A69: 1 | B69: Project Analyst | C69: 0.33 | D69: 59.4
A70: 1 | B70: Software Developer | C70: 1 | D70: 180
A71: 1 | B71: QA Engineer | C71: 0.25 | D71: 45
A72: 1 | B72: Diseñador | C72: 0.3 | D72: 54
A73: 1 | B73: Lider Técnico | C73: 0.33 | D73: 59.4
A74: 1 | B74: Master Data | C74: 0.33 | D74: 59.4
A75: 1 | B75: Infrastructure Engineer Senior | C75: 0.2 | D75: 36

Sheet  PRICING PLANTILLA  Itempo Equi
B2: Línea de Negocio | C2: Equipo Dedicado
B3: ¿Tipo de contrato vendedor? | C3: Prestación de Servicios
B4: Comisión vendedor | C4: =Ifs(C5="Referido Imagine", VLOOKUP(C2,'Parámetros'!$A$118:$B$124,2,0)*IF(C3="Nómina",1.38522,IF(C3="Prestación de Servicios",1,102%))/2,C5="Network - Cold Calling",VLOOKUP(C2,'Parámetros'!$A$118:$B$124,2,0)*IF(C3="Nómina",1.38522,IF(C3="Prestación de Servicios",1,102%))-2%*138.352222%,C5="Mercadeo",VLOOKUP(C2,'Parámetros'!$A$118:$B$124,2,0)*IF(C3="Nómina",1.38522,IF(C3="Prestación de Servicios",1,102%)),C5="Cold Calling",VLOOKUP(C2,'Parámetros'!$A$118:$B$124,2,0)*IF(C3="Nómina",1.38522,IF(C3="Prestación de Servicios",1,102%)),C5="Directo",VLOOKUP(C2,'Parámetros'!$A$118:$B$124,2,0)*IF(C3="Nómina",1.38522,IF(C3="Prestación de Servicios",1,102%)))*IF(C2="Servidores ",0,1) -> 0.1
B5: ¿Cuál es la fuente de tu lead? | C5: Mercadeo
B6: Perfil Network | C6: Perfil Semi senior
B7: ¿Pago con TC? | C7: 0 | F7: Gross Margin Meta | G7: =VLOOKUP($C$2,'Parámetros'!$A$118:$D$124,3,0) -> 0.4
B8: Factoring | C8: 0 | F8: =IF(D13>=G7,"Dentro del margen","¡Por debajo del margen!") -> Dentro del margen
B9: Tecnologia | C9: Java SpringBoot
B10: Tiempo Duración: Mes | C10: 6
F11: COP | G11: USD
B12: Jugar con Gross Margin | C12: Comisión Venta | D12: =F12*C4+IFS(C5="Cold Calling",2%*138.3522%,C5="Mercadeo",2%*101%,C5="Network - Cold Calling",2%*138.3522%,C5="Referido Imagine",5%*138.3522%,C5="Directo",0)*F12+ifs(AND(C6="Perfil Jr.",C2="Network"),200000,AND(C6="Perfil Sr.",C2="Network"),350000,AND(C2="Network",C6="Perfil Semi Senior"), 600000,C2="Proyecto",1,C2="Equipo dedicado",1,C2="Servidores",1,C2="Enterprise",1,C2="Descubrimiento",1) -> 36097693 | E12: Precio Total | F12: =((C61+C57+C59)/((1-D13-'Parámetros'!L8*C7)))*IF(C8=1,102.4%,1) -> 3.0031358e+08 | G12: =F12/'Parámetros'!$L$3 -> 84595.374
C13: Gross Margin | D13: 0.4 | E13: Precio mensual | F13: =F12/C10 -> 50052263 | G13: =F13/'Parámetros'!$L$3 -> 14099.229
C14: ICA | D14: =F12*'Parámetros'!L5 -> 2072163.7 | E14: Precio/Horas | F14: =F12/SUM(D43:D49) -> 608908.31 | G14: =G12/SUM(D43:D49) -> 171.52347
C15: NET Margin | D15: =(F12-C62-D14-D12-C7*'Parámetros'!L8*F12-IF(C8=1,2.4%,0)*F12)/F12 -> 0.062984785
B18: Jugar con Net Margin | C18: Comisión Venta | D18: =F18*C4+IFS(C5="Cold Calling",2%*138.3522%,C5="Mercadeo",2%*101%,C5="Network - Cold Calling",2%*138.3522%,C5="Referido Imagine",5%*138.3522%,C5="Directo",0)*F18 -> 43447867 | E18: Precio Total | F18: =+C62/((1-IFS(C5="Cold Calling",2%*138.3522%,C5="Mercadeo",2%*101%,C5="Network - Cold Calling",2%*138.3522%,C5="Referido Imagine",5%*138.3522%,C5="Directo",0)-C4-D19-'Parámetros'!L5-C7*'Parámetros'!L8))*IF(C8=1,102.4%,1) -> 361463121 | G18: =F18/'Parámetros'!L3 -> 101820.6
C19: NET Margin | D19: 0.2 | E19: Precio mensual | F19: =F18/C10 -> 60243854 | G19: =G18/C10 -> 16970.1
C20: ICA | D20: =F18*'Parámetros'!L5 -> 2494095.5 | E20: Precio/Horas | F20: =F18/SUM(D43:D49) -> 732893.59 | G20: =G18/SUM(D43:D49) -> 206.4489
C21: Gross Margin | D21: =(((F18-C57-C59-C61-C7*'Parámetros'!L8*F18)-IF(C8=1,2.4%,0)*F18)/F18) -> 0.50150337
B23: ='Parámetros'!B149 -> Considerar como mínimo por cada Dev: PM:33%, QA:20%, Diseño:10%
E25: =SUM(E27:E34) -> 2.74
B26: Equipo | C26: Salario Base | D26: Tipo Contrato | E26: Dedicación | F26: Costo mensual | G26: Costo total | H26: % Tiempo Equipo
A27: =IFERROR(__xludf.DUMMYFUNCTION("COUNTIF(SPLIT(B27,"" ""),""Developer"")"),0.0) -> 0 | B27: Project Analyst Senior | C27: =IFERROR(VLOOKUP(B27,'Parámetros'!A$1:B113,2, FALSE),"") | D27: Nómina | E27: 0.33 | F27: =+IFERROR(IF(D27="Nómina",C27*1.38352,C27),"")*E27*105% -> 0 | G27: =F27*C$10 -> 0 | H27: =F27/(AVERAGE('Parámetros'!$F$5:$F$6)+$F$37) -> 0
A28: =IFERROR(__xludf.DUMMYFUNCTION("COUNTIF(SPLIT(B28,"" ""),""Developer"")"),1.0) -> 1 | B28: Software Developer Senior Nivel 2 | C28: =IFERROR(VLOOKUP(B28,'Parámetros'!A$1:B114,2, FALSE),"") -> 12000000 | D28: Nómina | E28: 1 | F28: =+IFERROR(IF(D28="Nómina",C28*1.38352,C28),"")*E28*105% -> 17432352 | G28: =F28*C$10 -> 104594112 | H28: =G28/(AVERAGE('Parámetros'!$F$5:$F$6)+$F$37) -> 0.2898404
A29: =IFERROR(__xludf.DUMMYFUNCTION("COUNTIF(SPLIT(B29,"" ""),""Developer"")"),0.0) -> 0 | B29: QA Engineer Semi Senior | C29: =IFERROR(VLOOKUP(B29,'Parámetros'!A$1:B115,2, FALSE),"") -> 3000000 | D29: Nómina | E29: 0.25 | F29: =+IFERROR(IF(D29="Nómina",C29*1.38352,C29),"")*E29*105% -> 1089522 | G29: =F29*C$10 -> 6537132 | H29: =G29/(AVERAGE('Parámetros'!$F$5:$F$6)+$F$37) -> 0.018115025
A30: =IFERROR(__xludf.DUMMYFUNCTION("COUNTIF(SPLIT(B30,"" ""),""Developer"")"),0.0) -> 0 | B30: Diseñador Semi Senior | C30: =IFERROR(VLOOKUP(B30,'Parámetros'!A$1:B116,2, FALSE),"") | D30: Nómina | E30: 0.3 | F30: =+IFERROR(IF(D30="Nómina",C30*1.38352,C30),"")*E30*105% -> 0 | G30: =F30*C$10 -> 0 | H30: =G30/(AVERAGE('Parámetros'!$F$5:$F$6)+$F$37) -> 0
A31: =IFERROR(__xludf.DUMMYFUNCTION("COUNTIF(SPLIT(B31,"" ""),""Developer"")"),0.0) -> 0 | B31: Lider Técnico | C31: 9000000 | D31: Nómina | E31: 0.33 | F31: =+IFERROR(IF(D31="Nómina",C31*1.38352,C31),"")*E31*105% -> 4314507.1 | G31: =F31*C$10 -> 25887043 | H31: =G31/(AVERAGE('Parámetros'!$F$5:$F$6)+$F$37) -> 0.0717355
A32: =IFERROR(__xludf.DUMMYFUNCTION("COUNTIF(SPLIT(B32,"" ""),""Developer"")"),0.0) -> 0 | B32: Master Data | C32: 8500000 | D32: Nómina | E32: 0.33 | F32: =+IFERROR(IF(D32="Nómina",C32*1.38352,C32),"")*E32*105% -> 4074812.3 | G32: =F32*C$10 -> 24448874 | H32: =G32/(AVERAGE('Parámetros'!$F$5:$F$6)+$F$37) -> 0.067750194
A33: =IFERROR(__xludf.DUMMYFUNCTION("COUNTIF(SPLIT(B33,"" ""),""Developer"")"),0.0) -> 0 | B33: Infrastructure Engineer Senior | C33: =IFERROR(VLOOKUP(B33,'Parámetros'!A$1:B119,2, FALSE),"") | D33: Nómina | E33: 0.2 | F33: =+IFERROR(IF(D33="Nómina",C33*1.38352,C33),"")*E33*105% -> 0 | G33: =F33*C$10 -> 0 | H33: =G33/(AVERAGE('Parámetros'!$F$5:$F$6)+$F$37) -> 0
A34: =IFERROR(__xludf.DUMMYFUNCTION("COUNTIF(SPLIT(B34,"" ""),""Developer"")"),0.0) -> 0 | C34: =IFERROR(VLOOKUP(B34,'Parámetros'!A$1:B120,2, FALSE),"") | D34: Nómina | F34: =+IFERROR(IF(D34="Nómina",C34*1.38352,C34),"")*E34*105% -> 0 | G34: =F34*C$10 -> 0 | H34: =G34/(AVERAGE('Parámetros'!$F$5:$F$6)+$F$37) -> 0
C35: =IFERROR(VLOOKUP(B35,'Parámetros'!A$1:B121,2, FALSE),"") | D35: Nómina | F35: =+IFERROR(IF(D35="Nómina",C35*1.38352,C35),"")*E35*105% -> 0 | G35: =F35*C$10 -> 0 | H35: =G35/(AVERAGE('Parámetros'!$F$5:$F$6)+$F$37) -> 0
C36: =IFERROR(VLOOKUP(B36,'Parámetros'!A$1:B122,2, FALSE),"") | D36: Nómina | F36: =+IFERROR(IF(D36="Nómina",C36*1.38352,C36),"")*E36*105% -> 0 | G36: =F36*C$10 -> 0 | H36: =G36/(AVERAGE('Parámetros'!$F$5:$F$6)+$F$37) -> 0
F37: =SUM(F27:F36) -> 26911193 | G37: =SUM(G27:G36) -> 1.6146716e+08 | H37: =SUM(H27:H36) -> 0.44744112
C40: Gross Margin | D40: USD
B42: Equipo | C42: Dedicación | D42: Capacidad Horas | E42: Precio x Hora | F42: Precio Total
B43: =B27 -> Project Analyst Senior | C43: =E27 -> 0.33 | D43: =C43*180 -> 59.4 | E43: =IFERROR((IF($C$40="Gross Margin",F27/$F$37*$F$12,IF($C$40="Net Margin",F27/$F$37*$F$18,"Error")))/D43,"")/IF($D$40="USD",'Parámetros'!$L$3,1) -> 0 | F43: =E43*D43 -> 0
B44: =B28 -> Software Developer Senior Nivel 2 | C44: =E28 -> 1 | D44: =C44*180 -> 180 | E44: =IFERROR((IF($C$40="Gross Margin",F28/$F$37*$F$12,IF($C$40="Net Margin",F28/$F$37*$F$18,"Error")))/D44,"")/IF($D$40="USD",'Parámetros'!$L$3,1) -> 304.43679 | F44: =E44*D44 -> 54798.623
B45: =B29 -> QA Engineer Semi Senior | C45: =E29 -> 0.25 | D45: =C45*180 -> 45 | E45: =IFERROR((IF($C$40="Gross Margin",F29/$F$37*$F$12,IF($C$40="Net Margin",F29/$F$37*$F$18,"Error")))/D45,"")/IF($D$40="USD",'Parámetros'!$L$3,1) -> 76.109198 | F45: =E45*D45 -> 3424.9139
B46: =B30 -> Diseñador Semi Senior | C46: =E30 -> 0.3 | D46: =C46*180 -> 54 | E46: =IFERROR((IF($C$40="Gross Margin",F30/$F$37*$F$12,IF($C$40="Net Margin",F30/$F$37*$F$18,"Error")))/D46,"")/IF($D$40="USD",'Parámetros'!$L$3,1) -> 0 | F46: =E46*D46 -> 0
B47: =B31 -> Lider Técnico | C47: =E31 -> 0.33 | D47: =C47*180 -> 59.4 | E47: =IFERROR((IF($C$40="Gross Margin",F31/$F$37*$F$12,IF($C$40="Net Margin",F31/$F$37*$F$18,"Error")))/D47,"")/IF($D$40="USD",'Parámetros'!$L$3,1) -> 228.32759 | F47: =E47*D47 -> 13562.659
B48: =B32 -> Master Data | C48: =E32 -> 0.33 | D48: =C48*180 -> 59.4 | E48: =IFERROR((IF($C$40="Gross Margin",F32/$F$37*$F$12,IF($C$40="Net Margin",F32/$F$37*$F$18,"Error")))/D48,"")/IF($D$40="USD",'Parámetros'!$L$3,1) -> 215.64273 | F48: =E48*D48 -> 12809.178
B49: =B33 -> Infrastructure Engineer Senior | C49: =E33 -> 0.2 | D49: =C49*180 -> 36 | E49: =IFERROR((IF($C$40="Gross Margin",F33/$F$37*$F$12,IF($C$40="Net Margin",F33/$F$37*$F$18,"Error")))/D49,"")/IF($D$40="USD",'Parámetros'!$L$3,1) -> 0 | F49: =E49*D49 -> 0
B50: =B34 | C50: =E34 | D50: =C50*180 -> 0 | E50: =IFERROR((IF($C$40="Gross Margin",F34/$F$37*$F$12,IF($C$40="Net Margin",F34/$F$37*$F$18,"Error")))/D50,"")/IF($D$40="USD",'Parámetros'!$L$3,1) -> 0 | F50: =E50*D50 -> 0
B51: =B35 | C51: =E35 | D51: =C51*180 -> 0 | E51: =IFERROR((IF($C$40="Gross Margin",F35/$F$37*$F$12,IF($C$40="Net Margin",F35/$F$37*$F$18,"Error")))/D51,"")/IF($D$40="USD",'Parámetros'!$L$3,1) -> 0 | F51: =E51*D51 -> 0
B52: =B36 | C52: =E36 | D52: =C52*180 -> 0 | E52: =IFERROR((IF($C$40="Gross Margin",F36/$F$37*$F$12,IF($C$40="Net Margin",F36/$F$37*$F$18,"Error")))/D52,"")/IF($D$40="USD",'Parámetros'!$L$3,1) -> 0 | F52: =E52*D52 -> 0
E53: Total | F53: =SUM(F43:F52) -> 84595.374
E54: Validación | F54: =F53-G12 -> 0
B56: Resumen | C56: Total | D56: Mensual
B57: Costo Equipo | C57: =G37 -> 1.6146716e+08 | D57: =C57/C$10 -> 26911193
B58: Costo + Gasto Fijo | C58: =C60+C61+C59 -> 81761374 | D58: =C58/C$10 -> 13626896
B59: Computador Herramientas Trabajo | C59: =E25*5000000*9%*C10 -> 7398000 | D59: =C59/C$10 -> 1233000
B60: - ROP Gasto | C60: =H37*AVERAGE('Parámetros'!G8:G9)*IF(C2="Network",15%,100%)*IF(C2="Enterprise",40%,100%) -> 63040388 | D60: =C60/C$10 -> 10506731
B61: - ROP Costo Fijo | C61: =H37*AVERAGE('Parámetros'!H7)*IF(C2="Network",15%,100%) -> 11322986 | D61: =C61/C$10 -> 1887164.3
B62: T. C + G Equipo | C62: =C57+C58 -> 2.4322853e+08 | D62: =C62/C$10 -> 40538089
B63: Costo Total Interno Compañía | C63: =C57+C59+C61 -> 1.8018815e+08 | D63: =D57+D59+D61 -> 30031358
B67: Precio por mes COP 51´600.000, total inversión 6 meses COP 309´600.000
A68: Q | B68: Equipo | C68: Dedicación | D68: Capacidad Horas
A69: 1 | B69: Project Analyst | C69: 0.33 | D69: 59.4
A70: 1 | B70: Software Developer | C70: 1 | D70: 180
A71: 1 | B71: QA Engineer | C71: 0.25 | D71: 45
A72: 1 | B72: Diseñador | C72: 0.3 | D72: 54
A73: 1 | B73: Lider Técnico | C73: 0.33 | D73: 59.4
A74: 1 | B74: Master Data | C74: 0.33 | D74: 59.4
A75: 1 | B75: Infrastructure Engineer Senior | C75: 0.2 | D75: 36

Sheet Copy of PRICING PLANTILLA  5
B2: Línea de Negocio | C2: Equipo Dedicado
B3: ¿Tipo de contrato vendedor? | C3: Nómina
B4: Comisión Total | C4: =VLOOKUP(C2,'Parámetros'!$A$118:$B$124,2,0)*IF(C3="Nómina",1.38522,IF(C3="Prestación de Servicios",1,1.15)) -> 0.138522
B5: ¿Pago con TC? | C5: 0 | F5: Gross Margin Meta | G5: =VLOOKUP($C$2,'Parámetros'!$A$118:$D$124,3,0) -> 0.4
B6: Factoring | C6: =IF(C2="Enterprise",1,0) -> 0 | F6: =IF(D11>=G5,"Dentro del margen","¡Por debajo del margen!") -> Dentro del margen
B7: Tecnologia
B8: Tiempo Duración: Mes | C8: 1
F9: COP | G9: USD
B10: Jugar con Gross Margin | C10: Comisión Venta | D10: =F10*C4 -> 207783 | E10: Precio Total | F10: =((C54+C50+C52)/((1-D11-'Parámetros'!L8*C5)))*IF(C6=1,102.4%,1) -> 1500000 | G10: =F10/'Parámetros'!$L$3 -> 422.53521
C11: Gross Margin | D11: 0.4 | E11: Precio mensual | F11: =F10/C8 -> 1500000 | G11: =F11/'Parámetros'!$L$3 -> 422.53521 | H11: =G11*1.5 -> 633.80282 | J11: =F11/2 -> 750000 | K11: =J11*2.5 -> 1875000
C12: ICA | D12: =F10*'Parámetros'!L5 -> 10350 | E12: Precio/Horas | F12: =F10/SUM(D39:D45) -> 4166.6667 | G12: =G10/SUM(D39:D45) -> 1.1737089 | J12: =J11*2 -> 1500000 | K12: =J12*2.5 -> 3750000
C13: NET Margin | D13: =(F10-C55-D12-D10-C5*'Parámetros'!L8*F10-IF(C6=1,2.4%,0))/F10 -> 0.254578
B16: Jugar con Net Margin | C16: Comisión Venta | D16: =F16*C4 -> 224801.2 | E16: Precio Total | F16: =+(C55/(1-C4-D17-'Parámetros'!L5-C5*'Parámetros'!L8)) -> 1622855.6 | G16: =F16/'Parámetros'!L3 -> 457.14242
C17: NET Margin | D17: 0.3 | E17: Precio mensual | F17: =F16/C8 -> 1622855.6 | G17: =G16/C8 -> 457.14242
C18: ICA | D18: =F16*'Parámetros'!L5 -> 11197.703 | E18: Precio/Horas | F18: =F16/SUM(D39:D45) -> 4507.9322 | G18: =G16/SUM(D39:D45) -> 1.26984
C19: Gross Margin | D19: =((((F16-C50-C52-C54-C5*'Parámetros'!L8*F16))-(1-2.4%))/F16) -> 0.4454214
B21: ='Parámetros'!B149 -> Considerar como mínimo por cada Dev: PM:33%, QA:20%, Diseño:10%
E23: =SUM(E25:E32) -> 2
B24: Equipo | C24: Salario Base | D24: Tipo Contrato | E24: Dedicación | F24: Costo mensual | G24: Costo total | H24: % Tiempo Equipo
A25: =IFERROR(__xludf.DUMMYFUNCTION("COUNTIF(SPLIT(B25,"" ""),""Developer"")"),0.0) -> 0 | B25: Diseñador Junior | C25: =IFERROR(VLOOKUP(B25,'Parámetros'!A$1:B113,2, FALSE),"") | D25: Nómina | E25: 1 | F25: =+IFERROR(IF(D25="Nómina",C25*1.38352,C25),"")*E25*105% -> 0 | G25: =F25*C$8 -> 0 | H25: =F25/(AVERAGE('Parámetros'!$F$5:$F$6)+$F$33) -> 0
A26: =IFERROR(__xludf.DUMMYFUNCTION("COUNTIF(SPLIT(B26,"" ""),""Developer"")"),0.0) -> 0 | D26: Nómina | E26: 1 | F26: =+IFERROR(IF(D26="Nómina",C26*1.38352,C26),"")*E26*105% -> 0 | G26: =F26*C$8 -> 0 | H26: =G26/(AVERAGE('Parámetros'!$F$5:$F$6)+$F$33) -> 0
A27: =IFERROR(__xludf.DUMMYFUNCTION("COUNTIF(SPLIT(B27,"" ""),""Developer"")"),0.0) -> 0 | C27: =IFERROR(VLOOKUP(B27,'Parámetros'!A$1:B113,2, FALSE),"") | D27: Nómina | F27: =+IFERROR(IF(D27="Nómina",C27*1.38352,C27),"")*E27*105% -> 0 | G27: =F27*C$8 -> 0 | H27: =G27/(AVERAGE('Parámetros'!$F$5:$F$6)+$F$33) -> 0
A28: =IFERROR(__xludf.DUMMYFUNCTION("COUNTIF(SPLIT(B28,"" ""),""Developer"")"),0.0) -> 0 | C28: =IFERROR(VLOOKUP(B28,'Parámetros'!A$1:B114,2, FALSE),"") | D28: Nómina | F28: =+IFERROR(IF(D28="Nómina",C28*1.38352,C28),"")*E28*105% -> 0 | G28: =F28*C$8 -> 0 | H28: =G28/(AVERAGE('Parámetros'!$F$5:$F$6)+$F$33) -> 0
A29: =IFERROR(__xludf.DUMMYFUNCTION("COUNTIF(SPLIT(B29,"" ""),""Developer"")"),0.0) -> 0 | C29: =IFERROR(VLOOKUP(B29,'Parámetros'!A$1:B115,2, FALSE),"") | D29: Nómina | F29: =+IFERROR(IF(D29="Nómina",C29*1.38352,C29),"")*E29*105% -> 0 | G29: =F29*C$8 -> 0 | H29: =G29/(AVERAGE('Parámetros'!$F$5:$F$6)+$F$33) -> 0
A30: =IFERROR(__xludf.DUMMYFUNCTION("COUNTIF(SPLIT(B30,"" ""),""Developer"")"),0.0) -> 0 | C30: =IFERROR(VLOOKUP(B30,'Parámetros'!A$1:B116,2, FALSE),"") | D30: Nómina | F30: =+IFERROR(IF(D30="Nómina",C30*1.38352,C30),"")*E30*105% -> 0 | G30: =F30*C$8 -> 0 | H30: =G30/(AVERAGE('Parámetros'!$F$5:$F$6)+$F$33) -> 0
A31: =IFERROR(__xludf.DUMMYFUNCTION("COUNTIF(SPLIT(B31,"" ""),""Developer"")"),0.0) -> 0 | C31: =IFERROR(VLOOKUP(B31,'Parámetros'!A$1:B117,2, FALSE),"") | D31: Nómina | F31: =+IFERROR(IF(D31="Nómina",C31*1.38352,C31),"")*E31*105% -> 0 | G31: =F31*C$8 -> 0 | H31: =G31/(AVERAGE('Parámetros'!$F$5:$F$6)+$F$33) -> 0
A32: =IFERROR(__xludf.DUMMYFUNCTION("COUNTIF(SPLIT(B32,"" ""),""Developer"")"),0.0) -> 0 | C32: =iferror(VLOOKUP(B32,'Parámetros'!A$1:B127,2, FALSE),"") | D32: Nómina | F32: =+IFERROR(IF(D32="Nómina",C32*1.38352,C32),"")*E32*105% -> 0 | G32: =F32*C$8 -> 0 | H32: =G32/(AVERAGE('Parámetros'!$F$5:$F$6)+$F$33) -> 0
F33: =SUM(F25:F32) -> 0 | G33: =SUM(G25:G32) -> 0 | H33: =SUM(H25:H32) -> 0
C36: Gross Margin | D36: USD
B38: Equipo | C38: Dedicación | D38: Capacidad Horas | E38: Precio x Hora | F38: Precio Total
B39: =B25 -> Diseñador Junior | C39: =E25 -> 1 | D39: =C39*180 -> 180 | E39: =IFERROR((IF($C$36="Gross Margin",F25/$F$33*$F$10,IF($C$36="Net Margin",F25/$F$33*$F$16,"Error")))/D39,"")/IF($D$36="USD",'Parámetros'!$L$3,1) -> 0 | F39: =E39*D39 -> 0
B40: =B26 | C40: =E26 -> 1 | D40: =C40*180 -> 180 | E40: =IFERROR((IF($C$36="Gross Margin",F26/$F$33*$F$10,IF($C$36="Net Margin",F26/$F$33*$F$16,"Error")))/D40,"")/IF($D$36="USD",'Parámetros'!$L$3,1) -> 0 | F40: =E40*D40 -> 0
B41: =B27 | C41: =E27 | D41: =C41*180 -> 0 | E41: =IFERROR((IF($C$36="Gross Margin",F27/$F$33*$F$10,IF($C$36="Net Margin",F27/$F$33*$F$16,"Error")))/D41,"")/IF($D$36="USD",'Parámetros'!$L$3,1) -> 0 | F41: =E41*D41 -> 0
B42: =B28 | C42: =E28 | D42: =C42*180 -> 0 | E42: =IFERROR((IF($C$36="Gross Margin",F28/$F$33*$F$10,IF($C$36="Net Margin",F28/$F$33*$F$16,"Error")))/D42,"")/IF($D$36="USD",'Parámetros'!$L$3,1) -> 0 | F42: =E42*D42 -> 0
B43: =B29 | C43: =E29 | D43: =C43*180 -> 0 | E43: =IFERROR((IF($C$36="Gross Margin",F29/$F$33*$F$10,IF($C$36="Net Margin",F29/$F$33*$F$16,"Error")))/D43,"")/IF($D$36="USD",'Parámetros'!$L$3,1) -> 0 | F43: =E43*D43 -> 0
B44: =B30 | C44: =E30 | D44: =C44*180 -> 0 | E44: =IFERROR((IF($C$36="Gross Margin",F30/$F$33*$F$10,IF($C$36="Net Margin",F30/$F$33*$F$16,"Error")))/D44,"")/IF($D$36="USD",'Parámetros'!$L$3,1) -> 0 | F44: =E44*D44 -> 0
B45: =B31 | C45: =E31 | D45: =C45*180 -> 0 | E45: =IFERROR((IF($C$36="Gross Margin",F31/$F$33*$F$10,IF($C$36="Net Margin",F31/$F$33*$F$16,"Error")))/D45,"")/IF($D$36="USD",'Parámetros'!$L$3,1) -> 0 | F45: =E45*D45 -> 0
B49: Resumen | C49: Total | D49: Mensual
B50: Costo Equipo | C50: =G33 -> 0 | D50: =C50/C$8 -> 0
B51: Costo + Gasto Fijo | C51: =C53+C54+C52 -> 900000 | D51: =C51/C$8 -> 900000
B52: Computador Herramientas Trabajo | C52: =E23*5000000*9%*C8 -> 900000 | D52: =C52/C$8 -> 900000
B53: - ROP Gasto | C53: =H33*AVERAGE('Parámetros'!G6:G7)*IF(C2="Network",15%,100%)*IF(C2="Enterprise",40%,100%) -> 0 | D53: =C53/C$8 -> 0
B54: - ROP Costo Fijo | C54: =H33*AVERAGE('Parámetros'!H7)*IF(C2="Network",15%,100%) -> 0 | D54: =C54/C$8 -> 0
B55: T. C + G Equipo | C55: =C50+C51 -> 900000 | D55: =C55/C$8 -> 900000
B56: Costo Total Interno Compañía | C56: =C50+C52+C54 -> 900000 | D56: =D50+D52+D54 -> 900000

Sheet Copy of PRICING PLANTILLA  4
B2: Línea de Negocio | C2: Equipo Dedicado
B3: ¿Tipo de contrato vendedor? | C3: Nómina
B4: Comisión Total | C4: =VLOOKUP(C2,'Parámetros'!$A$118:$B$124,2,0)*IF(C3="Nómina",1.38522,IF(C3="Prestación de Servicios",1,1.15)) -> 0.138522
B5: ¿Pago con TC? | C5: 0 | F5: Gross Margin Meta | G5: =VLOOKUP($C$2,'Parámetros'!$A$118:$D$124,3,0) -> 0.4
B6: Factoring | C6: =IF(C2="Enterprise",1,0) -> 0 | F6: =IF(D11>=G5,"Dentro del margen","¡Por debajo del margen!") -> Dentro del margen
B7: Tecnologia
B8: Tiempo Duración: Mes | C8: 1
F9: COP | G9: USD | I9: Mensual
B10: Jugar con Gross Margin | C10: Comisión Venta | D10: =F10*C4 -> 5965219.9 | E10: Precio Total | F10: =((C54+C50+C52)/((1-D11-'Parámetros'!L8*C5)))*IF(C6=1,102.4%,1) -> 43063340 | G10: =F10/'Parámetros'!$L$3 -> 12130.518 | I10: =F10/3 -> 14354447
C11: Gross Margin | D11: 0.4 | E11: Precio mensual | F11: =F10/C8 -> 43063340 | G11: =F11/'Parámetros'!$L$3 -> 12130.518
C12: ICA | D12: =F10*'Parámetros'!L5 -> 297137.04 | E12: Precio/Horas | F12: =F10/SUM(D39:D45) -> 43106.446 | G12: =G10/SUM(D39:D45) -> 12.142661
C13: NET Margin | D13: =(F10-C55-D12-D10-C5*'Parámetros'!L8*F10-IF(C6=1,2.4%,0))/F10 -> 0.067261525
B16: Jugar con Net Margin | C16: Comisión Venta | D16: =F16*C4 -> 8468630.1 | E16: Precio Total | F16: =+(C55/(1-C4-D17-'Parámetros'!L5-C5*'Parámetros'!L8)) -> 61135633 | G16: =F16/'Parámetros'!L3 -> 17221.305
C17: NET Margin | D17: 0.3 | E17: Precio mensual | F17: =F16/C8 -> 61135633 | G17: =G16/C8 -> 17221.305
C18: ICA | D18: =F16*'Parámetros'!L5 -> 421835.86 | E18: Precio/Horas | F18: =F16/SUM(D39:D45) -> 61196.829 | G18: =G16/SUM(D39:D45) -> 17.238543
C19: Gross Margin | D19: =((((F16-C50-C52-C54-C5*'Parámetros'!L8*F16))-(1-2.4%))/F16) -> 0.57736587
B21: ='Parámetros'!B149 -> Considerar como mínimo por cada Dev: PM:33%, QA:20%, Diseño:10%
E23: =SUM(E25:E32) -> 5.55
B24: Equipo | C24: Salario Base | D24: Tipo Contrato | E24: Dedicación | F24: Costo mensual | G24: Costo total | H24: % Tiempo Equipo
A25: =IFERROR(__xludf.DUMMYFUNCTION("COUNTIF(SPLIT(B25,"" ""),""Developer"")"),1.0) -> 1 | B25: Software Developer Semi Senior Nivel 1 | C25: =IFERROR(VLOOKUP(B25,'Parámetros'!A$1:B113,2, FALSE),"") -> 5000000 | D25: Nómina | E25: =100%*3 -> 3 | F25: =+IFERROR(IF(D25="Nómina",C25*1.38352,C25),"")*E25*105% -> 21790440 | G25: =F25*C$8 -> 21790440 | H25: =F25/(AVERAGE('Parámetros'!$F$5:$F$6)+$F$33) -> 0.061252598
A26: =IFERROR(__xludf.DUMMYFUNCTION("COUNTIF(SPLIT(B26,"" ""),""Developer"")"),0.0) -> 0 | B26: Diseñador Junior | C26: =IFERROR(VLOOKUP(B26,'Parámetros'!A$1:B113,2, FALSE),"") | D26: Nómina | E26: 2 | F26: =+IFERROR(IF(D26="Nómina",C26*1.38352,C26),"")*E26*105% -> 0 | G26: =F26*C$8 -> 0 | H26: =G26/(AVERAGE('Parámetros'!$F$5:$F$6)+$F$33) -> 0
A27: =IFERROR(__xludf.DUMMYFUNCTION("COUNTIF(SPLIT(B27,"" ""),""Developer"")"),0.0) -> 0 | B27: Maria Paula Giraldo Castiblanco | C27: =IFERROR(VLOOKUP(B27,'Parámetros'!A$1:B113,2, FALSE),"") | D27: Nómina | E27: 0.4 | F27: =+IFERROR(IF(D27="Nómina",C27*1.38352,C27),"")*E27*105% -> 0 | G27: =F27*C$8 -> 0 | H27: =G27/(AVERAGE('Parámetros'!$F$5:$F$6)+$F$33) -> 0
A28: =IFERROR(__xludf.DUMMYFUNCTION("COUNTIF(SPLIT(B28,"" ""),""Developer"")"),0.0) -> 0 | B28: QA Engineer Junior | C28: =IFERROR(VLOOKUP(B28,'Parámetros'!A$1:B114,2, FALSE),"") | D28: Nómina | E28: 0.15 | F28: =+IFERROR(IF(D28="Nómina",C28*1.38352,C28),"")*E28*105% -> 0 | G28: =F28*C$8 -> 0 | H28: =G28/(AVERAGE('Parámetros'!$F$5:$F$6)+$F$33) -> 0
A29: =IFERROR(__xludf.DUMMYFUNCTION("COUNTIF(SPLIT(B29,"" ""),""Developer"")"),0.0) -> 0 | C29: =IFERROR(VLOOKUP(B29,'Parámetros'!A$1:B115,2, FALSE),"") | D29: Nómina | F29: =+IFERROR(IF(D29="Nómina",C29*1.38352,C29),"")*E29*105% -> 0 | G29: =F29*C$8 -> 0 | H29: =G29/(AVERAGE('Parámetros'!$F$5:$F$6)+$F$33) -> 0
A30: =IFERROR(__xludf.DUMMYFUNCTION("COUNTIF(SPLIT(B30,"" ""),""Developer"")"),0.0) -> 0 | C30: =IFERROR(VLOOKUP(B30,'Parámetros'!A$1:B116,2, FALSE),"") | D30: Nómina | F30: =+IFERROR(IF(D30="Nómina",C30*1.38352,C30),"")*E30*105% -> 0 | G30: =F30*C$8 -> 0 | H30: =G30/(AVERAGE('Parámetros'!$F$5:$F$6)+$F$33) -> 0
A31: =IFERROR(__xludf.DUMMYFUNCTION("COUNTIF(SPLIT(B31,"" ""),""Developer"")"),0.0) -> 0 | C31: =IFERROR(VLOOKUP(B31,'Parámetros'!A$1:B117,2, FALSE),"") | D31: Nómina | F31: =+IFERROR(IF(D31="Nómina",C31*1.38352,C31),"")*E31*105% -> 0 | G31: =F31*C$8 -> 0 | H31: =G31/(AVERAGE('Parámetros'!$F$5:$F$6)+$F$33) -> 0
A32: =IFERROR(__xludf.DUMMYFUNCTION("COUNTIF(SPLIT(B32,"" ""),""Developer"")"),0.0) -> 0 | C32: =iferror(VLOOKUP(B32,'Parámetros'!A$1:B127,2, FALSE),"") | D32: Nómina | F32: =+IFERROR(IF(D32="Nómina",C32*1.38352,C32),"")*E32*105% -> 0 | G32: =F32*C$8 -> 0 | H32: =G32/(AVERAGE('Parámetros'!$F$5:$F$6)+$F$33) -> 0
F33: =SUM(F25:F32) -> 21790440 | G33: =SUM(G25:G32) -> 21790440 | H33: =SUM(H25:H32) -> 0.061252598
C36: Gross Margin | D36: USD
B38: Equipo | C38: Dedicación | D38: Capacidad Horas | E38: Precio x Hora | F38: Precio Total
B39: =B25 -> Software Developer Semi Senior Nivel 1 | C39: =E25 -> 3 | D39: =C39*180 -> 540 | E39: =IFERROR((IF($C$36="Gross Margin",F25/$F$33*$F$10,IF($C$36="Net Margin",F25/$F$33*$F$16,"Error")))/D39,"")/IF($D$36="USD",'Parámetros'!$L$3,1) -> 22.463923 | F39: =E39*D39 -> 12130.518
B40: =B26 -> Diseñador Junior | C40: =E26 -> 2 | D40: =C40*180 -> 360 | E40: =IFERROR((IF($C$36="Gross Margin",F26/$F$33*$F$10,IF($C$36="Net Margin",F26/$F$33*$F$16,"Error")))/D40,"")/IF($D$36="USD",'Parámetros'!$L$3,1) -> 0 | F40: =E40*D40 -> 0
B41: =B27 -> Maria Paula Giraldo Castiblanco | C41: =E27 -> 0.4 | D41: =C41*180 -> 72 | E41: =IFERROR((IF($C$36="Gross Margin",F27/$F$33*$F$10,IF($C$36="Net Margin",F27/$F$33*$F$16,"Error")))/D41,"")/IF($D$36="USD",'Parámetros'!$L$3,1) -> 0 | F41: =E41*D41 -> 0
B42: =B28 -> QA Engineer Junior | C42: =E28 -> 0.15 | D42: =C42*180 -> 27 | E42: =IFERROR((IF($C$36="Gross Margin",F28/$F$33*$F$10,IF($C$36="Net Margin",F28/$F$33*$F$16,"Error")))/D42,"")/IF($D$36="USD",'Parámetros'!$L$3,1) -> 0 | F42: =E42*D42 -> 0
B43: =B29 | C43: =E29 | D43: =C43*180 -> 0 | E43: =IFERROR((IF($C$36="Gross Margin",F29/$F$33*$F$10,IF($C$36="Net Margin",F29/$F$33*$F$16,"Error")))/D43,"")/IF($D$36="USD",'Parámetros'!$L$3,1) -> 0 | F43: =E43*D43 -> 0
B44: =B30 | C44: =E30 | D44: =C44*180 -> 0 | E44: =IFERROR((IF($C$36="Gross Margin",F30/$F$33*$F$10,IF($C$36="Net Margin",F30/$F$33*$F$16,"Error")))/D44,"")/IF($D$36="USD",'Parámetros'!$L$3,1) -> 0 | F44: =E44*D44 -> 0
B45: =B31 | C45: =E31 | D45: =C45*180 -> 0 | E45: =IFERROR((IF($C$36="Gross Margin",F31/$F$33*$F$10,IF($C$36="Net Margin",F31/$F$33*$F$16,"Error")))/D45,"")/IF($D$36="USD",'Parámetros'!$L$3,1) -> 0 | F45: =E45*D45 -> 0
B49: Resumen | C49: Total | D49: Mensual
B50: Costo Equipo | C50: =G33 -> 21790440 | D50: =C50/C$8 -> 21790440
B51: Costo + Gasto Fijo | C51: =C53+C54+C52 -> 12114037 | D51: =C51/C$8 -> 12114037
B52: Computador Herramientas Trabajo | C52: =E23*5000000*9%*C8 -> 2497500 | D52: =C52/C$8 -> 2497500
B53: - ROP Gasto | C53: =H33*AVERAGE('Parámetros'!G6:G7)*IF(C2="Network",15%,100%)*IF(C2="Enterprise",40%,100%) -> 8066473 | D53: =C53/C$8 -> 8066473
B54: - ROP Costo Fijo | C54: =H33*AVERAGE('Parámetros'!H7)*IF(C2="Network",15%,100%) -> 1550063.8 | D54: =C54/C$8 -> 1550063.8
B55: T. C + G Equipo | C55: =C50+C51 -> 33904477 | D55: =C55/C$8 -> 33904477
B56: Costo Total Interno Compañía | C56: =C50+C52+C54 -> 25838004 | D56: =D50+D52+D54 -> 25838004

Sheet Copy of PRICING PLANTILLA  3
B2: Línea de Negocio | C2: Network
B3: ¿Tipo de contrato vendedor? | C3: Deel/Ontop | K3: Trm: 4,707.65
B4: Comisión Total | C4: =VLOOKUP(C2,'Parámetros'!$A$118:$B$124,2,0)*IF(C3="Nómina",1.38522,IF(C3="Prestación de Servicios",1,1.15)) -> 0.09775 | J4: Costo | K4: Precio | L4: Margen
B5: ¿Pago con TC? | C5: 0 | F5: Gross Margin Meta | G5: =VLOOKUP($C$2,'Parámetros'!$A$118:$D$124,3,0) -> 0.3 | I5: Miguel Palacios | J5: =4500000*138.3522% -> 6225849 | K5: =J5/$N$6 -> 7204767.4 | L5: =(K5-J5)/K5 -> 0.13587093
B6: Factoring | C6: 0 | F6: =IF(D11>=G5,"Dentro del margen","¡Por debajo del margen!") -> Dentro del margen | I6: Daniela Rocha | J6: =2600000*138.3522% -> 3597157.2 | K6: =J6/$N$6 -> 4162754.5 | L6: =(K6-J6)/K6 -> 0.13587093 | N6: =1-(K8-J8)/K8 -> 0.86412907
B7: Tecnologia | I7: Juan Rojas | J7: =4000000*138.3522% -> 5534088 | K7: =J7/$N$6 -> 6404237.7 | L7: =(K7-J7)/K7 -> 0.13587093
B8: Tiempo Duración: Mes | C8: 1 | J8: =SUM(J5:J7) -> 15357094 | K8: =4800*J15 -> 17771760 | L8: =(K8-J8)/K8 -> 0.13587093
F9: COP | G9: USD
B10: Jugar con Gross Margin | C10: Comisión Venta | D10: =F10*C4 -> 18851.786 | E10: Precio Total | F10: =((C54+C50+C52)/((1-D11-'Parámetros'!L8*C5)))*IF(C6=1,102.4%,1)-C52-C54 -> 192857.14 | G10: =F10/'Parámetros'!$L$3 -> 54.325956
C11: Gross Margin | D11: 0.3 | E11: Precio mensual | F11: =F10/C8 -> 192857.14 | G11: =F11/'Parámetros'!$L$3 -> 54.325956 | I11: =J8/70% -> 21938706 | J11: =I11/4800 -> 4570.5638
C12: ICA | D12: =F10*'Parámetros'!L5 -> 1330.7143 | E12: Precio/Horas | F12: =F10/SUM(D39:D45) -> 1071.4286 | G12: =G10/SUM(D39:D45) -> 0.30181087 | I12: =J8 -> 15357094
C13: NET Margin | D13: =(F10-C55-D12-D10-C5*'Parámetros'!L8*F10)/F10 -> -1.4379833 | I13: =I11-I12 -> 6581611.8 | J13: =I13/I11 -> 0.3
I15: =I11/J15 -> 5925.4565 | J15: ='Parámetros'!S9 -> 3702.4499
B16: Jugar con Net Margin | C16: Comisión Venta | D16: =F16*C4 -> 78211.871 | E16: Precio Total | F16: =+(C55/(1-C4-D17-'Parámetros'!L5-C5*'Parámetros'!L8))*IF(C6=1,102.4%,1) -> 800121.44 | G16: =F16/'Parámetros'!L3 -> 225.38632
C17: NET Margin | D17: 0.33293537 | E17: Precio mensual | F17: =F16/C8 -> 800121.44 | G17: =G16/C8 -> 225.38632
C18: ICA | D18: =F16*'Parámetros'!L5 -> 5520.8379 | E18: Precio/Horas | F18: =F16/SUM(D39:D45) -> 4445.1191 | G18: =G16/SUM(D39:D45) -> 1.2521462
C19: Gross Margin | D19: =(F16-C50-C52-C54-C5*'Parámetros'!L8*F16)/F16 -> 0.43758537
B21: ='Parámetros'!B149 -> Considerar como mínimo por cada Dev: PM:33%, QA:20%, Diseño:10%
E23: =SUM(E25:E32) -> 1
B24: Equipo | C24: Salario Base | D24: Tipo Contrato | E24: Dedicación | F24: Costo mensual | G24: Costo total | H24: % Tiempo Equipo
A25: =IFERROR(__xludf.DUMMYFUNCTION("COUNTIF(SPLIT(B25,"" ""),""Developer"")"),0.0) -> 0 | B25: Miguel Oswaldo Palacios Mosquera | C25: =IFERROR(VLOOKUP(B25,'Parámetros'!A$1:B113,2, FALSE),"") | D25: Nómina | E25: 1 | F25: =+IFERROR(IF(D25="Nómina",C25*1.38352,C25),"")*E25 -> 0 | G25: =F25*C$8 -> 0 | H25: =F25/(AVERAGE('Parámetros'!$F$5:$F$6)+$F$33) -> 0
A26: =IFERROR(__xludf.DUMMYFUNCTION("COUNTIF(SPLIT(B26,"" ""),""Developer"")"),0.0) -> 0 | C26: =IFERROR(VLOOKUP(B26,'Parámetros'!A$1:B113,2, FALSE),"") | D26: Nómina | F26: =+IFERROR(IF(D26="Nómina",C26*1.38352,C26),"")*E26*105% -> 0 | G26: =F26*C$8 -> 0 | H26: =G26/(AVERAGE('Parámetros'!$F$5:$F$6)+$F$33) -> 0
A27: =IFERROR(__xludf.DUMMYFUNCTION("COUNTIF(SPLIT(B27,"" ""),""Developer"")"),0.0) -> 0 | C27: =IFERROR(VLOOKUP(B27,'Parámetros'!A$1:B113,2, FALSE),"") | D27: Nómina | F27: =+IFERROR(IF(D27="Nómina",C27*1.38352,C27),"")*E27*105% -> 0 | G27: =F27*C$8 -> 0 | H27: =G27/(AVERAGE('Parámetros'!$F$5:$F$6)+$F$33) -> 0
A28: =IFERROR(__xludf.DUMMYFUNCTION("COUNTIF(SPLIT(B28,"" ""),""Developer"")"),0.0) -> 0 | C28: =IFERROR(VLOOKUP(B28,'Parámetros'!A$1:B114,2, FALSE),"") | D28: Nómina | F28: =+IFERROR(IF(D28="Nómina",C28*1.38352,C28),"")*E28*105% -> 0 | G28: =F28*C$8 -> 0 | H28: =G28/(AVERAGE('Parámetros'!$F$5:$F$6)+$F$33) -> 0
A29: =IFERROR(__xludf.DUMMYFUNCTION("COUNTIF(SPLIT(B29,"" ""),""Developer"")"),0.0) -> 0 | C29: =IFERROR(VLOOKUP(B29,'Parámetros'!A$1:B115,2, FALSE),"") | D29: Nómina | F29: =+IFERROR(IF(D29="Nómina",C29*1.38352,C29),"")*E29*105% -> 0 | G29: =F29*C$8 -> 0 | H29: =G29/(AVERAGE('Parámetros'!$F$5:$F$6)+$F$33) -> 0
A30: =IFERROR(__xludf.DUMMYFUNCTION("COUNTIF(SPLIT(B30,"" ""),""Developer"")"),0.0) -> 0 | C30: =IFERROR(VLOOKUP(B30,'Parámetros'!A$1:B116,2, FALSE),"") | D30: Nómina | F30: =+IFERROR(IF(D30="Nómina",C30*1.38352,C30),"")*E30*105% -> 0 | G30: =F30*C$8 -> 0 | H30: =G30/(AVERAGE('Parámetros'!$F$5:$F$6)+$F$33) -> 0
A31: =IFERROR(__xludf.DUMMYFUNCTION("COUNTIF(SPLIT(B31,"" ""),""Developer"")"),0.0) -> 0 | C31: =IFERROR(VLOOKUP(B31,'Parámetros'!A$1:B117,2, FALSE),"") | D31: Nómina | F31: =+IFERROR(IF(D31="Nómina",C31*1.38352,C31),"")*E31*105% -> 0 | G31: =F31*C$8 -> 0 | H31: =G31/(AVERAGE('Parámetros'!$F$5:$F$6)+$F$33) -> 0
A32: =IFERROR(__xludf.DUMMYFUNCTION("COUNTIF(SPLIT(B32,"" ""),""Developer"")"),0.0) -> 0 | C32: =iferror(VLOOKUP(B32,'Parámetros'!A$1:B127,2, FALSE),"") | D32: Nómina | F32: =+IFERROR(IF(D32="Nómina",C32*1.38352,C32),"")*E32*105% -> 0 | G32: =F32*C$8 -> 0 | H32: =G32/(AVERAGE('Parámetros'!$F$5:$F$6)+$F$33) -> 0
F33: =SUM(F25:F32) -> 0 | G33: =SUM(G25:G32) -> 0 | H33: =SUM(H25:H32) -> 0
C36: Gross Margin | D36: USD
B38: Equipo | C38: Dedicación | D38: Capacidad Horas | E38: Precio x Hora | F38: Precio Total
B39: =B25 -> Miguel Oswaldo Palacios Mosquera | C39: =E25 -> 1 | D39: =C39*180 -> 180 | E39: =IFERROR((IF($C$36="Gross Margin",F25/$F$33*$F$10,IF($C$36="Net Margin",F25/$F$33*$F$16,"Error")))/D39,"")/IF($D$36="USD",'Parámetros'!$L$3,1) -> 0 | F39: =E39*D39 -> 0
B40: =B26 | C40: =E26 | D40: =C40*180 -> 0 | E40: =IFERROR((IF($C$36="Gross Margin",F26/$F$33*$F$10,IF($C$36="Net Margin",F26/$F$33*$F$16,"Error")))/D40,"")/IF($D$36="USD",'Parámetros'!$L$3,1) -> 0 | F40: =E40*D40 -> 0
B41: =B27 | C41: =E27 | D41: =C41*180 -> 0 | E41: =IFERROR((IF($C$36="Gross Margin",F27/$F$33*$F$10,IF($C$36="Net Margin",F27/$F$33*$F$16,"Error")))/D41,"")/IF($D$36="USD",'Parámetros'!$L$3,1) -> 0 | F41: =E41*D41 -> 0
B42: =B28 | C42: =E28 | D42: =C42*180 -> 0 | E42: =IFERROR((IF($C$36="Gross Margin",F28/$F$33*$F$10,IF($C$36="Net Margin",F28/$F$33*$F$16,"Error")))/D42,"")/IF($D$36="USD",'Parámetros'!$L$3,1) -> 0 | F42: =E42*D42 -> 0
B43: =B29 | C43: =E29 | D43: =C43*180 -> 0 | E43: =IFERROR((IF($C$36="Gross Margin",F29/$F$33*$F$10,IF($C$36="Net Margin",F29/$F$33*$F$16,"Error")))/D43,"")/IF($D$36="USD",'Parámetros'!$L$3,1) -> 0 | F43: =E43*D43 -> 0
B44: =B30 | C44: =E30 | D44: =C44*180 -> 0 | E44: =IFERROR((IF($C$36="Gross Margin",F30/$F$33*$F$10,IF($C$36="Net Margin",F30/$F$33*$F$16,"Error")))/D44,"")/IF($D$36="USD",'Parámetros'!$L$3,1) -> 0 | F44: =E44*D44 -> 0
B45: =B31 | C45: =E31 | D45: =C45*180 -> 0 | E45: =IFERROR((IF($C$36="Gross Margin",F31/$F$33*$F$10,IF($C$36="Net Margin",F31/$F$33*$F$16,"Error")))/D45,"")/IF($D$36="USD",'Parámetros'!$L$3,1) -> 0 | F45: =E45*D45 -> 0
B49: Resumen | C49: Total | D49: Mensual
B50: Costo Equipo | C50: =G33 -> 0 | D50: =C50/C$8 -> 0
B51: Costo + Gasto Fijo | C51: =C53+C54+C52 -> 450000 | D51: =C51/C$8 -> 450000
B52: Computador Herramientas Trabajo | C52: =E23*5000000*9%*C8 -> 450000 | D52: =C52/C$8 -> 450000
B53: - ROP Gasto | C53: =H33*AVERAGE('Parámetros'!G6:G7)*IF(C2="Network",15%,100%)*IF(C2="Enterprise",40%,100%) -> 0 | D53: =C53/C$8 -> 0
B54: - ROP Costo Fijo | C54: =H33*AVERAGE('Parámetros'!H7)*IF(C2="Network",15%,100%) -> 0 | D54: =C54/C$8 -> 0
B55: T. C + G Equipo | C55: =C50+C51 -> 450000 | D55: =C55/C$8 -> 450000
B56: Costo Total Interno Compañía | C56: =C50+C52+C54 -> 450000 | D56: =D50+D52+D54 -> 450000

Sheet Copy of PRICING PLANTILLA  2
B2: Línea de Negocio | C2: Network
B3: ¿Tipo de contrato vendedor? | C3: Nómina
B4: Comisión Total | C4: =VLOOKUP(C2,'Parámetros'!$A$118:$B$124,2,0)*IF(C3="Nómina",1.38522,IF(C3="Prestación de Servicios",1,1.15)) -> 0.1177437
B5: ¿Pago con TC? | C5: 0 | F5: Gross Margin Meta | G5: =VLOOKUP($C$2,'Parámetros'!$A$118:$D$124,3,0) -> 0.3
B6: Factoring | C6: 0 | F6: =IF(D11>=G5,"Dentro del margen","¡Por debajo del margen!") -> Dentro del margen
B7: Tecnologia
B8: Tiempo Duración: Mes | C8: 1
F9: COP | G9: USD | I9: Ingreso | J9: 10300000
B10: Jugar con Gross Margin | C10: Comisión Venta | D10: =F10*C4 -> 79476.997 | E10: PV Total | F10: =((C54+C50+C52)/((1-D11-'Parámetros'!L8*C5)))*IF(C6=1,102.4%,1) -> 675000 | G10: =F10/'Parámetros'!$L$3 -> 190.14085 | I10: Costo | J10: =C50+C52+C54 -> 472500
C11: Gross Margin | D11: 0.3 | E11: PV mensual | F11: =F10/C8 -> 675000 | G11: =F11/'Parámetros'!$L$3 -> 190.14085 | I11: Utilidad Bruta | J11: =J9-J10 -> 9827500
C12: ICA | D12: =F10*'Parámetros'!L5 -> 4657.5 | E12: Pv/Horas | F12: =F10/SUM(D39:D45) -> 3571.4286 | G12: =G10/SUM(D39:D45) -> 1.0060362 | I12: Margen Bruto | J12: =J11/J9 -> 0.95412621
C13: NET Margin | D13: =(F10-C55-D12-D10-C5*'Parámetros'!L8*F10)/F10 -> 0.1753563 | I13: Comision | J13: =D10 -> 79476.997
I14: ICA | J14: =D12 -> 4657.5
I15: Gasto fijo | J15: =C53 -> 0
B16: Jugar con Net Margin | C16: Comisión Venta | D16: =F16*C4 -> 117036.21 | E16: PV Total | F16: =+(C55/(1-C4-D17-'Parámetros'!L5-C5*'Parámetros'!L8))*IF(C6=1,102.4%,1) -> 993991.24 | G16: =F16/'Parámetros'!L3 -> 279.99753 | I16: Utilidad Neta | J16: =J11-J13-J14-J15 -> 9743365.5
C17: NET Margin | D17: 0.4 | E17: PV mensual | F17: =F16/C8 -> 993991.24 | G17: =G16/C8 -> 279.99753 | I17: Margen Neto | J17: =J16/J9 -> 0.94595782
C18: ICA | D18: =F16*'Parámetros'!L5 -> 6858.5396 | E18: Pv/Horas | F18: =F16/SUM(D39:D45) -> 5259.2129 | G18: =G16/SUM(D39:D45) -> 1.4814684
C19: Gross Margin | D19: =(F16-C50-C52-C54-C5*'Parámetros'!L8*F16)/F16 -> 0.5246437
B21: ='Parámetros'!B149 -> Considerar como mínimo por cada Dev: PM:33%, QA:20%, Diseño:10%
E23: =SUM(E25:E32) -> 1.05
B24: Equipo | C24: Salario Base | D24: Tipo Contrato | E24: Dedicación | F24: Costo mensual | G24: Costo total | H24: % Tiempo Equipo
A25: =IFERROR(__xludf.DUMMYFUNCTION("COUNTIF(SPLIT(B25,"" ""),""Developer"")"),1.0) -> 1 | B25: Software Developer Junior Nivel 1 | C25: =IFERROR(VLOOKUP(B25,'Parámetros'!A$1:B113,2, FALSE),"") | D25: Nómina | E25: 0.5 | F25: =+IFERROR(IF(D25="Nómina",C25*1.38352,C25),"")*E25*105% -> 0 | G25: =F25*C$8 -> 0 | H25: =F25/(AVERAGE('Parámetros'!$F$5:$F$6)+$F$33) -> 0
A26: =IFERROR(__xludf.DUMMYFUNCTION("COUNTIF(SPLIT(B26,"" ""),""Developer"")"),0.0) -> 0 | B26: Diseñador Junior | C26: =IFERROR(VLOOKUP(B26,'Parámetros'!A$1:B113,2, FALSE),"") | D26: Nómina | E26: 0.15 | F26: =+IFERROR(IF(D26="Nómina",C26*1.38352,C26),"")*E26*105% -> 0 | G26: =F26*C$8 -> 0 | H26: =G26/(AVERAGE('Parámetros'!$F$5:$F$6)+$F$33) -> 0
A27: =IFERROR(__xludf.DUMMYFUNCTION("COUNTIF(SPLIT(B27,"" ""),""Developer"")"),0.0) -> 0 | B27: QA Engineer Junior | C27: =IFERROR(VLOOKUP(B27,'Parámetros'!A$1:B113,2, FALSE),"") | D27: Nómina | E27: 0.2 | F27: =+IFERROR(IF(D27="Nómina",C27*1.38352,C27),"")*E27*105% -> 0 | G27: =F27*C$8 -> 0 | H27: =G27/(AVERAGE('Parámetros'!$F$5:$F$6)+$F$33) -> 0
A28: =IFERROR(__xludf.DUMMYFUNCTION("COUNTIF(SPLIT(B28,"" ""),""Developer"")"),0.0) -> 0 | B28: Project Analyst Junior | C28: =IFERROR(VLOOKUP(B28,'Parámetros'!A$1:B114,2, FALSE),"") | D28: Nómina | E28: 0.2 | F28: =+IFERROR(IF(D28="Nómina",C28*1.38352,C28),"")*E28*105% -> 0 | G28: =F28*C$8 -> 0 | H28: =G28/(AVERAGE('Parámetros'!$F$5:$F$6)+$F$33) -> 0
A29: =IFERROR(__xludf.DUMMYFUNCTION("COUNTIF(SPLIT(B29,"" ""),""Developer"")"),0.0) -> 0 | C29: =IFERROR(VLOOKUP(B29,'Parámetros'!A$1:B115,2, FALSE),"") | D29: Nómina | F29: =+IFERROR(IF(D29="Nómina",C29*1.38352,C29),"")*E29*105% -> 0 | G29: =F29*C$8 -> 0 | H29: =G29/(AVERAGE('Parámetros'!$F$5:$F$6)+$F$33) -> 0
A30: =IFERROR(__xludf.DUMMYFUNCTION("COUNTIF(SPLIT(B30,"" ""),""Developer"")"),0.0) -> 0 | C30: =IFERROR(VLOOKUP(B30,'Parámetros'!A$1:B116,2, FALSE),"") | D30: Nómina | F30: =+IFERROR(IF(D30="Nómina",C30*1.38352,C30),"")*E30*105% -> 0 | G30: =F30*C$8 -> 0 | H30: =G30/(AVERAGE('Parámetros'!$F$5:$F$6)+$F$33) -> 0
A31: =IFERROR(__xludf.DUMMYFUNCTION("COUNTIF(SPLIT(B31,"" ""),""Developer"")"),0.0) -> 0 | C31: =IFERROR(VLOOKUP(B31,'Parámetros'!A$1:B117,2, FALSE),"") | D31: Nómina | F31: =+IFERROR(IF(D31="Nómina",C31*1.38352,C31),"")*E31*105% -> 0 | G31: =F31*C$8 -> 0 | H31: =G31/(AVERAGE('Parámetros'!$F$5:$F$6)+$F$33) -> 0
A32: =IFERROR(__xludf.DUMMYFUNCTION("COUNTIF(SPLIT(B32,"" ""),""Developer"")"),0.0) -> 0 | C32: =iferror(VLOOKUP(B32,'Parámetros'!A$1:B127,2, FALSE),"") | D32: Nómina | F32: =+IFERROR(IF(D32="Nómina",C32*1.38352,C32),"")*E32*105% -> 0 | G32: =F32*C$8 -> 0 | H32: =G32/(AVERAGE('Parámetros'!$F$5:$F$6)+$F$33) -> 0
F33: =SUM(F25:F32) -> 0 | G33: =SUM(G25:G32) -> 0 | H33: =SUM(H25:H32) -> 0
C36: Gross Margin | D36: USD
B38: Equipo | C38: Dedicación | D38: Capacidad Horas | E38: Precio x Hora | F38: Precio Total
B39: =B25 -> Software Developer Junior Nivel 1 | C39: =E25 -> 0.5 | D39: =C39*180 -> 90 | E39: =IFERROR((IF($C$36="Gross Margin",F25/$F$33*$F$10,IF($C$36="Net Margin",F25/$F$33*$F$16,"Error")))/D39,"")/IF($D$36="USD",'Parámetros'!$L$3,1) -> 0 | F39: =E39*D39 -> 0
B40: =B26 -> Diseñador Junior | C40: =E26 -> 0.15 | D40: =C40*180 -> 27 | E40: =IFERROR((IF($C$36="Gross Margin",F26/$F$33*$F$10,IF($C$36="Net Margin",F26/$F$33*$F$16,"Error")))/D40,"")/IF($D$36="USD",'Parámetros'!$L$3,1) -> 0 | F40: =E40*D40 -> 0
B41: =B27 -> QA Engineer Junior | C41: =E27 -> 0.2 | D41: =C41*180 -> 36 | E41: =IFERROR((IF($C$36="Gross Margin",F27/$F$33*$F$10,IF($C$36="Net Margin",F27/$F$33*$F$16,"Error")))/D41,"")/IF($D$36="USD",'Parámetros'!$L$3,1) -> 0 | F41: =E41*D41 -> 0
B42: =B28 -> Project Analyst Junior | C42: =E28 -> 0.2 | D42: =C42*180 -> 36 | E42: =IFERROR((IF($C$36="Gross Margin",F28/$F$33*$F$10,IF($C$36="Net Margin",F28/$F$33*$F$16,"Error")))/D42,"")/IF($D$36="USD",'Parámetros'!$L$3,1) -> 0 | F42: =E42*D42 -> 0
B43: =B29 | C43: =E29 | D43: =C43*180 -> 0 | E43: =IFERROR((IF($C$36="Gross Margin",F29/$F$33*$F$10,IF($C$36="Net Margin",F29/$F$33*$F$16,"Error")))/D43,"")/IF($D$36="USD",'Parámetros'!$L$3,1) -> 0 | F43: =E43*D43 -> 0
B44: =B30 | C44: =E30 | D44: =C44*180 -> 0 | E44: =IFERROR((IF($C$36="Gross Margin",F30/$F$33*$F$10,IF($C$36="Net Margin",F30/$F$33*$F$16,"Error")))/D44,"")/IF($D$36="USD",'Parámetros'!$L$3,1) -> 0 | F44: =E44*D44 -> 0
B45: =B31 | C45: =E31 | D45: =C45*180 -> 0 | E45: =IFERROR((IF($C$36="Gross Margin",F31/$F$33*$F$10,IF($C$36="Net Margin",F31/$F$33*$F$16,"Error")))/D45,"")/IF($D$36="USD",'Parámetros'!$L$3,1) -> 0 | F45: =E45*D45 -> 0
B49: Resumen | C49: Total | D49: Mensual
B50: Costo Equipo | C50: =G33 -> 0 | D50: =C50/C$8 -> 0
B51: Costo + Gasto Fijo | C51: =C53+C54+C52 -> 472500 | D51: =C51/C$8 -> 472500
B52: Computador Herramientas Trabajo | C52: =E23*5000000*9%*C8 -> 472500 | D52: =C52/C$8 -> 472500
B53: - ROP Gasto | C53: =H33*AVERAGE('Parámetros'!G6:G7)*IF(C2="Network",15%,100%)*IF(C2="Enterprise",40%,100%) -> 0 | D53: =C53/C$8 -> 0
B54: - ROP Costo Fijo | C54: =H33*AVERAGE('Parámetros'!H7)*IF(C2="Network",15%,100%) -> 0 | D54: =C54/C$8 -> 0
B55: T. C + G Equipo | C55: =C50+C51 -> 472500 | D55: =C55/C$8 -> 472500
B56: Costo Total | C56: =C50+C52+C54 -> 472500 | D56: =D50+D52+D54 -> 472500

Sheet Copy of Copy of PRICING PLANTIL
B2: Línea de Negocio | C2: Network
B3: ¿Tipo de contrato vendedor? | C3: Nómina
B4: Comisión Total | C4: =VLOOKUP(C2,'Parámetros'!$A$118:$B$124,2,0)*IF(C3="Nómina",1.38522,IF(C3="Prestación de Servicios",1,1.15)) -> 0.1177437
B5: ¿Pago con TC? | C5: 0 | F5: Gross Margin Meta | G5: =VLOOKUP($C$2,'Parámetros'!$A$118:$D$124,3,0) -> 0.3
B6: Factoring | C6: 0 | F6: =IF(D11>=G5,"Dentro del margen","¡Por debajo del margen!") -> Dentro del margen
B7: Tecnologia
B8: Tiempo Duración: Mes | C8: 1
F9: COP | G9: USD | I9: Ingreso | J9: 10300000
B10: Jugar con Gross Margin | C10: Comisión Venta | D10: =F10*C4 -> 1151708.4 | E10: PV Total | F10: =((C54+C50+C52)/((1-D11-'Parámetros'!L8*C5)))*IF(C6=1,102.4%,1) -> 9781486.4 | G10: =F10/'Parámetros'!$L$3 -> 2755.3483 | I10: Costo | J10: =C50+C52+C54 -> 5868891.8
C11: Gross Margin | D11: 0.4 | E11: PV mensual | F11: =F10/C8 -> 9781486.4 | G11: =F11/'Parámetros'!$L$3 -> 2755.3483 | I11: Utilidad Bruta | J11: =J9-J10 -> 4431108.2
C12: ICA | D12: =F10*'Parámetros'!L5 -> 67492.256 | E12: Pv/Horas | F12: =F10/SUM(D39:D45) -> 54341.591 | G12: =G10/SUM(D39:D45) -> 15.30749 | I12: Margen Bruto | J12: =J11/J9 -> 0.43020468
C13: NET Margin | D13: =(F10-C55-D12-D10-C5*'Parámetros'!L8*F10)/F10 -> 0.24047879 | I13: Comision | J13: =D10 -> 1151708.4
I14: ICA | J14: =D12 -> 67492.256
I15: Gasto fijo | J15: =C53 -> 341153.93
B16: Jugar con Net Margin | C16: Comisión Venta | D16: =F16*C4 -> 1538201.5 | E16: PV Total | F16: =+(C55/(1-C4-D17-'Parámetros'!L5-C5*'Parámetros'!L8))*IF(C6=1,102.4%,1) -> 13063981 | G16: =F16/'Parámetros'!L3 -> 3679.9947 | I16: Utilidad Neta | J16: =J11-J13-J14-J15 -> 2870753.6
C17: NET Margin | D17: 0.4 | E17: PV mensual | F17: =F16/C8 -> 13063981 | G17: =G16/C8 -> 3679.9947 | I17: Margen Neto | J17: =J16/J9 -> 0.27871394
C18: ICA | D18: =F16*'Parámetros'!L5 -> 90141.47 | E18: Pv/Horas | F18: =F16/SUM(D39:D45) -> 72577.673 | G18: =G16/SUM(D39:D45) -> 20.444415
C19: Gross Margin | D19: =(F16-C50-C52-C54-C5*'Parámetros'!L8*F16)/F16 -> 0.55075779
B21: ='Parámetros'!B149 -> Considerar como mínimo por cada Dev: PM:33%, QA:20%, Diseño:10%
E23: =SUM(E25:E32) -> 1
B24: Equipo | C24: Salario Base | D24: Tipo Contrato | E24: Dedicación | F24: Costo mensual | G24: Costo total | H24: % Tiempo Equipo
A25: =IFERROR(__xludf.DUMMYFUNCTION("COUNTIF(SPLIT(B25,"" ""),""Developer"")"),1.0) -> 1 | B25: Software Developer Junior Nivel 1 | C25: 4040000 | D25: Nómina | E25: 1 | F25: =+IFERROR(IF(D25="Nómina",C25*1.38352,C25),"")*E25*105% -> 5868891.8 | G25: =F25*C$8 -> 5868891.8 | H25: =F25/(AVERAGE('Parámetros'!$F$5:$F$6)+$F$33) -> 0.017270303
A26: =IFERROR(__xludf.DUMMYFUNCTION("COUNTIF(SPLIT(B26,"" ""),""Developer"")"),0.0) -> 0 | C26: =IFERROR(VLOOKUP(B26,'Parámetros'!A$1:B113,2, FALSE),"") | D26: Nómina | F26: =+IFERROR(IF(D26="Nómina",C26*1.38352,C26),"")*E26*105% -> 0 | G26: =F26*C$8 -> 0 | H26: =G26/(AVERAGE('Parámetros'!$F$5:$F$6)+$F$33) -> 0
A27: =IFERROR(__xludf.DUMMYFUNCTION("COUNTIF(SPLIT(B27,"" ""),""Developer"")"),0.0) -> 0 | C27: =IFERROR(VLOOKUP(B27,'Parámetros'!A$1:B113,2, FALSE),"") | D27: Nómina | F27: =+IFERROR(IF(D27="Nómina",C27*1.38352,C27),"")*E27*105% -> 0 | G27: =F27*C$8 -> 0 | H27: =G27/(AVERAGE('Parámetros'!$F$5:$F$6)+$F$33) -> 0
A28: =IFERROR(__xludf.DUMMYFUNCTION("COUNTIF(SPLIT(B28,"" ""),""Developer"")"),0.0) -> 0 | C28: =IFERROR(VLOOKUP(B28,'Parámetros'!A$1:B114,2, FALSE),"") | D28: Nómina | F28: =+IFERROR(IF(D28="Nómina",C28*1.38352,C28),"")*E28*105% -> 0 | G28: =F28*C$8 -> 0 | H28: =G28/(AVERAGE('Parámetros'!$F$5:$F$6)+$F$33) -> 0
A29: =IFERROR(__xludf.DUMMYFUNCTION("COUNTIF(SPLIT(B29,"" ""),""Developer"")"),0.0) -> 0 | C29: =IFERROR(VLOOKUP(B29,'Parámetros'!A$1:B115,2, FALSE),"") | D29: Nómina | F29: =+IFERROR(IF(D29="Nómina",C29*1.38352,C29),"")*E29*105% -> 0 | G29: =F29*C$8 -> 0 | H29: =G29/(AVERAGE('Parámetros'!$F$5:$F$6)+$F$33) -> 0
A30: =IFERROR(__xludf.DUMMYFUNCTION("COUNTIF(SPLIT(B30,"" ""),""Developer"")"),0.0) -> 0 | C30: =IFERROR(VLOOKUP(B30,'Parámetros'!A$1:B116,2, FALSE),"") | D30: Nómina | F30: =+IFERROR(IF(D30="Nómina",C30*1.38352,C30),"")*E30*105% -> 0 | G30: =F30*C$8 -> 0 | H30: =G30/(AVERAGE('Parámetros'!$F$5:$F$6)+$F$33) -> 0
A31: =IFERROR(__xludf.DUMMYFUNCTION("COUNTIF(SPLIT(B31,"" ""),""Developer"")"),0.0) -> 0 | C31: =IFERROR(VLOOKUP(B31,'Parámetros'!A$1:B117,2, FALSE),"") | D31: Nómina | F31: =+IFERROR(IF(D31="Nómina",C31*1.38352,C31),"")*E31*105% -> 0 | G31: =F31*C$8 -> 0 | H31: =G31/(AVERAGE('Parámetros'!$F$5:$F$6)+$F$33) -> 0
A32: =IFERROR(__xludf.DUMMYFUNCTION("COUNTIF(SPLIT(B32,"" ""),""Developer"")"),0.0) -> 0 | C32: =iferror(VLOOKUP(B32,'Parámetros'!A$1:B127,2, FALSE),"") | D32: Nómina | F32: =+IFERROR(IF(D32="Nómina",C32*1.38352,C32),"")*E32*105% -> 0 | G32: =F32*C$8 -> 0 | H32: =G32/(AVERAGE('Parámetros'!$F$5:$F$6)+$F$33) -> 0
F33: =SUM(F25:F32) -> 5868891.8 | G33: =SUM(G25:G32) -> 5868891.8 | H33: =SUM(H25:H32) -> 0.017270303
C36: Gross Margin | D36: USD
B38: Equipo | C38: Dedicación | D38: Capacidad Horas | E38: Precio x Hora | F38: Precio Total
B39: =B25 -> Software Developer Junior Nivel 1 | C39: =E25 -> 1 | D39: =C39*180 -> 180 | E39: =IFERROR((IF($C$36="Gross Margin",F25/$F$33*$F$10,IF($C$36="Net Margin",F25/$F$33*$F$16,"Error")))/D39,"")/IF($D$36="USD",'Parámetros'!$L$3,1) -> 15.30749 | F39: =E39*D39 -> 2755.3483
B40: =B26 | C40: =E26 | D40: =C40*180 -> 0 | E40: =IFERROR((IF($C$36="Gross Margin",F26/$F$33*$F$10,IF($C$36="Net Margin",F26/$F$33*$F$16,"Error")))/D40,"")/IF($D$36="USD",'Parámetros'!$L$3,1) -> 0 | F40: =E40*D40 -> 0
B41: =B27 | C41: =E27 | D41: =C41*180 -> 0 | E41: =IFERROR((IF($C$36="Gross Margin",F27/$F$33*$F$10,IF($C$36="Net Margin",F27/$F$33*$F$16,"Error")))/D41,"")/IF($D$36="USD",'Parámetros'!$L$3,1) -> 0 | F41: =E41*D41 -> 0
B42: =B28 | C42: =E28 | D42: =C42*180 -> 0 | E42: =IFERROR((IF($C$36="Gross Margin",F28/$F$33*$F$10,IF($C$36="Net Margin",F28/$F$33*$F$16,"Error")))/D42,"")/IF($D$36="USD",'Parámetros'!$L$3,1) -> 0 | F42: =E42*D42 -> 0
B43: =B29 | C43: =E29 | D43: =C43*180 -> 0 | E43: =IFERROR((IF($C$36="Gross Margin",F29/$F$33*$F$10,IF($C$36="Net Margin",F29/$F$33*$F$16,"Error")))/D43,"")/IF($D$36="USD",'Parámetros'!$L$3,1) -> 0 | F43: =E43*D43 -> 0
B44: =B30 | C44: =E30 | D44: =C44*180 -> 0 | E44: =IFERROR((IF($C$36="Gross Margin",F30/$F$33*$F$10,IF($C$36="Net Margin",F30/$F$33*$F$16,"Error")))/D44,"")/IF($D$36="USD",'Parámetros'!$L$3,1) -> 0 | F44: =E44*D44 -> 0
B45: =B31 | C45: =E31 | D45: =C45*180 -> 0 | E45: =IFERROR((IF($C$36="Gross Margin",F31/$F$33*$F$10,IF($C$36="Net Margin",F31/$F$33*$F$16,"Error")))/D45,"")/IF($D$36="USD",'Parámetros'!$L$3,1) -> 0 | F45: =E45*D45 -> 0
B49: Resumen | C49: Total | D49: Mensual
B50: Costo Equipo | C50: =G33 -> 5868891.8 | D50: =C50/C$8 -> 5868891.8
B51: Costo + Gasto Fijo | C51: =C53+C54+C52 -> 341153.93 | D51: =C51/C$8 -> 341153.93
B52: Computador Herramientas Trabajo | D52: =C52/C$8 -> 0
B53: - ROP Gasto | C53: =H33*AVERAGE('Parámetros'!G6:G7)*IF(C2="Network",15%,100%)*IF(C2="Enterprise",40%,100%) -> 341153.93 | D53: =C53/C$8 -> 341153.93
B54: - ROP Costo Fijo | D54: =C54/C$8 -> 0
B55: T. C + G Equipo | C55: =C50+C51 -> 6210045.8 | D55: =C55/C$8 -> 6210045.8
B56: Costo Total | C56: =C50+C52+C54 -> 5868891.8 | D56: =D50+D52+D54 -> 5868891.8

Sheet PRICING PLANTILLA  2
B2: Línea de Negocio | C2: Equipo Dedicado
B3: ¿Tipo de contrato vendedor? | C3: Deel/Ontop
B4: Comisión Total | C4: =VLOOKUP(C2,'Parámetros'!$A$118:$B$124,2,0)*IF(C3="Nómina",1.38522,IF(C3="Prestación de Servicios",1,1.15)) -> 0.115
B5: ¿Pago con TC? | C5: 0 | F5: Gross Margin Meta | G5: =VLOOKUP($C$2,'Parámetros'!$A$118:$D$124,3,0) -> 0.4
B6: Tecnologia | F6: =IF(D10>=G5,"Dentro del margen","¡Por debajo del margen!") -> Dentro del margen
B7: Tiempo Duración: Mes | C7: 1
F8: COP | G8: USD
B9: Jugar con Gross Margin | C9: Comisión Venta | D9: =F9*C4 -> 290179.66 | E9: PV Total | F9: =(C53+C49+C51)/((1-D10-'Parámetros'!L8*C5)) -> 2523301.4 | G9: =F9/'Parámetros'!$L$3 -> 710.78914
C10: Gross Margin | D10: 0.4 | E10: PV mensual | F10: =F9/C7 -> 2523301.4 | G10: =F10/'Parámetros'!$L$3 -> 710.78914
C11: ICA | D11: =F9*'Parámetros'!L5 -> 17410.78 | E11: Pv/Horas | F11: =F9/SUM(D38:D44) -> 2002.6202 | G11: =G9/SUM(D38:D44) -> 0.56411836
C12: NET Margin | D12: =(F9-C54-D11-D9-C5*'Parámetros'!L8*F9)/F9 -> 0.015080012
B15: Jugar con Net Margin | C15: Comisión Venta | D15: =F15*C4 -> 459367.39 | E15: PV Total | F15: =+(C54/(1-C4-D16-'Parámetros'!L5-C5*'Parámetros'!L8)) -> 3994499 | G15: =F15/'Parámetros'!L3 -> 1125.211
C16: NET Margin | D16: 0.33293537 | E16: PV mensual | F16: =F15/C7 -> 3994499 | G16: =G15/C7 -> 1125.211
C17: ICA | D17: =F15*'Parámetros'!L5 -> 27562.043 | E17: Pv/Horas | F17: =F15/SUM(D38:D44) -> 3170.2373 | G17: =G15/SUM(D38:D44) -> 0.8930246
C18: Gross Margin | D18: =(F15-C49-C51-C53-C5*'Parámetros'!L8*F15)/F15 -> 0.62098355
B20: ='Parámetros'!B149 -> Considerar como mínimo por cada Dev: PM:33%, QA:20%, Diseño:10%
E22: =SUM(E24:E31)*C7*100% -> 7
B23: Equipo | C23: Salario Base | D23: Tipo Contrato | E23: Dedicación | F23: Costo | G23: % Tiempo Equipo
A24: =IFERROR(__xludf.DUMMYFUNCTION("COUNTIF(SPLIT(B24,"" ""),""Developer"")"),0.0) -> 0 | B24: Dilan Joel Bergaño Caicedo | C24: =IFERROR(VLOOKUP(B24,'Parámetros'!A$1:B113,2, FALSE),"") | D24: Nómina | E24: 1 | F24: =+IFERROR(IF(D24="Nómina",C24*1.38352,C24),"")*E24*$C$7 -> 0 | G24: =F24/(AVERAGE('Parámetros'!$F$5:$F$6)+$F$32) -> 0
A25: =IFERROR(__xludf.DUMMYFUNCTION("COUNTIF(SPLIT(B25,"" ""),""Developer"")"),0.0) -> 0 | B25: Jeiner Alexis Bustos Quipo | C25: =IFERROR(VLOOKUP(B25,'Parámetros'!A$1:B113,2, FALSE),"") | D25: Nómina | E25: 1 | F25: =+IFERROR(IF(D25="Nómina",C25*1.38352,C25),"")*E25*$C$7 -> 0 | G25: =F25/(AVERAGE('Parámetros'!$F$5:$F$6)+$F$32) -> 0
B26: Mario Alfonso Garcia Marquez | C26: =IFERROR(VLOOKUP(B26,'Parámetros'!A$1:B113,2, FALSE),"") | D26: Nómina | E26: 1 | F26: =+IFERROR(IF(D26="Nómina",C26*1.38352,C26),"")*E26*$C$7 -> 0 | G26: =F26/(AVERAGE('Parámetros'!$F$5:$F$6)+$F$32) -> 0
A27: =IFERROR(__xludf.DUMMYFUNCTION("COUNTIF(SPLIT(B27,"" ""),""Developer"")"),0.0) -> 0 | B27: Carolina Andrea Capote Alfonso | C27: =IFERROR(VLOOKUP(B27,'Parámetros'!A$1:B114,2, FALSE),"") | D27: Nómina | E27: 1 | F27: =+IFERROR(IF(D27="Nómina",C27*1.38352,C27),"")*E27*$C$7 -> 0 | G27: =F27/(AVERAGE('Parámetros'!$F$5:$F$6)+$F$32) -> 0
A28: =IFERROR(__xludf.DUMMYFUNCTION("COUNTIF(SPLIT(B28,"" ""),""Developer"")"),0.0) -> 0 | B28: Juan David García Ocampo | C28: =IFERROR(VLOOKUP(B28,'Parámetros'!A$1:B115,2, FALSE),"")+1000000 -> 1000000 | D28: Nómina | E28: 1 | F28: =+IFERROR(IF(D28="Nómina",C28*1.38352,C28),"")*E28*$C$7 -> 1383520 | G28: =F28/(AVERAGE('Parámetros'!$F$5:$F$6)+$F$32) -> 0.0041257197
A29: =IFERROR(__xludf.DUMMYFUNCTION("COUNTIF(SPLIT(B29,"" ""),""Developer"")"),0.0) -> 0 | B29: Diego Alejandro Cadena Diaz | C29: =IFERROR(VLOOKUP(B29,'Parámetros'!A$1:B116,2, FALSE),"") | D29: Nómina | E29: 1 | F29: =+IFERROR(IF(D29="Nómina",C29*1.38352,C29),"")*E29*$C$7 -> 0 | G29: =F29/(AVERAGE('Parámetros'!$F$5:$F$6)+$F$32) -> 0
A30: =IFERROR(__xludf.DUMMYFUNCTION("COUNTIF(SPLIT(B30,"" ""),""Developer"")"),0.0) -> 0 | B30: Julian Alberto Ardila Arguello | C30: =IFERROR(VLOOKUP(B30,'Parámetros'!A$1:B117,2, FALSE),"") | D30: Nómina | E30: 1 | F30: =+IFERROR(IF(D30="Nómina",C30*1.38352,C30),"")*E30*$C$7 -> 0 | G30: =F30/(AVERAGE('Parámetros'!$F$5:$F$6)+$F$32) -> 0
A31: =IFERROR(__xludf.DUMMYFUNCTION("COUNTIF(SPLIT(B31,"" ""),""Developer"")"),0.0) -> 0 | C31: =iferror(VLOOKUP(B31,'Parámetros'!A$1:B127,2, FALSE),"") | F31: =+IFERROR(IF(D31="Nómina",C31*1.38352,C31),"")*E31*$C$7*105% -> 0 | G31: =F31/(AVERAGE('Parámetros'!$F$5:$F$6)+$F$32) -> 0
F32: =SUM(F24:F31) -> 1383520 | G32: =SUM(G24:G31) -> 0.0041257197
C35: Gross Margin | D35: USD
B37: Equipo | C37: Dedicación | D37: Capacidad Horas | E37: Precio x Hora | F37: Precio Total
B38: =B24 -> Dilan Joel Bergaño Caicedo | C38: =E24 -> 1 | D38: =C38*180 -> 180 | E38: =IFERROR((IF($C$35="Gross Margin",F24/$F$32*$F$9,IF($C$35="Net Margin",F24/$F$32*$F$15,"Error")))/D38,"")/IF($D$35="USD",'Parámetros'!$L$3,1) -> 0 | F38: =E38*D38 -> 0
B39: =B25 -> Jeiner Alexis Bustos Quipo | C39: =E25 -> 1 | D39: =C39*180 -> 180 | E39: =IFERROR((IF($C$35="Gross Margin",F25/$F$32*$F$9,IF($C$35="Net Margin",F25/$F$32*$F$15,"Error")))/D39,"")/IF($D$35="USD",'Parámetros'!$L$3,1) -> 0 | F39: =E39*D39 -> 0
B40: =B26 -> Mario Alfonso Garcia Marquez | C40: =E26 -> 1 | D40: =C40*180 -> 180 | E40: =IFERROR((IF($C$35="Gross Margin",F26/$F$32*$F$9,IF($C$35="Net Margin",F26/$F$32*$F$15,"Error")))/D40,"")/IF($D$35="USD",'Parámetros'!$L$3,1) -> 0 | F40: =E40*D40 -> 0
B41: =B27 -> Carolina Andrea Capote Alfonso | C41: =E27 -> 1 | D41: =C41*180 -> 180 | E41: =IFERROR((IF($C$35="Gross Margin",F27/$F$32*$F$9,IF($C$35="Net Margin",F27/$F$32*$F$15,"Error")))/D41,"")/IF($D$35="USD",'Parámetros'!$L$3,1) -> 0 | F41: =E41*D41 -> 0
B42: =B28 -> Juan David García Ocampo | C42: =E28 -> 1 | D42: =C42*180 -> 180 | E42: =IFERROR((IF($C$35="Gross Margin",F28/$F$32*$F$9,IF($C$35="Net Margin",F28/$F$32*$F$15,"Error")))/D42,"")/IF($D$35="USD",'Parámetros'!$L$3,1) -> 3.9488285 | F42: =E42*D42 -> 710.78914
B43: =B29 -> Diego Alejandro Cadena Diaz | C43: =E29 -> 1 | D43: =C43*180 -> 180 | E43: =IFERROR((IF($C$35="Gross Margin",F29/$F$32*$F$9,IF($C$35="Net Margin",F29/$F$32*$F$15,"Error")))/D43,"")/IF($D$35="USD",'Parámetros'!$L$3,1) -> 0 | F43: =E43*D43 -> 0
B44: =B30 -> Julian Alberto Ardila Arguello | C44: =E30 -> 1 | D44: =C44*180 -> 180 | E44: =IFERROR((IF($C$35="Gross Margin",F30/$F$32*$F$9,IF($C$35="Net Margin",F30/$F$32*$F$15,"Error")))/D44,"")/IF($D$35="USD",'Parámetros'!$L$3,1) -> 0 | F44: =E44*D44 -> 0
B48: Resumen
B49: Costo Equipo | C49: =F32 -> 1383520
B50: Costo + Gasto Fijo | C50: =C52+C53+C51 -> 794139.57
B51: Computador Herramientas Trabajo
B52: - ROP Gasto | C52: =G32*AVERAGE('Parámetros'!G5:G7)*IF(C2="Network",15%,100%)*IF(C2="Enterprise",40%,100%) -> 663678.71
B53: - ROP Costo Fijo | C53: =G32*AVERAGE('Parámetros'!H5:H7)*IF(C2="Network",15%,100%) -> 130460.86
B54: T. C + G Equipo | C54: =C49+C50 -> 2177659.6

Sheet Copy of PRICING PLANTILLA  1
B2: Línea de Negocio | C2: Network
B3: ¿Tipo de contrato vendedor? | C3: Nómina
B4: Comisión Total | C4: =VLOOKUP(C2,'Parámetros'!$A$118:$B$124,2,0)*IF(C3="Nómina",1.38522,IF(C3="Prestación de Servicios",1,1.15)) -> 0.1177437
B5: ¿Pago con TC? | C5: 0 | F5: Gross Margin Meta | G5: =VLOOKUP($C$2,'Parámetros'!$A$118:$D$124,3,0) -> 0.3
B6: Tecnologia | F6: =IF(D10>=G5,"Dentro del margen","¡Por debajo del margen!") -> Dentro del margen
B7: Tiempo Duración: Mes | C7: 1
F8: COP | G8: USD
B9: Jugar con Gross Margin | C9: Comisión Venta | D9: =F9*C4 -> 115001.95 | E9: PV Total | F9: =(C53+C49+C51)/((1-D10-'Parámetros'!L8*C5)) -> 976714.29 | G9: =F9/'Parámetros'!$L$3 -> 275.13078
C10: Gross Margin | D10: 0.3 | E10: PV mensual | F10: =F9/C7 -> 976714.29 | G10: =F10/'Parámetros'!$L$3 -> 275.13078
C11: ICA | D11: =F9*'Parámetros'!L5 -> 6739.3286 | E11: Pv/Horas | F11: =F9/SUM(D38:D44) -> 5426.1905 | G11: =G9/SUM(D38:D44) -> 1.5285044
C12: NET Margin | D12: =(F9-C54-D11-D9-C5*'Parámetros'!L8*F9)/F9 -> 0.1753563
B15: Jugar con Net Margin | C15: Comisión Venta | D15: =F15*C4 -> 148411.25 | E15: PV Total | F15: =+(C54/(1-C4-D16-'Parámetros'!L5-C5*'Parámetros'!L8)) -> 1260460.2 | G15: =F15/'Parámetros'!L3 -> 355.05922
C16: NET Margin | D16: 0.33293537 | E16: PV mensual | F16: =F15/C7 -> 1260460.2 | G16: =G15/C7 -> 355.05922
C17: ICA | D17: =F15*'Parámetros'!L5 -> 8697.1755 | E17: Pv/Horas | F17: =F15/SUM(D38:D44) -> 7002.5568 | G17: =G15/SUM(D38:D44) -> 1.9725512
C18: Gross Margin | D18: =(F15-C49-C51-C53-C5*'Parámetros'!L8*F15)/F15 -> 0.45757907
B20: ='Parámetros'!B149 -> Considerar como mínimo por cada Dev: PM:33%, QA:20%, Diseño:10%
E22: =SUM(E24:E31)*C7*100% -> 1
B23: Equipo | C23: Salario Base | D23: Tipo Contrato | E23: Dedicación | F23: Costo | G23: % Tiempo Equipo
A24: =IFERROR(__xludf.DUMMYFUNCTION("COUNTIF(SPLIT(B24,"" ""),""Developer"")"),0.0) -> 0 | B24: Carolina Andrea Capote Alfonso | C24: =IFERROR(VLOOKUP(B24,'Parámetros'!A$1:B113,2, FALSE),"") | D24: Nómina | E24: 1 | F24: =+IFERROR(IF(D24="Nómina",C24*1.38352,C24),"")*E24*$C$7*105% -> 0 | G24: =F24/(AVERAGE('Parámetros'!$F$5:$F$6)+$F$32) -> 0
A25: =IFERROR(__xludf.DUMMYFUNCTION("COUNTIF(SPLIT(B25,"" ""),""Developer"")"),0.0) -> 0 | C25: =IFERROR(VLOOKUP(B25,'Parámetros'!A$1:B113,2, FALSE),"") | D25: Nómina | F25: =+IFERROR(IF(D25="Nómina",C25*1.38352,C25),"")*E25*$C$7*105% -> 0 | G25: =F25/(AVERAGE('Parámetros'!$F$5:$F$6)+$F$32) -> 0
A26: =IFERROR(__xludf.DUMMYFUNCTION("COUNTIF(SPLIT(B26,"" ""),""Developer"")"),0.0) -> 0 | C26: =IFERROR(VLOOKUP(B26,'Parámetros'!A$1:B113,2, FALSE),"") | D26: Nómina | F26: =+IFERROR(IF(D26="Nómina",C26*1.38352,C26),"")*E26*$C$7*105% -> 0 | G26: =F26/(AVERAGE('Parámetros'!$F$5:$F$6)+$F$32) -> 0
A27: =IFERROR(__xludf.DUMMYFUNCTION("COUNTIF(SPLIT(B27,"" ""),""Developer"")"),0.0) -> 0 | C27: =IFERROR(VLOOKUP(B27,'Parámetros'!A$1:B114,2, FALSE),"") | D27: Nómina | F27: =+IFERROR(IF(D27="Nómina",C27*1.38352,C27),"")*E27*$C$7*105% -> 0 | G27: =F27/(AVERAGE('Parámetros'!$F$5:$F$6)+$F$32) -> 0
A28: =IFERROR(__xludf.DUMMYFUNCTION("COUNTIF(SPLIT(B28,"" ""),""Developer"")"),0.0) -> 0 | C28: =IFERROR(VLOOKUP(B28,'Parámetros'!A$1:B115,2, FALSE),"") | D28: Nómina | F28: =+IFERROR(IF(D28="Nómina",C28*1.38352,C28),"")*E28*$C$7*105% -> 0 | G28: =F28/(AVERAGE('Parámetros'!$F$5:$F$6)+$F$32) -> 0
A29: =IFERROR(__xludf.DUMMYFUNCTION("COUNTIF(SPLIT(B29,"" ""),""Developer"")"),0.0) -> 0 | C29: =IFERROR(VLOOKUP(B29,'Parámetros'!A$1:B116,2, FALSE),"") | D29: Nómina | F29: =+IFERROR(IF(D29="Nómina",C29*1.38352,C29),"")*E29*$C$7*105% -> 0 | G29: =F29/(AVERAGE('Parámetros'!$F$5:$F$6)+$F$32) -> 0
A30: =IFERROR(__xludf.DUMMYFUNCTION("COUNTIF(SPLIT(B30,"" ""),""Developer"")"),0.0) -> 0 | C30: =IFERROR(VLOOKUP(B30,'Parámetros'!A$1:B117,2, FALSE),"") | D30: Nómina | F30: =+IFERROR(IF(D30="Nómina",C30*1.38352,C30),"")*E30*$C$7*105% -> 0 | G30: =F30/(AVERAGE('Parámetros'!$F$5:$F$6)+$F$32) -> 0
A31: =IFERROR(__xludf.DUMMYFUNCTION("COUNTIF(SPLIT(B31,"" ""),""Developer"")"),0.0) -> 0 | C31: =iferror(VLOOKUP(B31,'Parámetros'!A$1:B127,2, FALSE),"") | D31: Nómina | F31: =+IFERROR(IF(D31="Nómina",C31*1.38352,C31),"")*E31*$C$7*105% -> 0 | G31: =F31/(AVERAGE('Parámetros'!$F$5:$F$6)+$F$32) -> 0
F32: =SUM(F24:F31) -> 0 | G32: =SUM(G24:G31) -> 0
C35: Gross Margin | D35: USD
B37: Equipo | C37: Dedicación | D37: Capacidad Horas | E37: Precio x Hora | F37: Precio Total
B38: =B24 -> Carolina Andrea Capote Alfonso | C38: =E24 -> 1 | D38: =C38*180 -> 180 | E38: =IFERROR((IF($C$35="Gross Margin",F24/$F$32*$F$9,IF($C$35="Net Margin",F24/$F$32*$F$15,"Error")))/D38,"")/IF($D$35="USD",'Parámetros'!$L$3,1) -> 0 | F38: =E38*D38 -> 0
B39: =B25 | C39: =E25 | D39: =C39*180 -> 0 | E39: =IFERROR((IF($C$35="Gross Margin",F25/$F$32*$F$9,IF($C$35="Net Margin",F25/$F$32*$F$15,"Error")))/D39,"")/IF($D$35="USD",'Parámetros'!$L$3,1) -> 0 | F39: =E39*D39 -> 0
B40: =B26 | C40: =E26 | D40: =C40*180 -> 0 | E40: =IFERROR((IF($C$35="Gross Margin",F26/$F$32*$F$9,IF($C$35="Net Margin",F26/$F$32*$F$15,"Error")))/D40,"")/IF($D$35="USD",'Parámetros'!$L$3,1) -> 0 | F40: =E40*D40 -> 0
B41: =B27 | C41: =E27 | D41: =C41*180 -> 0 | E41: =IFERROR((IF($C$35="Gross Margin",F27/$F$32*$F$9,IF($C$35="Net Margin",F27/$F$32*$F$15,"Error")))/D41,"")/IF($D$35="USD",'Parámetros'!$L$3,1) -> 0 | F41: =E41*D41 -> 0
B42: =B28 | C42: =E28 | D42: =C42*180 -> 0 | E42: =IFERROR((IF($C$35="Gross Margin",F28/$F$32*$F$9,IF($C$35="Net Margin",F28/$F$32*$F$15,"Error")))/D42,"")/IF($D$35="USD",'Parámetros'!$L$3,1) -> 0 | F42: =E42*D42 -> 0
B43: =B29 | C43: =E29 | D43: =C43*180 -> 0 | E43: =IFERROR((IF($C$35="Gross Margin",F29/$F$32*$F$9,IF($C$35="Net Margin",F29/$F$32*$F$15,"Error")))/D43,"")/IF($D$35="USD",'Parámetros'!$L$3,1) -> 0 | F43: =E43*D43 -> 0
B44: =B30 | C44: =E30 | D44: =C44*180 -> 0 | E44: =IFERROR((IF($C$35="Gross Margin",F30/$F$32*$F$9,IF($C$35="Net Margin",F30/$F$32*$F$15,"Error")))/D44,"")/IF($D$35="USD",'Parámetros'!$L$3,1) -> 0 | F44: =E44*D44 -> 0
B48: Resumen
B49: Costo Equipo | C49: =F32 -> 0
B50: Costo + Gasto Fijo | C50: =C52+C53+C51 -> 683700
B51: Computador Herramientas Trabajo | C51: =IF(((C53+C49)/(1-G5-'Parámetros'!L8*C5))>='Parámetros'!C148,'Parámetros'!B132*SUM(E24:E32),'Parámetros'!C132*SUM(E24:E32)*C7) -> 683700
B52: - ROP Gasto | C52: =G32*AVERAGE('Parámetros'!G5:G7)*IF(C2="Network",15%,100%)*IF(C2="Enterprise",40%,100%) -> 0
B53: - ROP Costo Fijo | C53: =G32*AVERAGE('Parámetros'!H5:H7)*IF(C2="Network",15%,100%) -> 0
B54: T. C + G Equipo | C54: =C49+C50 -> 683700

Sheet Copy of PRICING PLANTILLA 
B2: Línea de Negocio | C2: Network
B3: ¿Tipo de contrato vendedor? | C3: Deel/Ontop
B4: Comisión Total | C4: =VLOOKUP(C2,'Parámetros'!$A$118:$B$124,2,0)*IF(C3="Nómina",1.38522,IF(C3="Prestación de Servicios",1,1.15)) -> 0.09775
B5: ¿Pago con TC? | C5: 0 | F5: Gross Margin Meta | G5: =VLOOKUP($C$2,'Parámetros'!$A$118:$D$124,3,0) -> 0.3
B6: Tecnologia | F6: =IF(D10>=G5,"Dentro del margen","¡Por debajo del margen!") -> Dentro del margen
B7: Tiempo Duración: Mes | C7: 1
F8: COP | G8: USD
B9: Jugar con Gross Margin | C9: Comisión Venta | E9: PV Total | F9: =(C53+C49+C51)/((1-D10-'Parámetros'!L8*C5)) -> 1513907.1 | G9: =F9/'Parámetros'!$L$3 -> 426.45272
C10: Gross Margin | D10: 0.3 | E10: PV mensual | F10: =F9/C7 -> 1513907.1 | G10: =F10/'Parámetros'!$L$3 -> 426.45272
C11: ICA | D11: =F9*'Parámetros'!L5 -> 10445.959 | E11: Pv/Horas | F11: =F9/SUM(D38:D44) -> 5426.1905 | G11: =G9/SUM(D38:D44) -> 1.5285044
C12: NET Margin | D12: =(F9-C54-D11-D9-C5*'Parámetros'!L8*F9)/F9 -> 0.2931
B15: Jugar con Net Margin | C15: Comisión Venta | E15: PV Total | F15: =+(C54/(1-C4-D16-'Parámetros'!L5-C5*'Parámetros'!L8)) -> 1780020.2 | G15: =F15/'Parámetros'!L3 -> 501.41413
C16: NET Margin | D16: 0.3 | E16: PV mensual | F16: =F15/C7 -> 1780020.2 | G16: =G15/C7 -> 501.41413
C17: ICA | D17: =F15*'Parámetros'!L5 -> 12282.139 | E17: Pv/Horas | F17: =F15/SUM(D38:D44) -> 6380.0006 | G17: =G15/SUM(D38:D44) -> 1.7971833
C18: Gross Margin | D18: =(F15-C49-C51-C53-C5*'Parámetros'!L8*F15)/F15 -> 0.40465
B20: ='Parámetros'!B149 -> Considerar como mínimo por cada Dev: PM:33%, QA:20%, Diseño:10%
E22: =SUM(E24:E31)*C7*100% -> 1.55
B23: Equipo | C23: Salario Base | D23: Tipo Contrato | E23: Dedicación | F23: Costo | G23: % Tiempo Equipo
A24: =IFERROR(__xludf.DUMMYFUNCTION("COUNTIF(SPLIT(B24,"" ""),""Developer"")"),0.0) -> 0 | B24: Karol Dayanna Contreras Calderon | C24: =IFERROR(VLOOKUP(B24,'Parámetros'!A$1:B113,2, FALSE),"") | D24: Nómina | E24: 1 | F24: =+IFERROR(IF(D24="Nómina",C24*1.38352,C24),"")*E24*$C$7*105% -> 0 | G24: =F24/(AVERAGE('Parámetros'!$F$5:$F$6)+$F$32) -> 0
A25: =IFERROR(__xludf.DUMMYFUNCTION("COUNTIF(SPLIT(B25,"" ""),""Developer"")"),0.0) -> 0 | C25: =IFERROR(VLOOKUP(B25,'Parámetros'!A$1:B113,2, FALSE),"") | D25: Nómina | E25: 0.25 | F25: =+IFERROR(IF(D25="Nómina",C25*1.38352,C25),"")*E25*$C$7*105% -> 0 | G25: =F25/(AVERAGE('Parámetros'!$F$5:$F$6)+$F$32) -> 0
A26: =IFERROR(__xludf.DUMMYFUNCTION("COUNTIF(SPLIT(B26,"" ""),""Developer"")"),0.0) -> 0 | C26: =IFERROR(VLOOKUP(B26,'Parámetros'!A$1:B113,2, FALSE),"") | D26: Nómina | E26: 0.2 | F26: =+IFERROR(IF(D26="Nómina",C26*1.38352,C26),"")*E26*$C$7*105% -> 0 | G26: =F26/(AVERAGE('Parámetros'!$F$5:$F$6)+$F$32) -> 0
A27: =IFERROR(__xludf.DUMMYFUNCTION("COUNTIF(SPLIT(B27,"" ""),""Developer"")"),0.0) -> 0 | C27: =IFERROR(VLOOKUP(B27,'Parámetros'!A$1:B114,2, FALSE),"") | D27: Nómina | E27: 0.1 | F27: =+IFERROR(IF(D27="Nómina",C27*1.38352,C27),"")*E27*$C$7*105% -> 0 | G27: =F27/(AVERAGE('Parámetros'!$F$5:$F$6)+$F$32) -> 0
A28: =IFERROR(__xludf.DUMMYFUNCTION("COUNTIF(SPLIT(B28,"" ""),""Developer"")"),0.0) -> 0 | C28: =IFERROR(VLOOKUP(B28,'Parámetros'!A$1:B115,2, FALSE),"") | D28: Nómina | F28: =+IFERROR(IF(D28="Nómina",C28*1.38352,C28),"")*E28*$C$7*105% -> 0 | G28: =F28/(AVERAGE('Parámetros'!$F$5:$F$6)+$F$32) -> 0
A29: =IFERROR(__xludf.DUMMYFUNCTION("COUNTIF(SPLIT(B29,"" ""),""Developer"")"),0.0) -> 0 | C29: =IFERROR(VLOOKUP(B29,'Parámetros'!A$1:B116,2, FALSE),"") | D29: Nómina | F29: =+IFERROR(IF(D29="Nómina",C29*1.38352,C29),"")*E29*$C$7*105% -> 0 | G29: =F29/(AVERAGE('Parámetros'!$F$5:$F$6)+$F$32) -> 0
A30: =IFERROR(__xludf.DUMMYFUNCTION("COUNTIF(SPLIT(B30,"" ""),""Developer"")"),0.0) -> 0 | C30: =IFERROR(VLOOKUP(B30,'Parámetros'!A$1:B117,2, FALSE),"") | D30: Nómina | F30: =+IFERROR(IF(D30="Nómina",C30*1.38352,C30),"")*E30*$C$7*105% -> 0 | G30: =F30/(AVERAGE('Parámetros'!$F$5:$F$6)+$F$32) -> 0
A31: =IFERROR(__xludf.DUMMYFUNCTION("COUNTIF(SPLIT(B31,"" ""),""Developer"")"),0.0) -> 0 | C31: =iferror(VLOOKUP(B31,'Parámetros'!A$1:B127,2, FALSE),"") | D31: Nómina | F31: =+IFERROR(IF(D31="Nómina",C31*1.38352,C31),"")*E31*$C$7*105% -> 0 | G31: =F31/(AVERAGE('Parámetros'!$F$5:$F$6)+$F$32) -> 0
F32: =SUM(F24:F31) -> 0 | G32: =SUM(G24:G31) -> 0
C35: Gross Margin | D35: USD
B37: Equipo | C37: Dedicación | D37: Capacidad Horas | E37: Precio x Hora | F37: Precio Total
B38: =B24 -> Karol Dayanna Contreras Calderon | C38: =E24 -> 1 | D38: =C38*180 -> 180 | E38: =IFERROR((IF($C$35="Gross Margin",F24/$F$32*$F$9,IF($C$35="Net Margin",F24/$F$32*$F$15,"Error")))/D38,"")/IF($D$35="USD",'Parámetros'!$L$3,1) -> 0 | F38: =E38*D38 -> 0
B39: =B25 | C39: =E25 -> 0.25 | D39: =C39*180 -> 45 | E39: =IFERROR((IF($C$35="Gross Margin",F25/$F$32*$F$9,IF($C$35="Net Margin",F25/$F$32*$F$15,"Error")))/D39,"")/IF($D$35="USD",'Parámetros'!$L$3,1) -> 0 | F39: =E39*D39 -> 0
B40: =B26 | C40: =E26 -> 0.2 | D40: =C40*180 -> 36 | E40: =IFERROR((IF($C$35="Gross Margin",F26/$F$32*$F$9,IF($C$35="Net Margin",F26/$F$32*$F$15,"Error")))/D40,"")/IF($D$35="USD",'Parámetros'!$L$3,1) -> 0 | F40: =E40*D40 -> 0
B41: =B27 | C41: =E27 -> 0.1 | D41: =C41*180 -> 18 | E41: =IFERROR((IF($C$35="Gross Margin",F27/$F$32*$F$9,IF($C$35="Net Margin",F27/$F$32*$F$15,"Error")))/D41,"")/IF($D$35="USD",'Parámetros'!$L$3,1) -> 0 | F41: =E41*D41 -> 0
B42: =B28 | C42: =E28 | D42: =C42*180 -> 0 | E42: =IFERROR((IF($C$35="Gross Margin",F28/$F$32*$F$9,IF($C$35="Net Margin",F28/$F$32*$F$15,"Error")))/D42,"")/IF($D$35="USD",'Parámetros'!$L$3,1) -> 0 | F42: =E42*D42 -> 0
B43: =B29 | C43: =E29 | D43: =C43*180 -> 0 | E43: =IFERROR((IF($C$35="Gross Margin",F29/$F$32*$F$9,IF($C$35="Net Margin",F29/$F$32*$F$15,"Error")))/D43,"")/IF($D$35="USD",'Parámetros'!$L$3,1) -> 0 | F43: =E43*D43 -> 0
B44: =B30 | C44: =E30 | D44: =C44*180 -> 0 | E44: =IFERROR((IF($C$35="Gross Margin",F30/$F$32*$F$9,IF($C$35="Net Margin",F30/$F$32*$F$15,"Error")))/D44,"")/IF($D$35="USD",'Parámetros'!$L$3,1) -> 0 | F44: =E44*D44 -> 0
B48: Resumen
B49: Costo Equipo | C49: =F32 -> 0
B50: Costo + Gasto Fijo | C50: =C52+C53+C51 -> 1059735
B51: Computador Herramientas Trabajo | C51: =IF(((C53+C49)/(1-G5-'Parámetros'!L8*C5))>='Parámetros'!C148,'Parámetros'!B132*SUM(E24:E32),'Parámetros'!C132*SUM(E24:E32)*C7) -> 1059735
B52: - ROP Gasto | C52: =G32*AVERAGE('Parámetros'!G5:G7)*IF(C2="Network",15%,100%)*IF(C2="Enterprise",40%,100%) -> 0
B53: - ROP Costo Fijo | C53: =G32*AVERAGE('Parámetros'!H5:H7)*IF(C2="Network",15%,100%) -> 0
B54: T. C + G Equipo | C54: =C49+C50 -> 1059735

Sheet Personas ROP

Sheet Nueva Plantilla
C1: Herramienta Pricing | P1: Código: | Q1: FO - FI - 03
P2: Versión: | Q2: 1
P3: Fecha de emisión: | Q3: 44171
B5: Nivel 1 | C5: PV
B6: Descubrimiento | C6: =I17 -> 0
B8: Nivel 2 | C8: PV
B9: Caso Express
B11: Nivel 3 | C11: PV
B12: -
B14: Nivel 1
B15: *Todos los meses cambiar el # de personas actuales - Ojo!
B17: Resumen | E17: Comisión Venta | F17: =I17*C27 -> 0 | G17: Jugar con Gross Margin | H17: PV COP | I17: =+((C22+C18+C20)/(1-F18-'Parámetros'!L8*C28))+'Parámetros'!L9*C28 -> 0
B18: Costo Equipo | C18: =C35 | E18: Gross Margin | F18: 0.5 | H18: PV USD | I18: =I17/'Parámetros'!L3 -> 0
B19: Costo + Gasto Fijo | C19: =C21+C22+C20 -> 0 | E19: Imp. Renta | F19: =(I17-F17-C22)*'Parámetros'!L6 -> 0 | H19: Horas | I19: 180
B20: Computador Herramientas Trabajo | C20: =6000000/30*C34*1.095 -> 0 | E20: ICA | F20: =I17*'Parámetros'!L5 -> 0 | H20: USD/Horas | I20: =I18/I19 -> 0
B21: - ROP Gasto | C21: =C36*AVERAGE('Parámetros'!G5:G6)*IF(C29=1,15%,1) -> 0 | E21: NET Margin | F21: =(I17-C23-F20-F17-C28*'Parámetros'!L8*I17)/I17 -> #DIV/0!
B22: - ROP Costo Fijo | C22: =C36*AVERAGE('Parámetros'!H5:H6)*IF(C29=1,15%,1) -> 0
B23: T. C + G Equipo | C23: =C18+C19 -> 0
B25: Comisión Bruta | C25: 0.1 | E25: Comisión Venta | F25: =I25*C27 -> 0 | G25: Jugar con Net Margin | H25: PV COP | I25: =+(C23/(1-C27-F26-'Parámetros'!L5-'Parámetros'!L8*C28))+('Parámetros'!L9*C28) -> 0
B26: ¿Tipo de contrato vendedor? | C26: Prestación de Servicios | E26: NET Margin | F26: 0 | H26: PV USD | I26: =I25/'Parámetros'!L3 -> 0
B27: Comisión Total | C27: =IF('Nueva Plantilla'!C26="Nómina",C25*1.38522,C25) -> 0.1 | E27: Imp. Renta | F27: =(I25-F26-C22)*'Parámetros'!L6 -> 0 | H27: Horas | I27: 180
B28: ¿Pago con TC? | C28: 0 | E28: ICA | F28: =I25*'Parámetros'!L5 -> 0 | H28: USD/Horas | I28: =I26/I27 -> 0
B29: ¿Staff Augmentation? | C29: 0
B32: =IFERROR(__xludf.DUMMYFUNCTION("FILTER(#REF!,#REF!=B6)"),"#REF!") -> #REF!
B39: Nivel 2
B41: *Todos los meses cambiar el # de personas actuales - Ojo!
B43: Resumen | E43: Comisión Venta | F43: =I43*C53 -> #REF! | G43: Jugar con Gross Margin | H43: PV COP | I43: =+((C48+C44+C46)/(1-F44-'Parámetros'!L42*C54))+'Parámetros'!L43*C54 -> #REF!
B44: Costo Equipo | C44: =C61 | E44: Gross Margin | F44: 0.5 | H44: PV USD | I44: =I43/'Parámetros'!L30 -> #REF!
B45: Costo + Gasto Fijo | C45: =C47+C48+C46 -> #REF! | E45: Imp. Renta | F45: =(I43-F43-C48)*'Parámetros'!L40 -> #REF! | H45: Horas | I45: 180
B46: Computador Herramientas Trabajo | C46: =6000000/30*C60*1.095 -> 0 | E46: ICA | F46: =I43*'Parámetros'!L39 -> #REF! | H46: USD/Horas | I46: =I44/I45 -> #REF!
B47: - ROP Gasto | C47: =C62*AVERAGE(#REF!)*IF(C55=1,15%,1) -> #REF! | E47: NET Margin | F47: =(I43-C49-F46-F43-C54*'Parámetros'!L42*I43)/I43 -> #REF!
B48: - ROP Costo Fijo | C48: =C62*AVERAGE(#REF!)*IF(C55=1,15%,1) -> #REF!
B49: T. C + G Equipo | C49: =C44+C45 -> #REF!
B51: Comisión Bruta | C51: 0.1 | E51: Comisión Venta | F51: =I51*C53 -> #REF! | G51: Jugar con Net Margin | H51: PV COP | I51: =+(C49/(1-C53-F52-'Parámetros'!L39-'Parámetros'!L42*C54))+('Parámetros'!L43*C54) -> #REF!
B52: ¿Tipo de contrato vendedor? | C52: Prestación de Servicios | E52: NET Margin | F52: 0 | H52: PV USD | I52: =I51/'Parámetros'!L30 -> #REF!
B53: Comisión Total | C53: =IF('Nueva Plantilla'!C52="Nómina",C51*1.38522,C51) -> 0.1 | E53: Imp. Renta | F53: =(I51-F52-C48)*'Parámetros'!L40 -> #REF! | H53: Horas | I53: 180
B54: ¿Pago con TC? | C54: 0 | E54: ICA | F54: =I51*'Parámetros'!L39 -> #REF! | H54: USD/Horas | I54: =I52/I53 -> #REF!
B55: ¿Staff Augmentation? | C55: 0
B58: =B9 -> Caso Express

Sheet Sheet6
C2: Nivel 1 | D2: Nivel 2 | E2: Tiempo
C3: ¿El cliente sabe que quiere? | E3: 3
B4: TRUE | C4: Descubrimiento
C14: Staff Augmentation
C15: Descubrimiento
C16: Desarrollo Express
C17: Dedicated Team
C18: Proyecto Fijo
C19: Soporte

Sheet Copy of PRICING PLANTILLA
C1: Herramienta Pricing | P1: Código: | Q1: FO - FI - 03
P2: Versión: | Q2: 1
P3: Fecha de emisión: | Q3: 44171
B5: *Todos los meses cambiar el # de personas actuales - Ojo! | E5: Comisión Venta | F5: =I5*C17 -> 1471150.6 | G5: Jugar con Gross Margin | H5: PV COP | I5: =+((C12+C8+C10)/(1-F6-'Parámetros'!L8*C18))+'Parámetros'!L9*C18 -> 14711506
E6: Gross Margin | F6: 0.42 | H6: PV USD | I6: =I5/'Parámetros'!L3 -> 4144.0863
B7: Resumen | E7: Imp. Renta | F7: =(I5-F5-C12)*'Parámetros'!L6 -> 0 | H7: Horas | I7: 180
B8: Costo Equipo | C8: =G20 -> 7415802.7 | E8: ICA | F8: =I5*'Parámetros'!L5 -> 101509.39 | H8: USD/Horas | I8: =I6/I7 -> 23.022702
B9: Costo + Gasto Fijo | C9: =C11+C12+C10 -> 4911160.4 | E9: NET Margin | F9: =(I5-C13-F8-F5-C18*'Parámetros'!L8*I5)/I5 -> 0.055186956
B10: Computador Herramientas Trabajo | C10: =6000000/30*F20*1.095 -> 361350
B11: - ROP Gasto | C11: =H20*AVERAGE('Parámetros'!G5:G6)*IF(C19=1,15%,1) -> 3794289.4
B12: - ROP Costo Fijo | C12: =H20*AVERAGE('Parámetros'!H5:H6)*IF(C19=1,15%,1) -> 755521 | E12: Comisión Venta | F12: =I12*C17 -> 1380244.4 | G12: Jugar con Net Margin | H12: PV COP | I12: =+(C13/(1-C17-F13-'Parámetros'!L5-'Parámetros'!L8*C18))+('Parámetros'!L9*C18) -> 13802444
B13: T. C + G Equipo | C13: =C8+C9 -> 12326963 | E13: NET Margin | F13: 0 | H13: PV USD | I13: =I12/'Parámetros'!L3 -> 3888.0125
E14: Imp. Renta | F14: =(I12-F13-C12)*'Parámetros'!L6 -> 0 | H14: Horas | I14: 180
B15: Comisión Bruta | C15: 0.1 | E15: ICA | F15: =I12*'Parámetros'!L5 -> 95236.866 | H15: USD/Horas | I15: =I13/I14 -> 21.600069
B16: ¿Tipo de contrato vendedor? | C16: Prestación de Servicios
B17: Comisión Total | C17: =IF('Copy of PRICING PLANTILLA'!C16="Nómina",C15*1.38522,C15) -> 0.1
B18: ¿Pago con TC? | C18: 0 | F18: Proyectado
B19: ¿Staff Augmentation? | C19: 0
F20: =SUM(F22:F34) -> 1.65 | G20: =SUM(G22:G34) -> 7415802.7 | H20: =SUM(H22:H34) -> 0.021723488
B21: Equipo | C21: Salario Base | D21: Tipo Contrato | E21: Costo Total | F21: Dedicación | G21: Costo Final | H21: % Tiempo Equipo | I21: % Costo Equipo | J21: PV (USD)
B22: Software Developer Junior Nivel 1 | C22: 3000000 | D22: Nómina | E22: =+iferror(IF(D22="Nómina",C22*1.38352,C22),"") -> 4150560 | F22: 1 | G22: =E22*F22+C22/6 -> 4650560 | H22: =G22/(AVERAGE('Parámetros'!$F$5:$F$6)+$G$20) -> 0.013623122 | I22: =G22/$G$20 -> 0.62711485 | J22: =$I$13*I22 -> 2438.2304
B23: Project Analyst Junior | C23: 2800000 | D23: Nómina | E23: =+iferror(IF(D23="Nómina",C23*1.38352,C23),"") -> 3873856 | F23: 0.25 | G23: =E23*F23+C23/6 -> 1435130.7 | H23: =G23/(AVERAGE('Parámetros'!$F$5:$F$6)+$G$20) -> 0.0042040013 | I23: =G23/$G$20 -> 0.19352331 | J23: =$I$13*I23 -> 752.42104
B24: Diseñador Junior | C24: 3000000 | D24: Nómina | E24: =+iferror(IF(D24="Nómina",C24*1.38352,C24),"") -> 4150560 | F24: 0.2 | G24: =E24*F24+C24/6 -> 1330112 | H24: =G24/(AVERAGE('Parámetros'!$F$5:$F$6)+$G$20) -> 0.0038963647 | I24: =G24/$G$20 -> 0.17936184 | J24: =$I$13*I24 -> 697.36107
B25: QA Engineer Junior | C25: =iferror(VLOOKUP(B25,'Parámetros'!A$1:B123,2, FALSE),"") | D25: Nómina | E25: =+iferror(IF(D25="Nómina",C25*1.38352,C25),"") -> 0 | F25: 0.2 | G25: =E25*F25+C25/6 -> 0 | H25: =G25/(AVERAGE('Parámetros'!$F$5:$F$6)+$G$20) -> 0 | I25: =G25/$G$20 -> 0 | J25: =$I$13*I25 -> 0
C26: =iferror(VLOOKUP(B26,'Parámetros'!A$1:B124,2, FALSE),"") | E26: =+iferror(IF(D26="Nómina",C26*1.38352,C26),"") | G26: =E26*F26 -> 0 | H26: =G26/AVERAGE('Parámetros'!$F$5:$F$6) -> 0 | I26: =G26/$G$20 -> 0 | J26: =$I$13*I26 -> 0
C27: =iferror(VLOOKUP(B27,'Parámetros'!A$1:B126,2, FALSE),"") | E27: =+iferror(IF(D27="Nómina",C27*1.38352,C27),"") | G27: =E27*F27 -> 0 | I27: =G27/$G$20 -> 0 | J27: =$I$13*I27 -> 0
C28: =iferror(VLOOKUP(B28,'Parámetros'!A$1:B126,2, FALSE),"") | E28: =+iferror(IF(D28="Nómina",C28*1.38352,C28),"") | G28: =E28*F28 -> 0 | I28: =G28/$G$20 -> 0 | J28: =$I$13*I28 -> 0
C29: =iferror(VLOOKUP(B29,'Parámetros'!A$1:B126,2, FALSE),"") | D29: Nómina | E29: =+iferror(IF(D29="Nómina",C29*1.38352,C29),"") -> 0 | G29: =E29*F29 -> 0 | I29: =G29/$G$20 -> 0 | J29: =$I$13*I29 -> 0
C30: =iferror(VLOOKUP(B30,'Parámetros'!A$1:B126,2, FALSE),"") | E30: =+iferror(IF(D30="Nómina",C30*1.38352,C30),"") | G30: =E30*F30 -> 0 | I30: =G30/$G$20 -> 0 | J30: =$I$13*I30 -> 0
C31: =iferror(VLOOKUP(B31,'Parámetros'!A$1:B126,2, FALSE),"") | E31: =+iferror(IF(D31="Nómina",C31*1.38352,C31),"") | G31: =E31*F31 -> 0 | I31: =G31/$G$20 -> 0 | J31: =$I$13*I31 -> 0
C32: =iferror(VLOOKUP(B32,'Parámetros'!A$1:B126,2, FALSE),"") | E32: =+iferror(IF(D32="Nómina",C32*1.38352,C32),"") | G32: =E32*F32 -> 0 | I32: =G32/$G$20 -> 0 | J32: =$I$13*I32 -> 0
C33: =iferror(VLOOKUP(B33,'Parámetros'!A$1:B126,2, FALSE),"") | E33: =+iferror(IF(D33="Nómina",C33*1.38352,C33),"") | G33: =E33*F33 -> 0 | I33: =G33/$G$20 -> 0 | J33: =$I$13*I33 -> 0
C34: =iferror(VLOOKUP(B34,'Parámetros'!A$1:B126,2, FALSE),"") | D34: Nómina | E34: =+iferror(IF(D34="Nómina",C34*1.38352,C34),"") -> 0 | G34: =E34*F34 -> 0 | I34: =G34/$G$20 -> 0 | J34: =$I$13*I34 -> 0
B36: COP | K36: USD
B37: Pricing | C37: Gross Margin | K37: Pricing | L37: Gross Margin
B39: Perfil | C39: Dedicación | D39: Capacidad Horas | E39: Precio COP | F39: Precio x Hora | K39: Perfil | L39: Dedicación | M39: Capacidad Horas | N39: Precio USD | O39: Precio x Hora
B40: =B22 -> Software Developer Junior Nivel 1 | C40: =F22 -> 1 | D40: =C40*180 -> 180 | E40: =IF(C$37="Gross Margin",I22*$I$5,IF(C$37="Net Margin",I22*$I$12,"Error")) -> 9225804.1 | F40: =iferror(E40/D40,0) -> 51254.467 | K40: =B40 -> Software Developer Junior Nivel 1 | L40: =C40 -> 1 | M40: =D40 -> 180 | N40: =E40/'Parámetros'!$L$3 -> 2598.8181 | O40: =iferror(N40/M40,0) -> 14.437878
B41: =B23 -> Project Analyst Junior | C41: =F23 -> 0.25 | D41: =C41*180 -> 45 | E41: =IF(C$37="Gross Margin",I23*$I$5,IF(C$37="Net Margin",I23*$I$12,"Error")) -> 2847019.4 | F41: =iferror(E41/D41,0) -> 63267.097 | K41: =B41 -> Project Analyst Junior | L41: =C41 -> 0.25 | M41: =D41 -> 45 | N41: =E41/'Parámetros'!$L$3 -> 801.97729 | O41: =iferror(N41/M41,0) -> 17.821718
B42: =B24 -> Diseñador Junior | C42: =F24 -> 0.2 | D42: =C42*180 -> 36 | E42: =IF(C$37="Gross Margin",I24*$I$5,IF(C$37="Net Margin",I24*$I$12,"Error")) -> 2638682.8 | F42: =iferror(E42/D42,0) -> 73296.745 | K42: =B42 -> Diseñador Junior | L42: =C42 -> 0.2 | M42: =D42 -> 36 | N42: =E42/'Parámetros'!$L$3 -> 743.29094 | O42: =iferror(N42/M42,0) -> 20.64697
B43: =B25 -> QA Engineer Junior | C43: =F25 -> 0.2 | D43: =C43*180 -> 36 | E43: =IF(C$37="Gross Margin",I25*$I$5,IF(C$37="Net Margin",I25*$I$12,"Error")) -> 0 | F43: =iferror(E43/D43,0) -> 0 | K43: =B43 -> QA Engineer Junior | L43: =C43 -> 0.2 | M43: =D43 -> 36 | N43: =E43/'Parámetros'!$L$3 -> 0 | O43: =iferror(N43/M43,0) -> 0
B44: =B26 | C44: =F26 | D44: =C44*180 -> 0 | E44: =IF(C$37="Gross Margin",I26*$I$5,IF(C$37="Net Margin",I26*$I$12,"Error")) -> 0 | F44: =iferror(E44/D44,0) -> 0 | K44: =B44 | L44: =C44 | M44: =D44 -> 0 | N44: =E44/'Parámetros'!$L$3 -> 0 | O44: =iferror(N44/M44,0) -> 0
B45: =B27 | C45: =F27 | D45: =C45*180 -> 0 | E45: =IF(C$37="Gross Margin",I27*$I$5,IF(C$37="Net Margin",I27*$I$12,"Error")) -> 0 | F45: =iferror(E45/D45,0) -> 0 | K45: =B45 | L45: =C45 | M45: =D45 -> 0 | N45: =E45/'Parámetros'!$L$3 -> 0 | O45: =iferror(N45/M45,0) -> 0
B46: =B28 | C46: =F28 | D46: =C46*180 -> 0 | E46: =IF(C$37="Gross Margin",I28*$I$5,IF(C$37="Net Margin",I28*$I$12,"Error")) -> 0 | F46: =iferror(E46/D46,0) -> 0 | K46: =B46 | L46: =C46 | M46: =D46 -> 0 | N46: =E46/'Parámetros'!$L$3 -> 0 | O46: =iferror(N46/M46,0) -> 0
B47: =B29 | C47: =F29 | D47: =C47*180 -> 0 | E47: =IF(C$37="Gross Margin",I29*$I$5,IF(C$37="Net Margin",I29*$I$12,"Error")) -> 0 | F47: =iferror(E47/D47,0) -> 0 | K47: =B47 | L47: =C47 | M47: =D47 -> 0 | N47: =E47/'Parámetros'!$L$3 -> 0 | O47: =iferror(N47/M47,0) -> 0
B48: =B30 | C48: =F30 | D48: =C48*180 -> 0 | E48: =IF(C$37="Gross Margin",I30*$I$5,IF(C$37="Net Margin",I30*$I$12,"Error")) -> 0 | F48: =iferror(E48/D48,0) -> 0 | K48: =B48 | L48: =C48 | M48: =D48 -> 0 | N48: =E48/'Parámetros'!$L$3 -> 0 | O48: =iferror(N48/M48,0) -> 0
C49: Total | D49: =SUM(D40:D45) -> 297 | E49: =SUM(E40:E48) -> 14711506 | F49: =E49/D49 -> 49533.691 | L49: Total | M49: =SUM(M40:M45) -> 297 | N49: =SUM(N40:N45) -> 4144.0863 | O49: =N49/M49 -> 13.953152

Sheet Copy Pricing 
B1: LOGO | D1: Herramienta Pricing | N1: Código: | O1: FO - FI - 03
N2: Versión: | O2: 1
N3: Fecha de emisión: | O3: 44171
C4: 3600
C5: Rubros | G5: =SUM(G7:G15) -> 3.45 | H5: =SUM(H7:H15) -> 12329706 | J5: Parámetros | M5: Resumen
C6: Cargo | D6: Salario | E6: Tipo de Contrato | F6: Valor Total | G6: Factor | H6: Valor Total 2 | J6: TRM | K6: 3980 | M6: Costo Equipo | N6: =H5 -> 12329706
A7: =$N$17*B7 -> #REF! | B7: =H7/$H$5 -> 0.048662962 | C7: PM Jr | D7: 2400000 | E7: P. Servicios | F7: =+IF(E7="Nómina",D7*1.38322,D7) -> 2400000 | G7: 0.25 | H7: =F7*G7 -> 600000 | J7: Tasa Comisión Ventas | K7: 0.1 | M7: Licenciamiento | N7: =+SUM(D17)/$K$11*$G$5 -> 501915.97
A8: =$N$17*B8 -> #REF! | B8: =H8/$H$5 -> 0.22437194 | C8: PM Sr | D8: 4000000 | E8: Nómina | F8: =+IF(E8="Nómina",D8*1.38322,D8) -> 5532880 | G8: 0.5 | H8: =F8*G8 -> 2766440 | J8: # Proyectos x Pod | K8: 1 | M8: Mercadeo & Ventas | N8: =+SUM(E19:E20)/$K$11*$G$5 -> #REF!
A9: =$N$17*B9 -> #REF! | B9: =H9/$H$5 -> 0.26924633 | C9: Diseñador Jr | D9: 2400000 | E9: Nómina | F9: =+IF(E9="Nómina",D9*1.38322,D9) -> 3319728 | G9: 1 | H9: =F9*G9 -> 3319728 | J9: ICA | K9: =6.9/1000 -> 0.0069 | M9: Administración | N9: =+SUM(D23:D28)/$K$11*$G$5 -> 971245.87
A10: =$N$17*B10 -> #REF! | B10: =H10/$H$5 -> 0.26924633 | C10: Diseñador S Sr. | D10: 2400000 | E10: Nómina | F10: =+IF(E10="Nómina",D10*1.38322,D10) -> 3319728 | G10: 1 | H10: =F10*G10 -> 3319728 | J10: Renta | K10: 0 | M10: Financiero | N10: =+D31/$K$11*$G$5 -> 179161.21
A11: =$N$17*B11 -> #REF! | B11: =H11/$H$5 -> 0.026924633 | C11: Diseñador Sr. | D11: 2400000 | E11: Nómina | F11: =+IF(E11="Nómina",D11*1.38322,D11) -> 3319728 | G11: 0.1 | H11: =F11*G11 -> 331972.8 | J11: Personas Oper. | K11: 45 | M11: Total Costos x Pod | N11: =SUM(N6:N10) -> #REF!
A12: =$N$17*B12 -> #REF! | B12: =H12/$H$5 -> 0.053849266 | C12: Desarrollador Jr | D12: 2400000 | E12: Nómina | F12: =+IF(E12="Nómina",D12*1.38322,D12) -> 3319728 | G12: 0.2 | H12: =F12*G12 -> 663945.6
C13: Desarrollador S Sr. | D13: 2400000 | E13: Nómina | F13: =+IF(E13="Nómina",D13*1.38322,D13) -> 3319728 | G13: 0.2 | H13: =F13*G13 -> 663945.6
C14: Desarrollador S Sr. | D14: 2400000 | E14: Nómina | F14: =+IF(E14="Nómina",D14*1.38322,D14) -> 3319728 | G14: 0.2 | H14: =F14*G14 -> 663945.6 | M14: Costo Equipo | N14: =N11 -> #REF!
C16: Licenciamiento | J16: Comisión Venta | K16: =N16*K7 -> #REF! | L16: Jugar con Net Margin | M16: Precio de Venta | N16: =+(N14/(1-K7-K17)) -> #REF!
C17: Promedio Ene - Abr 21 | D17: 6546730 | J17: Margin EBIT | K17: 0.2 | M17: Precio de Venta USD | N17: =+N16/$K$6 -> #REF! | O17: =N17*6 -> #REF!
B18: Mercadeo | C18: Mercadeo & Ventas | E18: Total | J18: Impuesto a la Renta | K18: =(N16-K16-N14)*K10 -> #REF! | M18: Horas | N18: 682
B19: Ventas | C19: Promedio Ene - Abr 21 | E19: =Pricing!E18 -> #REF! | J19: ICA | K19: =N16*K9 -> #REF! | M19: USD/Horas | N19: =N17/N18 -> #REF!
C20: Promedio Ene - Abr 21 | E20: =Pricing!E19 -> #REF! | F20: *Excluye comisiones y Consultores de ventas (SUM y Sapper) | J20: NET Margin | K20: =(N16-N14-K18-K19-K16)/N16 -> #REF!
C22: Administración | L22: Jugar con PV | M22: PV USD | N22: =+K24/$K$6 -> 4522.6131
C23: Promedio Ene - Abr 21 | D23: 12668424 | J23: Comisión Venta | K23: =K24*K7 -> 1800000
J24: Precio de Venta COP | K24: 18000000 | M24: Precio Equipo | N24: =K24*K8 -> 18000000
J26: Impuesto a la Renta | K26: =((1-K7)*K24-N14)*K10 -> #REF! | M26: Margin EBIT | N26: =(K24-K23-N14)/K24 -> #REF!
J27: Rete ICA | K27: =K24*K9 -> 124200
M28: NET Margin | N28: =(K24-N14-K18-K19-K16)/K24 -> #REF!
C31: Financieros | D31: 2336885.4
C34: Perfil | D34: Dedicación | E34: Capacidad Horas | F34: Precio
C35: Project Manager | D35: 0.25 | E35: =192*D35 -> 48 | F35: 376.23899
C36: Dev Sr Angular / Node | D36: 0.5 | E36: =192*D36 -> 96 | F36: 1254.13
C37: Dev Jr Angular | D37: 1 | E37: =192*D37 -> 192 | F37: 1504.956
C38: Dev Jr Angular | D38: 1 | E38: =192*D38 -> 192 | F38: 1504.956
C39: Diseñador UX/UI | D39: 0.1 | E39: =192*D39 -> 19.2 | F39: 150.4956
C40: Ingeniero QA | D40: 0.2 | E40: =192*D40 -> 38.4 | F40: 300.99119
D41: Total | E41: =SUM(E35:E40) -> 585.6 | F41: =SUM(F35:F40) -> 5091.7677
